Workbook

Sheet Leesmij
A1: Hypotheek-toetsmodel 2026
A2: Onafhankelijk Excel-model van de leencapaciteitstoets (Nibud-woonquote, toetsrente, studieschuld, meenemen van bestaande leningdelen) om de hypotheekcalculator mee te controleren.
A4: Doel
A5: Dit werkboek rekent dezelfde toets als de app, maar volledig met cel-formules. U voert een dossier in (Invoer, kolom C of M), leest de uitkomst in Samenvatting en vergelijkt desgewenst met de app (Controle).
A7: Werkbladen
A8: Samenvatting: opbouw van de leencapaciteit en de uitkomst voor het gekozen scenario (cel C4).
A9: Invoer: alle invoer per scenario. Gele cellen met blauwe tekst zijn invoer. Kolom C = uw dossier, D t/m L = testscenario's, M = vrij testscenario.
A10: Berekening: stap voor stap, alles formules. Groene vakken zijn sleutelresultaten.
A11: Solver: bepaalt het hoogste bedrag nieuw geld bij meenemen, waarbij de woonquote meebeweegt met de gewogen toetsrente.
A12: Tabellen: parameters en de woonquote-tabellen. Oranje kolommen zijn GESCHAT (zie hieronder) en kunnen worden overschreven.
A13: Controle: Excel-uitkomst naast de uitkomst van de app-engine voor de testscenario's, met verschil en status.
A14: Bronnen: wat is geverifieerd, wat niet, en hoe zeker.
... A32: Indicatief; geen bindend advies. Peildatum scenario's: 8 oktober 2026.

Sheet Samenvatting
A1: Samenvatting: wat kunt u lenen?
A2: Kies een scenario (1 t/m 11). Alle cijfers komen uit de berekening; scenario 1 is uw eigen dossier.
A4: Gekozen scenario | C4: 1
A6: Scenario
A7: Naam | C7: =INDEX(Invoer!$C$6:$M$6,$C$4) -> Mijn dossier
A8: Type | C8: =IF(INDEX(Berekening!$C$6:$M$6,$C$4)=1,"Doorstromer","Starter") -> Doorstromer
A9: Opbouw van de leencapaciteit
A10: Leencapaciteit op inkomen (woonquote × inkomen, gekapitaliseerd) | C10: =INDEX(Berekening!$C$83:$M$83,$C$4) -> 1056874.5
A11: − Schulden en tweede woning | C11: =-MIN(INDEX(Berekening!$C$18:$M$18,$C$4)*INDEX(Berekening!$C$11:$M$11,$C$4),INDEX(Berekening!$C$83:$M$83,$C$4)) -> -37286.07
A12: − Studieschuld | C12: =-MIN(INDEX(Berekening!$C$75:$M$75,$C$4),INDEX(Berekening!$C$84:$M$84,$C$4)) -> -80110.119
A13: ± Correctie (ondergrens € 0; normaal 0) | C13: =C17-(C10+C11+C12+C14+C15+C16) -> 0
A14: ± AOW-toets (pensioeninkomen bindend) | C14: =INDEX(Berekening!$C$100:$M$100,$C$4)-INDEX(Berekening!$C$85:$M$85,$C$4) -> 0
A15: + Energielabelbonus | C15: =INDEX(Berekening!$C$87:$M$87,$C$4) -> 10000
A16: + Alleenstaandenbedrag | C16: =INDEX(Berekening!$C$86:$M$86,$C$4) -> 0
A17: Maximale hypotheek o.b.v. inkomen (alles tegen de toetsrente) | C17: =INDEX(Berekening!$C$101:$M$101,$C$4) -> 949478.28
A18: − Toetslast meegenomen leningdelen (omgerekend in euro's) | C18: =-IF(INDEX(Berekening!$C$47:$M$47,$C$4)=1,INDEX(Berekening!$C$44:$M$44,$C$4)*INDEX(Berekening!$C$11:$M$11,$C$4),0) -> -555976.31
A19: ± Woonquote bij gewogen toetsrente en overig (restpost) | C19: =C20-(C17+C18) -> -65149.796
A20: Ruimte voor nieuw geld (inkomen) | C20: =INDEX(Berekening!$C$105:$M$105,$C$4) -> 328352.17
A21: − Plafond geldverstrekker (alleen als dat lager is) | C21: =C22-C20 -> 0
A22: Maximaal nieuw te lenen | C22: =INDEX(Berekening!$C$118:$M$118,$C$4) -> 328352.17
A23: Uitkomst
A24: Maximale totale hypotheek | C24: =INDEX(Berekening!$C$117:$M$117,$C$4) -> 952102.08
A25: waarvan meegenomen (al geleend) | C25: =INDEX(Berekening!$C$43:$M$43,$C$4) -> 623749.91
A26: Nieuw geld nodig voor de aankoopprijs | C26: =INDEX(Berekening!$C$119:$M$119,$C$4) -> 323980
A27: Ruimte (+) of tekort (−) | C27: =INDEX(Berekening!$C$120:$M$120,$C$4) -> 4372.1704
A28: Haalbaar? | C28: =IF(INDEX(Berekening!$C$122:$M$122,$C$4)=1,"Ja, deze woning past","Nee, deze woning past nog niet") -> Ja, deze woning past
A29: Kerngetallen
A30: Totaal toetsinkomen | C30: =INDEX(Berekening!$C$9:$M$9,$C$4) -> 225000
A31: Toetsrente nieuw geld | C31: =INDEX(Berekening!$C$10:$M$10,$C$4) -> 0.0469
A32: Woonquote bij de toetsrente van het nieuwe geld | C32: =INDEX(Berekening!$C$81:$M$81,$C$4) -> 0.292
A33: Gewogen toetsrente nieuwe hypotheek bij het maximum | C33: =INDEX(Berekening!$C$107:$M$107,$C$4) -> 0.036487604
A34: Opslagfactor studieschuld | C34: =INDEX(Berekening!$C$71:$M$71,$C$4) -> 1.25
A35: Kosten koper | C35: =INDEX(Berekening!$C$56:$M$56,$C$4) -> 32230
A36: Overgebleven budget na woning en kosten koper | C36: =INDEX(Berekening!$C$123:$M$123,$C$4) -> 4372.1704

Sheet Invoer
A1: Invoer
A2: Vul alleen de gele cellen met blauwe tekst in. Kolom C is uw eigen dossier; D t/m L zijn testscenario's met bekende app-uitkomst; M is een vrij testscenario.
A4: Scenario | B4: Eenheid | C4: 1 | D4: 2 | E4: 3 | F4: 4 | G4: 5 | H4: 6 | I4: 7 | J4: 8 | K4: 9 | L4: 10 | M4: 11
A5: Algemeen
A6: Naam scenario | C6: Mijn dossier | D6: Plafond € 1,5 mln, 30 jaar toetsloptijd | E6: Deel 2 slechts 10 jaar rentevast | F6: Nieuwe hypotheek 5 jaar rentevast | G6: Starter, 1 aanvrager € 60k | H6: Starter, 2 aanvragers, studieschuld | I6: Doorstromer, hypotheek niet meenemen | J6: AOW-toets bindend (leeftijd 60) | K6: 3 delen, 2e woning 5 jaar vast, schulden | L6: Hoge schuld: ondergrens € 0 | M6: Eigen test
A7: Doorstromer (bestaande woning)? | B7: Ja/Nee | C7: Ja | D7: Ja | E7: Ja | F7: Ja | G7: Nee | H7: Nee | I7: Ja | J7: Ja | K7: Ja | L7: Ja | M7: Ja
A8: Twee aanvragers? | B8: Ja/Nee | C8: Ja | D8: Ja | E8: Ja | F8: Ja | G8: Nee | H8: Ja | I8: Ja | J8: Ja | K8: Ja | L8: Ja | M8: Ja
A9: Inkomen en leeftijd
A10: Toetsinkomen aanvrager 1 | B10: € per jaar | C10: 118000 | D10: 118000 | E10: 118000 | F10: 118000 | G10: 60000 | H10: 80000 | I10: 118000 | J10: 118000 | K10: 118000 | L10: 118000 | M10: 118000
A11: Toetsinkomen aanvrager 2 | B11: € per jaar | C11: 107000 | D11: 107000 | E11: 107000 | F11: 107000 | G11: 0 | H11: 70000 | I11: 107000 | J11: 107000 | K11: 107000 | L11: 107000 | M11: 107000
A12: Leeftijd aanvrager 1 | B12: jaar | C12: 36 | D12: 36 | E12: 36 | F12: 36 | G12: 30 | H12: 31 | I12: 36 | J12: 60 | K12: 36 | L12: 36 | M12: 36
A13: Leeftijd aanvrager 2 | B13: jaar | C13: 36 | D13: 36 | E13: 36 | F13: 36 | G13: 36 | H13: 29 | I13: 36 | J13: 36 | K13: 36 | L13: 36 | M13: 36
A14: Verwacht pensioeninkomen aanvrager 1 (bij ≥ 57 jaar) | B14: € per jaar | C14: 0 | D14: 0 | E14: 0 | F14: 0 | G14: 0 | H14: 0 | I14: 0 | J14: 40000 | K14: 0 | L14: 0 | M14: 0
A15: Verwacht pensioeninkomen aanvrager 2 (bij ≥ 57 jaar) | B15: € per jaar | C15: 0 | D15: 0 | E15: 0 | F15: 0 | G15: 0 | H15: 0 | I15: 0 | J15: 0 | K15: 0 | L15: 0 | M15: 0
A16: Energielabel woning | B16: label | C16: A | D16: A | E16: A | F16: A | G16: C | H16: B | I16: A | J16: A | K16: G | L16: A | M16: A
A17: Nieuwe hypotheek
A18: Rente nieuwe hypotheek | B18: % per jaar | C18: 0.0469 | D18: 0.0469 | E18: 0.0469 | F18: 0.0469 | G18: 0.0469 | H18: 0.0469 | I18: 0.0469 | J18: 0.0469 | K18: 0.0469 | L18: 0.0469 | M18: 0.0469
A19: Rentevaste periode nieuwe hypotheek | B19: jaar | C19: 10 | D19: 10 | E19: 10 | F19: 5 | G19: 10 | H19: 10 | I19: 10 | J19: 10 | K19: 10 | L19: 10 | M19: 10
A20: Aankoopprijs beoogde woning | B20: € | C20: 1330000 | D20: 1330000 | E20: 1330000 | F20: 1330000 | G20: 400000 | H20: 650000 | I20: 1330000 | J20: 1330000 | K20: 1100000 | L20: 1330000 | M20: 1330000
A21: Plafond totale hypotheek bij geldverstrekker | B21: € | C21: 1000000 | D21: 1500000 | E21: 1000000 | F21: 1000000 | G21: 1000000 | H21: 1000000 | I21: 1000000 | J21: 1000000 | K21: 1000000 | L21: 1000000 | M21: 1000000
A22: Schulden en lasten
A23: Overige schulden aanvrager 1 (kredietbedrag) | B23: € | C23: 0 | D23: 0 | E23: 0 | F23: 0 | G23: 0 | H23: 0 | I23: 0 | J23: 0 | K23: 15000 | L23: 3000000 | M23: 0
A24: Overige schulden aanvrager 2 (kredietbedrag) | B24: € | C24: 0 | D24: 0 | E24: 0 | F24: 0 | G24: 0 | H24: 0 | I24: 0 | J24: 0 | K24: 8000 | L24: 0 | M24: 0
A25: Maandelijkse aflossing familielening | B25: € per maand | C25: 0 | D25: 0 | E25: 0 | F25: 0 | G25: 0 | H25: 0 | I25: 0 | J25: 0 | K25: 250 | L25: 0 | M25: 0
A26: Studieschuld: totaal maandbedrag DUO (alle leningen) | B26: € per maand | C26: 332 | D26: 332 | E26: 332 | F26: 332 | G26: 0 | H26: 120 | I26: 332 | J26: 332 | K26: 332 | L26: 332 | M26: 332
A27: Studieschuld: debetrente voor opslagfactor | B27: keuze | C27: Gewogen toetsrente | D27: Gewogen toetsrente | E27: Gewogen toetsrente | F27: Gewogen toetsrente | G27: Gewogen toetsrente | H27: Gewogen toetsrente | I27: Gewogen toetsrente | J27: Gewogen toetsrente | K27: Contractrente | L27: Gewogen toetsrente | M27: Gewogen toetsrente
A28: Studieschuld: kapitaliseren tegen | B28: keuze | C28: Marginaal | D28: Marginaal | E28: Marginaal | F28: Marginaal | G28: Marginaal | H28: Gewogen | I28: Marginaal | J28: Marginaal | K28: Marginaal | L28: Marginaal | M28: Marginaal
A29: Tweede woning (aanhouden)
A30: Tweede woning met hypotheek aanhouden? | B30: Ja/Nee | C30: Ja | D30: Ja | E30: Ja | F30: Ja | G30: Nee | H30: Nee | I30: Ja | J30: Nee | K30: Ja | L30: Nee | M30: Ja
A31: Hypotheekschuld tweede woning | B31: € | C31: 42000 | D31: 42000 | E31: 42000 | F31: 42000 | G31: 42000 | H31: 42000 | I31: 42000 | J31: 42000 | K31: 42000 | L31: 42000 | M31: 42000
A32: Rente tweede woning | B32: % per jaar | C32: 0.01 | D32: 0.01 | E32: 0.01 | F32: 0.01 | G32: 0.01 | H32: 0.01 | I32: 0.01 | J32: 0.01 | K32: 0.01 | L32: 0.01 | M32: 0.01
A33: Aflosvorm tweede woning | B33: keuze | C33: Annuïteit | D33: Annuïteit | E33: Annuïteit | F33: Annuïteit | G33: Annuïteit | H33: Annuïteit | I33: Annuïteit | J33: Annuïteit | K33: Aflossingsvrij | L33: Annuïteit | M33: Annuïteit
A34: Resterende looptijd tweede woning | B34: jaar | C34: 20 | D34: 20 | E34: 20 | F34: 20 | G34: 20 | H34: 20 | I34: 20 | J34: 20 | K34: 20 | L34: 20 | M34: 20
A35: Resterende rentevaste periode tweede woning | B35: jaar | C35: 10 | D35: 10 | E35: 10 | F35: 10 | G35: 10 | H35: 10 | I35: 10 | J35: 10 | K35: 5 | L35: 10 | M35: 10
A36: Bestaande hypotheek (alleen doorstromer)
A37: Hypotheek meenemen naar de nieuwe woning? | B37: Ja/Nee | C37: Ja | D37: Ja | E37: Ja | F37: Ja | G37: Ja | H37: Ja | I37: Nee | J37: Ja | K37: Ja | L37: Ja | M37: Ja
A38: Looptijd voor toetslast meegenomen delen | B38: keuze | C38: Resterend | D38: 30 jaar | E38: Resterend | F38: Resterend | G38: Resterend | H38: Resterend | I38: Resterend | J38: Resterend | K38: Resterend | L38: Resterend | M38: Resterend
A39: Ingangsdatum hypotheek | B39: datum | C39: 44211 | D39: 44211 | E39: 44211 | F39: 44211 | G39: 44211 | H39: 44211 | I39: 44211 | J39: 44211 | K39: 44211 | L39: 44211 | M39: 44211
A40: Peildatum (restsaldi) | B40: datum | C40: 46303 | D40: 46303 | E40: 46303 | F40: 46303 | G40: 46303 | H40: 46303 | I40: 46303 | J40: 46303 | K40: 46303 | L40: 46303 | M40: 46303
A41: Leningdeel 1
A42: Deel 1: aflosvorm | B42: keuze | C42: Annuïteit | D42: Annuïteit | E42: Annuïteit | F42: Annuïteit | G42: Annuïteit | H42: Annuïteit | I42: Annuïteit | J42: Annuïteit | K42: Lineair | L42: Annuïteit | M42: Annuïteit
A43: Deel 1: restsaldo op peildatum | B43: € | C43: 269480.64 | D43: 269480.64 | E43: 269480.64 | F43: 269480.64 | G43: 269480.64 | H43: 269480.64 | I43: 269480.64 | J43: 269480.64 | K43: 180000 | L43: 269480.64 | M43: 269480.64
A44: Deel 1: contractrente | B44: % per jaar | C44: 0.0125 | D44: 0.0125 | E44: 0.0125 | F44: 0.0125 | G44: 0.0125 | H44: 0.0125 | I44: 0.0125 | J44: 0.0125 | K44: 0.021 | L44: 0.0125 | M44: 0.0125
A45: Deel 1: oorspronkelijke rentevaste periode | B45: jaar | C45: 10 | D45: 10 | E45: 10 | F45: 10 | G45: 10 | H45: 10 | I45: 10 | J45: 10 | K45: 12 | L45: 10 | M45: 10
A46: Leningdeel 2
A47: Deel 2: aflosvorm | B47: keuze | C47: Aflossingsvrij | D47: Aflossingsvrij | E47: Aflossingsvrij | F47: Aflossingsvrij | G47: Aflossingsvrij | H47: Aflossingsvrij | I47: Aflossingsvrij | J47: Aflossingsvrij | K47: Annuïteit | L47: Aflossingsvrij | M47: Aflossingsvrij
A48: Deel 2: restsaldo op peildatum | B48: € | C48: 354269.27 | D48: 354269.27 | E48: 354269.27 | F48: 354269.27 | G48: 354269.27 | H48: 354269.27 | I48: 354269.27 | J48: 354269.27 | K48: 220000 | L48: 354269.27 | M48: 354269.27
A49: Deel 2: contractrente | B49: % per jaar | C49: 0.0185 | D49: 0.0185 | E49: 0.0185 | F49: 0.0185 | G49: 0.0185 | H49: 0.0185 | I49: 0.0185 | J49: 0.0185 | K49: 0.034 | L49: 0.0185 | M49: 0.0185
A50: Deel 2: oorspronkelijke rentevaste periode | B50: jaar | C50: 20 | D50: 20 | E50: 10 | F50: 20 | G50: 20 | H50: 20 | I50: 20 | J50: 20 | K50: 5 | L50: 20 | M50: 20
A51: Leningdeel 3
A52: Deel 3: aflosvorm | B52: keuze | C52: Annuïteit | D52: Annuïteit | E52: Annuïteit | F52: Annuïteit | G52: Annuïteit | H52: Annuïteit | I52: Annuïteit | J52: Annuïteit | K52: Aflossingsvrij | L52: Annuïteit | M52: Annuïteit
A53: Deel 3: restsaldo op peildatum | B53: € | C53: 0 | D53: 0 | E53: 0 | F53: 0 | G53: 0 | H53: 0 | I53: 0 | J53: 0 | K53: 150000 | L53: 0 | M53: 0
A54: Deel 3: contractrente | B54: % per jaar | C54: 0.03 | D54: 0.03 | E54: 0.03 | F54: 0.03 | G54: 0.03 | H54: 0.03 | I54: 0.03 | J54: 0.03 | K54: 0.0485 | L54: 0.03 | M54: 0.03
A55: Deel 3: oorspronkelijke rentevaste periode | B55: jaar | C55: 10 | D55: 10 | E55: 10 | F55: 10 | G55: 10 | H55: 10 | I55: 10 | J55: 10 | K55: 3 | L55: 10 | M55: 10
A56: Leningdeel 4
A57: Deel 4: aflosvorm | B57: keuze | C57: Annuïteit | D57: Annuïteit | E57: Annuïteit | F57: Annuïteit | G57: Annuïteit | H57: Annuïteit | I57: Annuïteit | J57: Annuïteit | K57: Annuïteit | L57: Annuïteit | M57: Annuïteit
A58: Deel 4: restsaldo op peildatum | B58: € | C58: 0 | D58: 0 | E58: 0 | F58: 0 | G58: 0 | H58: 0 | I58: 0 | J58: 0 | K58: 0 | L58: 0 | M58: 0
A59: Deel 4: contractrente | B59: % per jaar | C59: 0.03 | D59: 0.03 | E59: 0.03 | F59: 0.03 | G59: 0.03 | H59: 0.03 | I59: 0.03 | J59: 0.03 | K59: 0.03 | L59: 0.03 | M59: 0.03
A60: Deel 4: oorspronkelijke rentevaste periode | B60: jaar | C60: 10 | D60: 10 | E60: 10 | F60: 10 | G60: 10 | H60: 10 | I60: 10 | J60: 10 | K60: 10 | L60: 10 | M60: 10
A61: Woning, eigen geld en kosten koper
A62: Marktwaarde huidige woning | B62: € | C62: 935000 | D62: 935000 | E62: 935000 | F62: 935000 | G62: 935000 | H62: 935000 | I62: 935000 | J62: 935000 | K62: 900000 | L62: 935000 | M62: 935000
A63: Verkoopwaarde als % van marktwaarde (voorzichtig) | B63: % | C63: 0.95 | D63: 0.95 | E63: 0.95 | F63: 0.95 | G63: 0.95 | H63: 0.95 | I63: 0.95 | J63: 0.95 | K63: 0.95 | L63: 0.95 | M63: 0.95
A64: Eigen geld (liquide) voor de aankoop | B64: € | C64: 150000 | D64: 150000 | E64: 150000 | F64: 150000 | G64: 40000 | H64: 60000 | I64: 150000 | J64: 150000 | K64: 90000 | L64: 150000 | M64: 150000
A65: Overdrachtsbelasting | B65: % koopsom | C65: 0.02 | D65: 0.02 | E65: 0.02 | F65: 0.02 | G65: 0.02 | H65: 0 | I65: 0.02 | J65: 0.02 | K65: 0.02 | L65: 0.02 | M65: 0.02
A66: Notaris | B66: € | C66: 1200 | D66: 1200 | E66: 1200 | F66: 1200 | G66: 1200 | H66: 1200 | I66: 1200 | J66: 1200 | K66: 1200 | L66: 1200 | M66: 1200
A67: Taxatie | B67: € | C67: 600 | D67: 600 | E67: 600 | F67: 600 | G67: 600 | H67: 600 | I67: 600 | J67: 600 | K67: 600 | L67: 600 | M67: 600
A68: Hypotheekadvies en bemiddeling | B68: € | C68: 2500 | D68: 2500 | E68: 2500 | F68: 2500 | G68: 2500 | H68: 2500 | I68: 2500 | J68: 2500 | K68: 2500 | L68: 2500 | M68: 2500
A69: Bankgarantie meenemen? | B69: Ja/Nee | C69: Ja | D69: Ja | E69: Ja | F69: Ja | G69: Ja | H69: Ja | I69: Ja | J69: Ja | K69: Ja | L69: Ja | M69: Ja
A70: Aankoopmakelaar meenemen? | B70: Ja/Nee | C70: Nee | D70: Nee | E70: Nee | F70: Nee | G70: Nee | H70: Nee | I70: Nee | J70: Nee | K70: Nee | L70: Nee | M70: Nee
A71: Kosten koper meetellen in de toets? | B71: Ja/Nee | C71: Ja | D71: Ja | E71: Ja | F71: Ja | G71: Ja | H71: Ja | I71: Ja | J71: Ja | K71: Ja | L71: Ja | M71: Ja

Sheet Berekening
A1: Berekening
A2: Alle cellen zijn formules. Opbouw per scenariokolom; groen = sleutelresultaat. Rente-invoer staat als fractie (4,00% = 0,04).
A4: Stap | B4: Eenheid | C4: =Invoer!C4 -> 1 | D4: =Invoer!D4 -> 2 | E4: =Invoer!E4 -> 3 | F4: =Invoer!F4 -> 4 | G4: =Invoer!G4 -> 5 | H4: =Invoer!H4 -> 6 | I4: =Invoer!I4 -> 7 | J4: =Invoer!J4 -> 8 | ... M4: =Invoer!M4 -> 11
A5: 1. Uitgangspunten
A6: Doorstromer (1 = ja) | C6: =IF(Invoer!C7="Ja",1,0) -> 1 | D6: =IF(Invoer!D7="Ja",1,0) -> 1 | E6: =IF(Invoer!E7="Ja",1,0) -> 1 | F6: =IF(Invoer!F7="Ja",1,0) -> 1 | G6: =IF(Invoer!G7="Ja",1,0) -> 0 | H6: =IF(Invoer!H7="Ja",1,0) -> 0 | I6: =IF(Invoer!I7="Ja",1,0) -> 1 | J6: =IF(Invoer!J7="Ja",1,0) -> 1 | ... M6: =IF(Invoer!M7="Ja",1,0) -> 1
A7: Twee aanvragers (1 = ja) | C7: =IF(Invoer!C8="Ja",1,0) -> 1 | D7: =IF(Invoer!D8="Ja",1,0) -> 1 | E7: =IF(Invoer!E8="Ja",1,0) -> 1 | F7: =IF(Invoer!F8="Ja",1,0) -> 1 | G7: =IF(Invoer!G8="Ja",1,0) -> 0 | H7: =IF(Invoer!H8="Ja",1,0) -> 1 | I7: =IF(Invoer!I8="Ja",1,0) -> 1 | J7: =IF(Invoer!J8="Ja",1,0) -> 1 | ... M7: =IF(Invoer!M8="Ja",1,0) -> 1
A8: Hypotheek wordt meegenomen (1 = ja) | C8: =C6*IF(Invoer!C37="Ja",1,0) -> 1 | D8: =D6*IF(Invoer!D37="Ja",1,0) -> 1 | E8: =E6*IF(Invoer!E37="Ja",1,0) -> 1 | F8: =F6*IF(Invoer!F37="Ja",1,0) -> 1 | G8: =G6*IF(Invoer!G37="Ja",1,0) -> 0 | H8: =H6*IF(Invoer!H37="Ja",1,0) -> 0 | I8: =I6*IF(Invoer!I37="Ja",1,0) -> 0 | J8: =J6*IF(Invoer!J37="Ja",1,0) -> 1 | ... M8: =M6*IF(Invoer!M37="Ja",1,0) -> 1
A9: Totaal toetsinkomen | B9: € | C9: =Invoer!C10+C7*Invoer!C11 -> 225000 | D9: =Invoer!D10+D7*Invoer!D11 -> 225000 | E9: =Invoer!E10+E7*Invoer!E11 -> 225000 | F9: =Invoer!F10+F7*Invoer!F11 -> 225000 | G9: =Invoer!G10+G7*Invoer!G11 -> 60000 | H9: =Invoer!H10+H7*Invoer!H11 -> 150000 | I9: =Invoer!I10+I7*Invoer!I11 -> 225000 | J9: =Invoer!J10+J7*Invoer!J11 -> 225000 | ... M9: =Invoer!M10+M7*Invoer!M11 -> 225000
A10: Toetsrente nieuwe hypotheek | B10: % | C10: =IF(AND(Invoer!C19<10,AFM_Toetsrente>Invoer!C18),AFM_Toetsrente,Invoer!C18) -> 0.0469 | D10: =IF(AND(Invoer!D19<10,AFM_Toetsrente>Invoer!D18),AFM_Toetsrente,Invoer!D18) -> 0.0469 | E10: =IF(AND(Invoer!E19<10,AFM_Toetsrente>Invoer!E18),AFM_Toetsrente,Invoer!E18) -> 0.0469 | F10: =IF(AND(Invoer!F19<10,AFM_Toetsrente>Invoer!F18),AFM_Toetsrente,Invoer!F18) -> 0.05 | G10: =IF(AND(Invoer!G19<10,AFM_Toetsrente>Invoer!G18),AFM_Toetsrente,Invoer!G18) -> 0.0469 | H10: =IF(AND(Invoer!H19<10,AFM_Toetsrente>Invoer!H18),AFM_Toetsrente,Invoer!H18) -> 0.0469 | I10: =IF(AND(Invoer!I19<10,AFM_Toetsrente>Invoer!I18),AFM_Toetsrente,Invoer!I18) -> 0.0469 | J10: =IF(AND(Invoer!J19<10,AFM_Toetsrente>Invoer!J18),AFM_Toetsrente,Invoer!J18) -> 0.0469 | ... M10: =IF(AND(Invoer!M19<10,AFM_Toetsrente>Invoer!M18),AFM_Toetsrente,Invoer!M18) -> 0.0469
A11: Kapitalisatiefactor (360 mnd) bij toetsrente | C11: =IF(C10=0,360,(1-(1+C10/12)^(-360))/(C10/12)) -> 193.03643 | D11: =IF(D10=0,360,(1-(1+D10/12)^(-360))/(D10/12)) -> 193.03643 | E11: =IF(E10=0,360,(1-(1+E10/12)^(-360))/(E10/12)) -> 193.03643 | F11: =IF(F10=0,360,(1-(1+F10/12)^(-360))/(F10/12)) -> 186.28162 | G11: =IF(G10=0,360,(1-(1+G10/12)^(-360))/(G10/12)) -> 193.03643 | H11: =IF(H10=0,360,(1-(1+H10/12)^(-360))/(H10/12)) -> 193.03643 | I11: =IF(I10=0,360,(1-(1+I10/12)^(-360))/(I10/12)) -> 193.03643 | J11: =IF(J10=0,360,(1-(1+J10/12)^(-360))/(J10/12)) -> 193.03643 | ... M11: =IF(M10=0,360,(1-(1+M10/12)^(-360))/(M10/12)) -> 193.03643
A12: 2. Schulden en lasten
A13: Overige schulden: maandlast (2%) | B13: € p/m | C13: =(Invoer!C23+C7*Invoer!C24)*Weging_overig -> 0 | D13: =(Invoer!D23+D7*Invoer!D24)*Weging_overig -> 0 | E13: =(Invoer!E23+E7*Invoer!E24)*Weging_overig -> 0 | F13: =(Invoer!F23+F7*Invoer!F24)*Weging_overig -> 0 | G13: =(Invoer!G23+G7*Invoer!G24)*Weging_overig -> 0 | H13: =(Invoer!H23+H7*Invoer!H24)*Weging_overig -> 0 | I13: =(Invoer!I23+I7*Invoer!I24)*Weging_overig -> 0 | J13: =(Invoer!J23+J7*Invoer!J24)*Weging_overig -> 0 | ... M13: =(Invoer!M23+M7*Invoer!M24)*Weging_overig -> 0
A14: Tweede woning aangehouden (1 = ja) | C14: =IF(Invoer!C30="Ja",1,0) -> 1 | D14: =IF(Invoer!D30="Ja",1,0) -> 1 | E14: =IF(Invoer!E30="Ja",1,0) -> 1 | F14: =IF(Invoer!F30="Ja",1,0) -> 1 | G14: =IF(Invoer!G30="Ja",1,0) -> 0 | H14: =IF(Invoer!H30="Ja",1,0) -> 0 | I14: =IF(Invoer!I30="Ja",1,0) -> 1 | J14: =IF(Invoer!J30="Ja",1,0) -> 0 | ... M14: =IF(Invoer!M30="Ja",1,0) -> 1
A15: Tweede woning: toetsrente | B15: % | C15: =C14*IF(AND(Invoer!C35<10,AFM_Toetsrente>Invoer!C32),AFM_Toetsrente,Invoer!C32) -> 0.01 | D15: =D14*IF(AND(Invoer!D35<10,AFM_Toetsrente>Invoer!D32),AFM_Toetsrente,Invoer!D32) -> 0.01 | E15: =E14*IF(AND(Invoer!E35<10,AFM_Toetsrente>Invoer!E32),AFM_Toetsrente,Invoer!E32) -> 0.01 | F15: =F14*IF(AND(Invoer!F35<10,AFM_Toetsrente>Invoer!F32),AFM_Toetsrente,Invoer!F32) -> 0.01 | G15: =G14*IF(AND(Invoer!G35<10,AFM_Toetsrente>Invoer!G32),AFM_Toetsrente,Invoer!G32) -> 0 | H15: =H14*IF(AND(Invoer!H35<10,AFM_Toetsrente>Invoer!H32),AFM_Toetsrente,Invoer!H32) -> 0 | I15: =I14*IF(AND(Invoer!I35<10,AFM_Toetsrente>Invoer!I32),AFM_Toetsrente,Invoer!I32) -> 0.01 | J15: =J14*IF(AND(Invoer!J35<10,AFM_Toetsrente>Invoer!J32),AFM_Toetsrente,Invoer!J32) -> 0 | ... M15: =M14*IF(AND(Invoer!M35<10,AFM_Toetsrente>Invoer!M32),AFM_Toetsrente,Invoer!M32) -> 0.01
A16: Tweede woning: toetslooptijd | B16: maanden | C16: =IF(Invoer!C33="Aflossingsvrij",360,MIN(360,MAX(1,ROUND(Invoer!C34*12,0)))) -> 240 | D16: =IF(Invoer!D33="Aflossingsvrij",360,MIN(360,MAX(1,ROUND(Invoer!D34*12,0)))) -> 240 | E16: =IF(Invoer!E33="Aflossingsvrij",360,MIN(360,MAX(1,ROUND(Invoer!E34*12,0)))) -> 240 | F16: =IF(Invoer!F33="Aflossingsvrij",360,MIN(360,MAX(1,ROUND(Invoer!F34*12,0)))) -> 240 | G16: =IF(Invoer!G33="Aflossingsvrij",360,MIN(360,MAX(1,ROUND(Invoer!G34*12,0)))) -> 240 | H16: =IF(Invoer!H33="Aflossingsvrij",360,MIN(360,MAX(1,ROUND(Invoer!H34*12,0)))) -> 240 | I16: =IF(Invoer!I33="Aflossingsvrij",360,MIN(360,MAX(1,ROUND(Invoer!I34*12,0)))) -> 240 | J16: =IF(Invoer!J33="Aflossingsvrij",360,MIN(360,MAX(1,ROUND(Invoer!J34*12,0)))) -> 240 | ... M16: =IF(Invoer!M33="Aflossingsvrij",360,MIN(360,MAX(1,ROUND(Invoer!M34*12,0)))) -> 240
A17: Tweede woning: toetslast | B17: € p/m | C17: =C14*IF(Invoer!C31<=0,0,IF(C15=0,Invoer!C31/C16,Invoer!C31*(C15/12)/(1-(1+C15/12)^(-C16)))) -> 193.15561 | D17: =D14*IF(Invoer!D31<=0,0,IF(D15=0,Invoer!D31/D16,Invoer!D31*(D15/12)/(1-(1+D15/12)^(-D16)))) -> 193.15561 | E17: =E14*IF(Invoer!E31<=0,0,IF(E15=0,Invoer!E31/E16,Invoer!E31*(E15/12)/(1-(1+E15/12)^(-E16)))) -> 193.15561 | F17: =F14*IF(Invoer!F31<=0,0,IF(F15=0,Invoer!F31/F16,Invoer!F31*(F15/12)/(1-(1+F15/12)^(-F16)))) -> 193.15561 | G17: =G14*IF(Invoer!G31<=0,0,IF(G15=0,Invoer!G31/G16,Invoer!G31*(G15/12)/(1-(1+G15/12)^(-G16)))) -> 0 | H17: =H14*IF(Invoer!H31<=0,0,IF(H15=0,Invoer!H31/H16,Invoer!H31*(H15/12)/(1-(1+H15/12)^(-H16)))) -> 0 | I17: =I14*IF(Invoer!I31<=0,0,IF(I15=0,Invoer!I31/I16,Invoer!I31*(I15/12)/(1-(1+I15/12)^(-I16)))) -> 193.15561 | J17: =J14*IF(Invoer!J31<=0,0,IF(J15=0,Invoer!J31/J16,Invoer!J31*(J15/12)/(1-(1+J15/12)^(-J16)))) -> 0 | ... M17: =M14*IF(Invoer!M31<=0,0,IF(M15=0,Invoer!M31/M16,Invoer!M31*(M15/12)/(1-(1+M15/12)^(-M16)))) -> 193.15561
A18: Totale maandlast schulden (excl. studieschuld) | B18: € p/m | C18: =C13+C17+Invoer!C25 -> 193.15561 | D18: =D13+D17+Invoer!D25 -> 193.15561 | E18: =E13+E17+Invoer!E25 -> 193.15561 | F18: =F13+F17+Invoer!F25 -> 193.15561 | G18: =G13+G17+Invoer!G25 -> 0 | H18: =H13+H17+Invoer!H25 -> 0 | I18: =I13+I17+Invoer!I25 -> 193.15561 | J18: =J13+J17+Invoer!J25 -> 0 | ... M18: =M13+M17+Invoer!M25 -> 193.15561
A19: 3. Bestaande hypotheek: toets per leningdeel
A20: Verstreken maanden sinds ingangsdatum | B20: maanden | C20: =IFERROR(DATEDIF(Invoer!C39,Invoer!C40,"m"),0) -> 68 | D20: =IFERROR(DATEDIF(Invoer!D39,Invoer!D40,"m"),0) -> 68 | E20: =IFERROR(DATEDIF(Invoer!E39,Invoer!E40,"m"),0) -> 68 | F20: =IFERROR(DATEDIF(Invoer!F39,Invoer!F40,"m"),0) -> 68 | G20: =IFERROR(DATEDIF(Invoer!G39,Invoer!G40,"m"),0) -> 68 | H20: =IFERROR(DATEDIF(Invoer!H39,Invoer!H40,"m"),0) -> 68 | I20: =IFERROR(DATEDIF(Invoer!I39,Invoer!I40,"m"),0) -> 68 | J20: =IFERROR(DATEDIF(Invoer!J39,Invoer!J40,"m"),0) -> 68 | ... M20: =IFERROR(DATEDIF(Invoer!M39,Invoer!M40,"m"),0) -> 68
A21: Resterende looptijd (360 min verstreken) | B21: maanden | C21: =MAX(1,360-C20) -> 292 | D21: =MAX(1,360-D20) -> 292 | E21: =MAX(1,360-E20) -> 292 | F21: =MAX(1,360-F20) -> 292 | G21: =MAX(1,360-G20) -> 292 | H21: =MAX(1,360-H20) -> 292 | I21: =MAX(1,360-I20) -> 292 | J21: =MAX(1,360-J20) -> 292 | ... M21: =MAX(1,360-M20) -> 292
A22: Deel 1: restsaldo | B22: € | C22: =Invoer!C43 -> 269480.64 | D22: =Invoer!D43 -> 269480.64 | E22: =Invoer!E43 -> 269480.64 | F22: =Invoer!F43 -> 269480.64 | G22: =Invoer!G43 -> 269480.64 | H22: =Invoer!H43 -> 269480.64 | I22: =Invoer!I43 -> 269480.64 | J22: =Invoer!J43 -> 269480.64 | ... M22: =Invoer!M43 -> 269480.64
A23: Deel 1: resterende rentevaste periode | B23: maanden | C23: =MAX(0,Invoer!C45*12-C20) -> 52 | D23: =MAX(0,Invoer!D45*12-D20) -> 52 | E23: =MAX(0,Invoer!E45*12-E20) -> 52 | F23: =MAX(0,Invoer!F45*12-F20) -> 52 | G23: =MAX(0,Invoer!G45*12-G20) -> 52 | H23: =MAX(0,Invoer!H45*12-H20) -> 52 | I23: =MAX(0,Invoer!I45*12-I20) -> 52 | J23: =MAX(0,Invoer!J45*12-J20) -> 52 | ... M23: =MAX(0,Invoer!M45*12-M20) -> 52
A24: Deel 1: toetsrente | B24: % | C24: =IF(C22>0,IF(C23<120,MAX(AFM_Toetsrente,Invoer!C44),Invoer!C44),0) -> 0.05 | D24: =IF(D22>0,IF(D23<120,MAX(AFM_Toetsrente,Invoer!D44),Invoer!D44),0) -> 0.05 | E24: =IF(E22>0,IF(E23<120,MAX(AFM_Toetsrente,Invoer!E44),Invoer!E44),0) -> 0.05 | F24: =IF(F22>0,IF(F23<120,MAX(AFM_Toetsrente,Invoer!F44),Invoer!F44),0) -> 0.05 | G24: =IF(G22>0,IF(G23<120,MAX(AFM_Toetsrente,Invoer!G44),Invoer!G44),0) -> 0.05 | H24: =IF(H22>0,IF(H23<120,MAX(AFM_Toetsrente,Invoer!H44),Invoer!H44),0) -> 0.05 | I24: =IF(I22>0,IF(I23<120,MAX(AFM_Toetsrente,Invoer!I44),Invoer!I44),0) -> 0.05 | J24: =IF(J22>0,IF(J23<120,MAX(AFM_Toetsrente,Invoer!J44),Invoer!J44),0) -> 0.05 | ... M24: =IF(M22>0,IF(M23<120,MAX(AFM_Toetsrente,Invoer!M44),Invoer!M44),0) -> 0.05
A25: Deel 1: toetslooptijd | B25: maanden | C25: =IF(OR(Invoer!C42="Aflossingsvrij",Invoer!C38="30 jaar"),360,C21) -> 292 | D25: =IF(OR(Invoer!D42="Aflossingsvrij",Invoer!D38="30 jaar"),360,D21) -> 360 | E25: =IF(OR(Invoer!E42="Aflossingsvrij",Invoer!E38="30 jaar"),360,E21) -> 292 | F25: =IF(OR(Invoer!F42="Aflossingsvrij",Invoer!F38="30 jaar"),360,F21) -> 292 | G25: =IF(OR(Invoer!G42="Aflossingsvrij",Invoer!G38="30 jaar"),360,G21) -> 292 | H25: =IF(OR(Invoer!H42="Aflossingsvrij",Invoer!H38="30 jaar"),360,H21) -> 292 | I25: =IF(OR(Invoer!I42="Aflossingsvrij",Invoer!I38="30 jaar"),360,I21) -> 292 | J25: =IF(OR(Invoer!J42="Aflossingsvrij",Invoer!J38="30 jaar"),360,J21) -> 292 | ... M25: =IF(OR(Invoer!M42="Aflossingsvrij",Invoer!M38="30 jaar"),360,M21) -> 292
A26: Deel 1: toetslast (annuïteit) | B26: € p/m | C26: =IF(C22<=0,0,IF(C24=0,C22/C25,C22*(C24/12)/(1-(1+C24/12)^(-C25)))) -> 1597.1281 | D26: =IF(D22<=0,0,IF(D24=0,D22/D25,D22*(D24/12)/(1-(1+D24/12)^(-D25)))) -> 1446.6303 | E26: =IF(E22<=0,0,IF(E24=0,E22/E25,E22*(E24/12)/(1-(1+E24/12)^(-E25)))) -> 1597.1281 | F26: =IF(F22<=0,0,IF(F24=0,F22/F25,F22*(F24/12)/(1-(1+F24/12)^(-F25)))) -> 1597.1281 | G26: =IF(G22<=0,0,IF(G24=0,G22/G25,G22*(G24/12)/(1-(1+G24/12)^(-G25)))) -> 1597.1281 | H26: =IF(H22<=0,0,IF(H24=0,H22/H25,H22*(H24/12)/(1-(1+H24/12)^(-H25)))) -> 1597.1281 | I26: =IF(I22<=0,0,IF(I24=0,I22/I25,I22*(I24/12)/(1-(1+I24/12)^(-I25)))) -> 1597.1281 | J26: =IF(J22<=0,0,IF(J24=0,J22/J25,J22*(J24/12)/(1-(1+J24/12)^(-J25)))) -> 1597.1281 | ... M26: =IF(M22<=0,0,IF(M24=0,M22/M25,M22*(M24/12)/(1-(1+M24/12)^(-M25)))) -> 1597.1281
A27: Deel 2: restsaldo | B27: € | C27: =Invoer!C48 -> 354269.27 | D27: =Invoer!D48 -> 354269.27 | E27: =Invoer!E48 -> 354269.27 | F27: =Invoer!F48 -> 354269.27 | G27: =Invoer!G48 -> 354269.27 | H27: =Invoer!H48 -> 354269.27 | I27: =Invoer!I48 -> 354269.27 | J27: =Invoer!J48 -> 354269.27 | ... M27: =Invoer!M48 -> 354269.27
A28: Deel 2: resterende rentevaste periode | B28: maanden | C28: =MAX(0,Invoer!C50*12-C20) -> 172 | D28: =MAX(0,Invoer!D50*12-D20) -> 172 | E28: =MAX(0,Invoer!E50*12-E20) -> 52 | F28: =MAX(0,Invoer!F50*12-F20) -> 172 | G28: =MAX(0,Invoer!G50*12-G20) -> 172 | H28: =MAX(0,Invoer!H50*12-H20) -> 172 | I28: =MAX(0,Invoer!I50*12-I20) -> 172 | J28: =MAX(0,Invoer!J50*12-J20) -> 172 | ... M28: =MAX(0,Invoer!M50*12-M20) -> 172
A29: Deel 2: toetsrente | B29: % | C29: =IF(C27>0,IF(C28<120,MAX(AFM_Toetsrente,Invoer!C49),Invoer!C49),0) -> 0.0185 | D29: =IF(D27>0,IF(D28<120,MAX(AFM_Toetsrente,Invoer!D49),Invoer!D49),0) -> 0.0185 | E29: =IF(E27>0,IF(E28<120,MAX(AFM_Toetsrente,Invoer!E49),Invoer!E49),0) -> 0.05 | F29: =IF(F27>0,IF(F28<120,MAX(AFM_Toetsrente,Invoer!F49),Invoer!F49),0) -> 0.0185 | G29: =IF(G27>0,IF(G28<120,MAX(AFM_Toetsrente,Invoer!G49),Invoer!G49),0) -> 0.0185 | H29: =IF(H27>0,IF(H28<120,MAX(AFM_Toetsrente,Invoer!H49),Invoer!H49),0) -> 0.0185 | I29: =IF(I27>0,IF(I28<120,MAX(AFM_Toetsrente,Invoer!I49),Invoer!I49),0) -> 0.0185 | J29: =IF(J27>0,IF(J28<120,MAX(AFM_Toetsrente,Invoer!J49),Invoer!J49),0) -> 0.0185 | ... M29: =IF(M27>0,IF(M28<120,MAX(AFM_Toetsrente,Invoer!M49),Invoer!M49),0) -> 0.0185
A30: Deel 2: toetslooptijd | B30: maanden | C30: =IF(OR(Invoer!C47="Aflossingsvrij",Invoer!C38="30 jaar"),360,C21) -> 360 | D30: =IF(OR(Invoer!D47="Aflossingsvrij",Invoer!D38="30 jaar"),360,D21) -> 360 | E30: =IF(OR(Invoer!E47="Aflossingsvrij",Invoer!E38="30 jaar"),360,E21) -> 360 | F30: =IF(OR(Invoer!F47="Aflossingsvrij",Invoer!F38="30 jaar"),360,F21) -> 360 | G30: =IF(OR(Invoer!G47="Aflossingsvrij",Invoer!G38="30 jaar"),360,G21) -> 360 | H30: =IF(OR(Invoer!H47="Aflossingsvrij",Invoer!H38="30 jaar"),360,H21) -> 360 | I30: =IF(OR(Invoer!I47="Aflossingsvrij",Invoer!I38="30 jaar"),360,I21) -> 360 | J30: =IF(OR(Invoer!J47="Aflossingsvrij",Invoer!J38="30 jaar"),360,J21) -> 360 | ... M30: =IF(OR(Invoer!M47="Aflossingsvrij",Invoer!M38="30 jaar"),360,M21) -> 360
A31: Deel 2: toetslast (annuïteit) | B31: € p/m | C31: =IF(C27<=0,0,IF(C29=0,C27/C30,C27*(C29/12)/(1-(1+C29/12)^(-C30)))) -> 1283.0345 | D31: =IF(D27<=0,0,IF(D29=0,D27/D30,D27*(D29/12)/(1-(1+D29/12)^(-D30)))) -> 1283.0345 | E31: =IF(E27<=0,0,IF(E29=0,E27/E30,E27*(E29/12)/(1-(1+E29/12)^(-E30)))) -> 1901.794 | F31: =IF(F27<=0,0,IF(F29=0,F27/F30,F27*(F29/12)/(1-(1+F29/12)^(-F30)))) -> 1283.0345 | G31: =IF(G27<=0,0,IF(G29=0,G27/G30,G27*(G29/12)/(1-(1+G29/12)^(-G30)))) -> 1283.0345 | H31: =IF(H27<=0,0,IF(H29=0,H27/H30,H27*(H29/12)/(1-(1+H29/12)^(-H30)))) -> 1283.0345 | I31: =IF(I27<=0,0,IF(I29=0,I27/I30,I27*(I29/12)/(1-(1+I29/12)^(-I30)))) -> 1283.0345 | J31: =IF(J27<=0,0,IF(J29=0,J27/J30,J27*(J29/12)/(1-(1+J29/12)^(-J30)))) -> 1283.0345 | ... M31: =IF(M27<=0,0,IF(M29=0,M27/M30,M27*(M29/12)/(1-(1+M29/12)^(-M30)))) -> 1283.0345
A32: Deel 3: restsaldo | B32: € | C32: =Invoer!C53 -> 0 | D32: =Invoer!D53 -> 0 | E32: =Invoer!E53 -> 0 | F32: =Invoer!F53 -> 0 | G32: =Invoer!G53 -> 0 | H32: =Invoer!H53 -> 0 | I32: =Invoer!I53 -> 0 | J32: =Invoer!J53 -> 0 | ... M32: =Invoer!M53 -> 0
A33: Deel 3: resterende rentevaste periode | B33: maanden | C33: =MAX(0,Invoer!C55*12-C20) -> 52 | D33: =MAX(0,Invoer!D55*12-D20) -> 52 | E33: =MAX(0,Invoer!E55*12-E20) -> 52 | F33: =MAX(0,Invoer!F55*12-F20) -> 52 | G33: =MAX(0,Invoer!G55*12-G20) -> 52 | H33: =MAX(0,Invoer!H55*12-H20) -> 52 | I33: =MAX(0,Invoer!I55*12-I20) -> 52 | J33: =MAX(0,Invoer!J55*12-J20) -> 52 | ... M33: =MAX(0,Invoer!M55*12-M20) -> 52
A34: Deel 3: toetsrente | B34: % | C34: =IF(C32>0,IF(C33<120,MAX(AFM_Toetsrente,Invoer!C54),Invoer!C54),0) -> 0 | D34: =IF(D32>0,IF(D33<120,MAX(AFM_Toetsrente,Invoer!D54),Invoer!D54),0) -> 0 | E34: =IF(E32>0,IF(E33<120,MAX(AFM_Toetsrente,Invoer!E54),Invoer!E54),0) -> 0 | F34: =IF(F32>0,IF(F33<120,MAX(AFM_Toetsrente,Invoer!F54),Invoer!F54),0) -> 0 | G34: =IF(G32>0,IF(G33<120,MAX(AFM_Toetsrente,Invoer!G54),Invoer!G54),0) -> 0 | H34: =IF(H32>0,IF(H33<120,MAX(AFM_Toetsrente,Invoer!H54),Invoer!H54),0) -> 0 | I34: =IF(I32>0,IF(I33<120,MAX(AFM_Toetsrente,Invoer!I54),Invoer!I54),0) -> 0 | J34: =IF(J32>0,IF(J33<120,MAX(AFM_Toetsrente,Invoer!J54),Invoer!J54),0) -> 0 | ... M34: =IF(M32>0,IF(M33<120,MAX(AFM_Toetsrente,Invoer!M54),Invoer!M54),0) -> 0
A35: Deel 3: toetslooptijd | B35: maanden | C35: =IF(OR(Invoer!C52="Aflossingsvrij",Invoer!C38="30 jaar"),360,C21) -> 292 | D35: =IF(OR(Invoer!D52="Aflossingsvrij",Invoer!D38="30 jaar"),360,D21) -> 360 | E35: =IF(OR(Invoer!E52="Aflossingsvrij",Invoer!E38="30 jaar"),360,E21) -> 292 | F35: =IF(OR(Invoer!F52="Aflossingsvrij",Invoer!F38="30 jaar"),360,F21) -> 292 | G35: =IF(OR(Invoer!G52="Aflossingsvrij",Invoer!G38="30 jaar"),360,G21) -> 292 | H35: =IF(OR(Invoer!H52="Aflossingsvrij",Invoer!H38="30 jaar"),360,H21) -> 292 | I35: =IF(OR(Invoer!I52="Aflossingsvrij",Invoer!I38="30 jaar"),360,I21) -> 292 | J35: =IF(OR(Invoer!J52="Aflossingsvrij",Invoer!J38="30 jaar"),360,J21) -> 292 | ... M35: =IF(OR(Invoer!M52="Aflossingsvrij",Invoer!M38="30 jaar"),360,M21) -> 292
A36: Deel 3: toetslast (annuïteit) | B36: € p/m | C36: =IF(C32<=0,0,IF(C34=0,C32/C35,C32*(C34/12)/(1-(1+C34/12)^(-C35)))) -> 0 | D36: =IF(D32<=0,0,IF(D34=0,D32/D35,D32*(D34/12)/(1-(1+D34/12)^(-D35)))) -> 0 | E36: =IF(E32<=0,0,IF(E34=0,E32/E35,E32*(E34/12)/(1-(1+E34/12)^(-E35)))) -> 0 | F36: =IF(F32<=0,0,IF(F34=0,F32/F35,F32*(F34/12)/(1-(1+F34/12)^(-F35)))) -> 0 | G36: =IF(G32<=0,0,IF(G34=0,G32/G35,G32*(G34/12)/(1-(1+G34/12)^(-G35)))) -> 0 | H36: =IF(H32<=0,0,IF(H34=0,H32/H35,H32*(H34/12)/(1-(1+H34/12)^(-H35)))) -> 0 | I36: =IF(I32<=0,0,IF(I34=0,I32/I35,I32*(I34/12)/(1-(1+I34/12)^(-I35)))) -> 0 | J36: =IF(J32<=0,0,IF(J34=0,J32/J35,J32*(J34/12)/(1-(1+J34/12)^(-J35)))) -> 0 | ... M36: =IF(M32<=0,0,IF(M34=0,M32/M35,M32*(M34/12)/(1-(1+M34/12)^(-M35)))) -> 0
A37: Deel 4: restsaldo | B37: € | C37: =Invoer!C58 -> 0 | D37: =Invoer!D58 -> 0 | E37: =Invoer!E58 -> 0 | F37: =Invoer!F58 -> 0 | G37: =Invoer!G58 -> 0 | H37: =Invoer!H58 -> 0 | I37: =Invoer!I58 -> 0 | J37: =Invoer!J58 -> 0 | ... M37: =Invoer!M58 -> 0
A38: Deel 4: resterende rentevaste periode | B38: maanden | C38: =MAX(0,Invoer!C60*12-C20) -> 52 | D38: =MAX(0,Invoer!D60*12-D20) -> 52 | E38: =MAX(0,Invoer!E60*12-E20) -> 52 | F38: =MAX(0,Invoer!F60*12-F20) -> 52 | G38: =MAX(0,Invoer!G60*12-G20) -> 52 | H38: =MAX(0,Invoer!H60*12-H20) -> 52 | I38: =MAX(0,Invoer!I60*12-I20) -> 52 | J38: =MAX(0,Invoer!J60*12-J20) -> 52 | ... M38: =MAX(0,Invoer!M60*12-M20) -> 52
A39: Deel 4: toetsrente | B39: % | C39: =IF(C37>0,IF(C38<120,MAX(AFM_Toetsrente,Invoer!C59),Invoer!C59),0) -> 0 | D39: =IF(D37>0,IF(D38<120,MAX(AFM_Toetsrente,Invoer!D59),Invoer!D59),0) -> 0 | E39: =IF(E37>0,IF(E38<120,MAX(AFM_Toetsrente,Invoer!E59),Invoer!E59),0) -> 0 | F39: =IF(F37>0,IF(F38<120,MAX(AFM_Toetsrente,Invoer!F59),Invoer!F59),0) -> 0 | G39: =IF(G37>0,IF(G38<120,MAX(AFM_Toetsrente,Invoer!G59),Invoer!G59),0) -> 0 | H39: =IF(H37>0,IF(H38<120,MAX(AFM_Toetsrente,Invoer!H59),Invoer!H59),0) -> 0 | I39: =IF(I37>0,IF(I38<120,MAX(AFM_Toetsrente,Invoer!I59),Invoer!I59),0) -> 0 | J39: =IF(J37>0,IF(J38<120,MAX(AFM_Toetsrente,Invoer!J59),Invoer!J59),0) -> 0 | ... M39: =IF(M37>0,IF(M38<120,MAX(AFM_Toetsrente,Invoer!M59),Invoer!M59),0) -> 0
A40: Deel 4: toetslooptijd | B40: maanden | C40: =IF(OR(Invoer!C57="Aflossingsvrij",Invoer!C38="30 jaar"),360,C21) -> 292 | D40: =IF(OR(Invoer!D57="Aflossingsvrij",Invoer!D38="30 jaar"),360,D21) -> 360 | E40: =IF(OR(Invoer!E57="Aflossingsvrij",Invoer!E38="30 jaar"),360,E21) -> 292 | F40: =IF(OR(Invoer!F57="Aflossingsvrij",Invoer!F38="30 jaar"),360,F21) -> 292 | G40: =IF(OR(Invoer!G57="Aflossingsvrij",Invoer!G38="30 jaar"),360,G21) -> 292 | H40: =IF(OR(Invoer!H57="Aflossingsvrij",Invoer!H38="30 jaar"),360,H21) -> 292 | I40: =IF(OR(Invoer!I57="Aflossingsvrij",Invoer!I38="30 jaar"),360,I21) -> 292 | J40: =IF(OR(Invoer!J57="Aflossingsvrij",Invoer!J38="30 jaar"),360,J21) -> 292 | ... M40: =IF(OR(Invoer!M57="Aflossingsvrij",Invoer!M38="30 jaar"),360,M21) -> 292
A41: Deel 4: toetslast (annuïteit) | B41: € p/m | C41: =IF(C37<=0,0,IF(C39=0,C37/C40,C37*(C39/12)/(1-(1+C39/12)^(-C40)))) -> 0 | D41: =IF(D37<=0,0,IF(D39=0,D37/D40,D37*(D39/12)/(1-(1+D39/12)^(-D40)))) -> 0 | E41: =IF(E37<=0,0,IF(E39=0,E37/E40,E37*(E39/12)/(1-(1+E39/12)^(-E40)))) -> 0 | F41: =IF(F37<=0,0,IF(F39=0,F37/F40,F37*(F39/12)/(1-(1+F39/12)^(-F40)))) -> 0 | G41: =IF(G37<=0,0,IF(G39=0,G37/G40,G37*(G39/12)/(1-(1+G39/12)^(-G40)))) -> 0 | H41: =IF(H37<=0,0,IF(H39=0,H37/H40,H37*(H39/12)/(1-(1+H39/12)^(-H40)))) -> 0 | I41: =IF(I37<=0,0,IF(I39=0,I37/I40,I37*(I39/12)/(1-(1+I39/12)^(-I40)))) -> 0 | J41: =IF(J37<=0,0,IF(J39=0,J37/J40,J37*(J39/12)/(1-(1+J39/12)^(-J40)))) -> 0 | ... M41: =IF(M37<=0,0,IF(M39=0,M37/M40,M37*(M39/12)/(1-(1+M39/12)^(-M40)))) -> 0
A42: Totale restschuld bestaande hypotheek | B42: € | C42: =C22+C27+C32+C37 -> 623749.91 | D42: =D22+D27+D32+D37 -> 623749.91 | E42: =E22+E27+E32+E37 -> 623749.91 | F42: =F22+F27+F32+F37 -> 623749.91 | G42: =G22+G27+G32+G37 -> 623749.91 | H42: =H22+H27+H32+H37 -> 623749.91 | I42: =I22+I27+I32+I37 -> 623749.91 | J42: =J22+J27+J32+J37 -> 623749.91 | ... M42: =M22+M27+M32+M37 -> 623749.91
A43: Meegenomen hypotheek | B43: € | C43: =C8*C42 -> 623749.91 | D43: =D8*D42 -> 623749.91 | E43: =E8*E42 -> 623749.91 | F43: =F8*F42 -> 623749.91 | G43: =G8*G42 -> 0 | H43: =H8*H42 -> 0 | I43: =I8*I42 -> 0 | J43: =J8*J42 -> 623749.91 | ... M43: =M8*M42 -> 623749.91
A44: Toetslast meegenomen delen samen | B44: € p/m | C44: =C8*(C26+C31+C36+C41) -> 2880.1626 | D44: =D8*(D26+D31+D36+D41) -> 2729.6648 | E44: =E8*(E26+E31+E36+E41) -> 3498.9222 | F44: =F8*(F26+F31+F36+F41) -> 2880.1626 | G44: =G8*(G26+G31+G36+G41) -> 0 | H44: =H8*(H26+H31+H36+H41) -> 0 | I44: =I8*(I26+I31+I36+I41) -> 0 | J44: =J8*(J26+J31+J36+J41) -> 2880.1626 | ... M44: =M8*(M26+M31+M36+M41) -> 2880.1626
A45: Σ saldo × looptijd × toetsrente (teller gewogen rente) | C45: =C8*(C22*C25*C24+C27*C30*C29+C32*C35*C34+C37*C40*C39) -> 6293850.7 | D45: =D8*(D22*D25*D24+D27*D30*D29+D32*D35*D34+D37*D40*D39) -> 7210084.9 | E45: =E8*(E22*E25*E24+E27*E30*E29+E32*E35*E34+E37*E40*E39) -> 10311264 | F45: =F8*(F22*F25*F24+F27*F30*F29+F32*F35*F34+F37*F40*F39) -> 6293850.7 | G45: =G8*(G22*G25*G24+G27*G30*G29+G32*G35*G34+G37*G40*G39) -> 0 | H45: =H8*(H22*H25*H24+H27*H30*H29+H32*H35*H34+H37*H40*H39) -> 0 | I45: =I8*(I22*I25*I24+I27*I30*I29+I32*I35*I34+I37*I40*I39) -> 0 | J45: =J8*(J22*J25*J24+J27*J30*J29+J32*J35*J34+J37*J40*J39) -> 6293850.7 | ... M45: =M8*(M22*M25*M24+M27*M30*M29+M32*M35*M34+M37*M40*M39) -> 6293850.7
A46: Σ saldo × looptijd (noemer gewogen rente) | C46: =C8*(C22*C25+C27*C30+C32*C35+C37*C40) -> 2.0622528e+08 | D46: =D8*(D22*D25+D27*D30+D32*D35+D37*D40) -> 2.2454997e+08 | E46: =E8*(E22*E25+E27*E30+E32*E35+E37*E40) -> 2.0622528e+08 | F46: =F8*(F22*F25+F27*F30+F32*F35+F37*F40) -> 2.0622528e+08 | G46: =G8*(G22*G25+G27*G30+G32*G35+G37*G40) -> 0 | H46: =H8*(H22*H25+H27*H30+H32*H35+H37*H40) -> 0 | I46: =I8*(I22*I25+I27*I30+I32*I35+I37*I40) -> 0 | J46: =J8*(J22*J25+J27*J30+J32*J35+J37*J40) -> 2.0622528e+08 | ... M46: =M8*(M22*M25+M27*M30+M32*M35+M37*M40) -> 2.0622528e+08
A47: Samengestelde toets actief (1 = ja) | C47: =IF(AND(C8=1,C42>0),1,0) -> 1 | D47: =IF(AND(D8=1,D42>0),1,0) -> 1 | E47: =IF(AND(E8=1,E42>0),1,0) -> 1 | F47: =IF(AND(F8=1,F42>0),1,0) -> 1 | G47: =IF(AND(G8=1,G42>0),1,0) -> 0 | H47: =IF(AND(H8=1,H42>0),1,0) -> 0 | I47: =IF(AND(I8=1,I42>0),1,0) -> 0 | J47: =IF(AND(J8=1,J42>0),1,0) -> 1 | ... M47: =IF(AND(M8=1,M42>0),1,0) -> 1
A48: 4. Financieringsgat en kosten koper
A49: Verkoopwaarde huidige woning (voorzichtig) | B49: € | C49: =Invoer!C62*Invoer!C63 -> 888250 | D49: =Invoer!D62*Invoer!D63 -> 888250 | E49: =Invoer!E62*Invoer!E63 -> 888250 | F49: =Invoer!F62*Invoer!F63 -> 888250 | G49: =Invoer!G62*Invoer!G63 -> 888250 | H49: =Invoer!H62*Invoer!H63 -> 888250 | I49: =Invoer!I62*Invoer!I63 -> 888250 | J49: =Invoer!J62*Invoer!J63 -> 888250 | ... M49: =Invoer!M62*Invoer!M63 -> 888250
A50: Bruikbare overwaarde | B50: € | C50: =MAX(0,C49-C42) -> 264500.09 | D50: =MAX(0,D49-D42) -> 264500.09 | E50: =MAX(0,E49-E42) -> 264500.09 | F50: =MAX(0,F49-F42) -> 264500.09 | G50: =MAX(0,G49-G42) -> 264500.09 | H50: =MAX(0,H49-H42) -> 264500.09 | I50: =MAX(0,I49-I42) -> 264500.09 | J50: =MAX(0,J49-J42) -> 264500.09 | ... M50: =MAX(0,M49-M42) -> 264500.09
A51: Restschuld-tekort bij verkoop | B51: € | C51: =MAX(0,C42-C49) -> 0 | D51: =MAX(0,D42-D49) -> 0 | E51: =MAX(0,E42-E49) -> 0 | F51: =MAX(0,F42-F49) -> 0 | G51: =MAX(0,G42-G49) -> 0 | H51: =MAX(0,H42-H49) -> 0 | I51: =MAX(0,I42-I49) -> 0 | J51: =MAX(0,J42-J49) -> 0 | ... M51: =MAX(0,M42-M49) -> 0
A52: Financieringsgat (aankoopprijs − meegenomen − overwaarde + tekort) | B52: € | C52: =C6*(Invoer!C20-C43-C50+C51) -> 441750 | D52: =D6*(Invoer!D20-D43-D50+D51) -> 441750 | E52: =E6*(Invoer!E20-E43-E50+E51) -> 441750 | F52: =F6*(Invoer!F20-F43-F50+F51) -> 441750 | G52: =G6*(Invoer!G20-G43-G50+G51) -> 0 | H52: =H6*(Invoer!H20-H43-H50+H51) -> 0 | I52: =I6*(Invoer!I20-I43-I50+I51) -> 1065499.9 | J52: =J6*(Invoer!J20-J43-J50+J51) -> 441750 | ... M52: =M6*(Invoer!M20-M43-M50+M51) -> 441750
A53: Overdrachtsbelasting | B53: € | C53: =Invoer!C20*Invoer!C65 -> 26600 | D53: =Invoer!D20*Invoer!D65 -> 26600 | E53: =Invoer!E20*Invoer!E65 -> 26600 | F53: =Invoer!F20*Invoer!F65 -> 26600 | G53: =Invoer!G20*Invoer!G65 -> 8000 | H53: =Invoer!H20*Invoer!H65 -> 0 | I53: =Invoer!I20*Invoer!I65 -> 26600 | J53: =Invoer!J20*Invoer!J65 -> 26600 | ... M53: =Invoer!M20*Invoer!M65 -> 26600
A54: Bankgarantie | B54: € | C54: =IF(Invoer!C69="Ja",Invoer!C20*Bankgarantie_pct,0) -> 1330 | D54: =IF(Invoer!D69="Ja",Invoer!D20*Bankgarantie_pct,0) -> 1330 | E54: =IF(Invoer!E69="Ja",Invoer!E20*Bankgarantie_pct,0) -> 1330 | F54: =IF(Invoer!F69="Ja",Invoer!F20*Bankgarantie_pct,0) -> 1330 | G54: =IF(Invoer!G69="Ja",Invoer!G20*Bankgarantie_pct,0) -> 400 | H54: =IF(Invoer!H69="Ja",Invoer!H20*Bankgarantie_pct,0) -> 650 | I54: =IF(Invoer!I69="Ja",Invoer!I20*Bankgarantie_pct,0) -> 1330 | J54: =IF(Invoer!J69="Ja",Invoer!J20*Bankgarantie_pct,0) -> 1330 | ... M54: =IF(Invoer!M69="Ja",Invoer!M20*Bankgarantie_pct,0) -> 1330
A55: Aankoopmakelaar | B55: € | C55: =IF(Invoer!C70="Ja",Invoer!C20*Makelaar_pct,0) -> 0 | D55: =IF(Invoer!D70="Ja",Invoer!D20*Makelaar_pct,0) -> 0 | E55: =IF(Invoer!E70="Ja",Invoer!E20*Makelaar_pct,0) -> 0 | F55: =IF(Invoer!F70="Ja",Invoer!F20*Makelaar_pct,0) -> 0 | G55: =IF(Invoer!G70="Ja",Invoer!G20*Makelaar_pct,0) -> 0 | H55: =IF(Invoer!H70="Ja",Invoer!H20*Makelaar_pct,0) -> 0 | I55: =IF(Invoer!I70="Ja",Invoer!I20*Makelaar_pct,0) -> 0 | J55: =IF(Invoer!J70="Ja",Invoer!J20*Makelaar_pct,0) -> 0 | ... M55: =IF(Invoer!M70="Ja",Invoer!M20*Makelaar_pct,0) -> 0
A56: Kosten koper totaal | B56: € | C56: =C53+Invoer!C66+Invoer!C67+Invoer!C68+C54+C55 -> 32230 | D56: =D53+Invoer!D66+Invoer!D67+Invoer!D68+D54+D55 -> 32230 | E56: =E53+Invoer!E66+Invoer!E67+Invoer!E68+E54+E55 -> 32230 | F56: =F53+Invoer!F66+Invoer!F67+Invoer!F68+F54+F55 -> 32230 | G56: =G53+Invoer!G66+Invoer!G67+Invoer!G68+G54+G55 -> 12700 | H56: =H53+Invoer!H66+Invoer!H67+Invoer!H68+H54+H55 -> 4950 | I56: =I53+Invoer!I66+Invoer!I67+Invoer!I68+I54+I55 -> 32230 | J56: =J53+Invoer!J66+Invoer!J67+Invoer!J68+J54+J55 -> 32230 | ... M56: =M53+Invoer!M66+Invoer!M67+Invoer!M68+M54+M55 -> 32230
A57: Kosten koper die van eigen geld afgaan | B57: € | C57: =IF(Invoer!C71="Ja",C56,0) -> 32230 | D57: =IF(Invoer!D71="Ja",D56,0) -> 32230 | E57: =IF(Invoer!E71="Ja",E56,0) -> 32230 | F57: =IF(Invoer!F71="Ja",F56,0) -> 32230 | G57: =IF(Invoer!G71="Ja",G56,0) -> 12700 | H57: =IF(Invoer!H71="Ja",H56,0) -> 4950 | I57: =IF(Invoer!I71="Ja",I56,0) -> 32230 | J57: =IF(Invoer!J71="Ja",J56,0) -> 32230 | ... M57: =IF(Invoer!M71="Ja",M56,0) -> 32230
A58: Eigen geld beschikbaar voor het gat | B58: € | C58: =MAX(0,Invoer!C64-C57) -> 117770 | D58: =MAX(0,Invoer!D64-D57) -> 117770 | E58: =MAX(0,Invoer!E64-E57) -> 117770 | F58: =MAX(0,Invoer!F64-F57) -> 117770 | G58: =MAX(0,Invoer!G64-G57) -> 27300 | H58: =MAX(0,Invoer!H64-H57) -> 55050 | I58: =MAX(0,Invoer!I64-I57) -> 117770 | J58: =MAX(0,Invoer!J64-J57) -> 117770 | ... M58: =MAX(0,Invoer!M64-M57) -> 117770
A59: Eigen geld ingezet op het gat | B59: € | C59: =MIN(C58,MAX(0,C52)) -> 117770 | D59: =MIN(D58,MAX(0,D52)) -> 117770 | E59: =MIN(E58,MAX(0,E52)) -> 117770 | F59: =MIN(F58,MAX(0,F52)) -> 117770 | G59: =MIN(G58,MAX(0,G52)) -> 0 | H59: =MIN(H58,MAX(0,H52)) -> 0 | I59: =MIN(I58,MAX(0,I52)) -> 117770 | J59: =MIN(J58,MAX(0,J52)) -> 117770 | ... M59: =MIN(M58,MAX(0,M52)) -> 117770
A60: Nieuw geld nodig (doorstromer) | B60: € | C60: =MAX(0,C52-C59) -> 323980 | D60: =MAX(0,D52-D59) -> 323980 | E60: =MAX(0,E52-E59) -> 323980 | F60: =MAX(0,F52-F59) -> 323980 | G60: =MAX(0,G52-G59) -> 0 | H60: =MAX(0,H52-H59) -> 0 | I60: =MAX(0,I52-I59) -> 947729.91 | J60: =MAX(0,J52-J59) -> 323980 | ... M60: =MAX(0,M52-M59) -> 323980
A61: 5. Studieschuld (art. 3a)
A62: Nieuw geld in de weging van de debetrente | B62: € | C62: =C6*C60 -> 323980 | D62: =D6*D60 -> 323980 | E62: =E6*E60 -> 323980 | F62: =F6*F60 -> 323980 | G62: =G6*G60 -> 0 | H62: =H6*H60 -> 0 | I62: =I6*I60 -> 947729.91 | J62: =J6*J60 -> 323980 | ... M62: =M6*M60 -> 323980
A63: Meegenomen saldo in de weging | B63: € | C63: =C8*C42 -> 623749.91 | D63: =D8*D42 -> 623749.91 | E63: =E8*E42 -> 623749.91 | F63: =F8*F42 -> 623749.91 | G63: =G8*G42 -> 0 | H63: =H8*H42 -> 0 | I63: =I8*I42 -> 0 | J63: =J8*J42 -> 623749.91 | ... M63: =M8*M42 -> 623749.91
A64: Σ saldo × toetsrente (meegenomen) | C64: =C8*(C22*C24+C27*C29+C32*C34+C37*C39) -> 20028.013 | D64: =D8*(D22*D24+D27*D29+D32*D34+D37*D39) -> 20028.013 | E64: =E8*(E22*E24+E27*E29+E32*E34+E37*E39) -> 31187.496 | F64: =F8*(F22*F24+F27*F29+F32*F34+F37*F39) -> 20028.013 | G64: =G8*(G22*G24+G27*G29+G32*G34+G37*G39) -> 0 | H64: =H8*(H22*H24+H27*H29+H32*H34+H37*H39) -> 0 | I64: =I8*(I22*I24+I27*I29+I32*I34+I37*I39) -> 0 | J64: =J8*(J22*J24+J27*J29+J32*J34+J37*J39) -> 20028.013 | ... M64: =M8*(M22*M24+M27*M29+M32*M34+M37*M39) -> 20028.013
A65: Σ saldo × contractrente (meegenomen) | C65: =C8*(C22*Invoer!C44+C27*Invoer!C49+C32*Invoer!C54+C37*Invoer!C59) -> 9922.4895 | D65: =D8*(D22*Invoer!D44+D27*Invoer!D49+D32*Invoer!D54+D37*Invoer!D59) -> 9922.4895 | E65: =E8*(E22*Invoer!E44+E27*Invoer!E49+E32*Invoer!E54+E37*Invoer!E59) -> 9922.4895 | F65: =F8*(F22*Invoer!F44+F27*Invoer!F49+F32*Invoer!F54+F37*Invoer!F59) -> 9922.4895 | G65: =G8*(G22*Invoer!G44+G27*Invoer!G49+G32*Invoer!G54+G37*Invoer!G59) -> 0 | H65: =H8*(H22*Invoer!H44+H27*Invoer!H49+H32*Invoer!H54+H37*Invoer!H59) -> 0 | I65: =I8*(I22*Invoer!I44+I27*Invoer!I49+I32*Invoer!I54+I37*Invoer!I59) -> 0 | J65: =J8*(J22*Invoer!J44+J27*Invoer!J49+J32*Invoer!J54+J37*Invoer!J59) -> 9922.4895 | ... M65: =M8*(M22*Invoer!M44+M27*Invoer!M49+M32*Invoer!M54+M37*Invoer!M59) -> 9922.4895
A66: Gewicht nieuw geld | B66: € | C66: =IF(C62>0,C62,IF(C63>0,0,1)) -> 323980 | D66: =IF(D62>0,D62,IF(D63>0,0,1)) -> 323980 | E66: =IF(E62>0,E62,IF(E63>0,0,1)) -> 323980 | F66: =IF(F62>0,F62,IF(F63>0,0,1)) -> 323980 | G66: =IF(G62>0,G62,IF(G63>0,0,1)) -> 1 | H66: =IF(H62>0,H62,IF(H63>0,0,1)) -> 1 | I66: =IF(I62>0,I62,IF(I63>0,0,1)) -> 947729.91 | J66: =IF(J62>0,J62,IF(J63>0,0,1)) -> 323980 | ... M66: =IF(M62>0,M62,IF(M63>0,0,1)) -> 323980
A67: Toetsrente nieuw geld | B67: % | C67: =IF(Invoer!C19<10,MAX(Invoer!C18,AFM_Toetsrente),Invoer!C18) -> 0.0469 | D67: =IF(Invoer!D19<10,MAX(Invoer!D18,AFM_Toetsrente),Invoer!D18) -> 0.0469 | E67: =IF(Invoer!E19<10,MAX(Invoer!E18,AFM_Toetsrente),Invoer!E18) -> 0.0469 | F67: =IF(Invoer!F19<10,MAX(Invoer!F18,AFM_Toetsrente),Invoer!F18) -> 0.05 | G67: =IF(Invoer!G19<10,MAX(Invoer!G18,AFM_Toetsrente),Invoer!G18) -> 0.0469 | H67: =IF(Invoer!H19<10,MAX(Invoer!H18,AFM_Toetsrente),Invoer!H18) -> 0.0469 | I67: =IF(Invoer!I19<10,MAX(Invoer!I18,AFM_Toetsrente),Invoer!I18) -> 0.0469 | J67: =IF(Invoer!J19<10,MAX(Invoer!J18,AFM_Toetsrente),Invoer!J18) -> 0.0469 | ... M67: =IF(Invoer!M19<10,MAX(Invoer!M18,AFM_Toetsrente),Invoer!M18) -> 0.0469
A68: Gewogen toetsrente (gewicht saldo) | B68: % | C68: =(C64+C66*C67)/(C63+C66) -> 0.03716531 | D68: =(D64+D66*D67)/(D63+D66) -> 0.03716531 | E68: =(E64+E66*E67)/(E63+E66) -> 0.04894027 | F68: =(F64+F66*F67)/(F63+F66) -> 0.03822504 | G68: =(G64+G66*G67)/(G63+G66) -> 0.0469 | H68: =(H64+H66*H67)/(H63+H66) -> 0.0469 | I68: =(I64+I66*I67)/(I63+I66) -> 0.0469 | J68: =(J64+J66*J67)/(J63+J66) -> 0.03716531 | ... M68: =(M64+M66*M67)/(M63+M66) -> 0.03716531
A69: Gewogen contractrente (gewicht saldo) | B69: % | C69: =(C65+C66*Invoer!C18)/(C63+C66) -> 0.026502436 | D69: =(D65+D66*Invoer!D18)/(D63+D66) -> 0.026502436 | E69: =(E65+E66*Invoer!E18)/(E63+E66) -> 0.026502436 | F69: =(F65+F66*Invoer!F18)/(F63+F66) -> 0.026502436 | G69: =(G65+G66*Invoer!G18)/(G63+G66) -> 0.0469 | H69: =(H65+H66*Invoer!H18)/(H63+H66) -> 0.0469 | I69: =(I65+I66*Invoer!I18)/(I63+I66) -> 0.0469 | J69: =(J65+J66*Invoer!J18)/(J63+J66) -> 0.026502436 | ... M69: =(M65+M66*Invoer!M18)/(M63+M66) -> 0.026502436
A70: Debetrente voor de opslagfactor | B70: % | C70: =IF(Invoer!C27="Contractrente",C69,C68) -> 0.03716531 | D70: =IF(Invoer!D27="Contractrente",D69,D68) -> 0.03716531 | E70: =IF(Invoer!E27="Contractrente",E69,E68) -> 0.04894027 | F70: =IF(Invoer!F27="Contractrente",F69,F68) -> 0.03822504 | G70: =IF(Invoer!G27="Contractrente",G69,G68) -> 0.0469 | H70: =IF(Invoer!H27="Contractrente",H69,H68) -> 0.0469 | I70: =IF(Invoer!I27="Contractrente",I69,I68) -> 0.0469 | J70: =IF(Invoer!J27="Contractrente",J69,J68) -> 0.03716531 | ... M70: =IF(Invoer!M27="Contractrente",M69,M68) -> 0.03716531
A71: Opslagfactor | C71: =INDEX(Studie_factor,SUMPRODUCT(--(Studie_upTo<ROUND(C70,5)))+1) -> 1.25 | D71: =INDEX(Studie_factor,SUMPRODUCT(--(Studie_upTo<ROUND(D70,5)))+1) -> 1.25 | E71: =INDEX(Studie_factor,SUMPRODUCT(--(Studie_upTo<ROUND(E70,5)))+1) -> 1.3 | F71: =INDEX(Studie_factor,SUMPRODUCT(--(Studie_upTo<ROUND(F70,5)))+1) -> 1.25 | G71: =INDEX(Studie_factor,SUMPRODUCT(--(Studie_upTo<ROUND(G70,5)))+1) -> 1.3 | H71: =INDEX(Studie_factor,SUMPRODUCT(--(Studie_upTo<ROUND(H70,5)))+1) -> 1.3 | I71: =INDEX(Studie_factor,SUMPRODUCT(--(Studie_upTo<ROUND(I70,5)))+1) -> 1.3 | J71: =INDEX(Studie_factor,SUMPRODUCT(--(Studie_upTo<ROUND(J70,5)))+1) -> 1.25 | ... M71: =INDEX(Studie_factor,SUMPRODUCT(--(Studie_upTo<ROUND(M70,5)))+1) -> 1.25
A72: Kapitalisatierente studieschuld | B72: % | C72: =IF(Invoer!C28="Gewogen",C68,C10) -> 0.0469 | D72: =IF(Invoer!D28="Gewogen",D68,D10) -> 0.0469 | E72: =IF(Invoer!E28="Gewogen",E68,E10) -> 0.0469 | F72: =IF(Invoer!F28="Gewogen",F68,F10) -> 0.05 | G72: =IF(Invoer!G28="Gewogen",G68,G10) -> 0.0469 | H72: =IF(Invoer!H28="Gewogen",H68,H10) -> 0.0469 | I72: =IF(Invoer!I28="Gewogen",I68,I10) -> 0.0469 | J72: =IF(Invoer!J28="Gewogen",J68,J10) -> 0.0469 | ... M72: =IF(Invoer!M28="Gewogen",M68,M10) -> 0.0469
A73: Maandbedrag per geleende euro | C73: =IF(C72=0,1/360,(C72/12)/(1-(1+C72/12)^(-360))) -> 0.0051803693 | D73: =IF(D72=0,1/360,(D72/12)/(1-(1+D72/12)^(-360))) -> 0.0051803693 | E73: =IF(E72=0,1/360,(E72/12)/(1-(1+E72/12)^(-360))) -> 0.0051803693 | F73: =IF(F72=0,1/360,(F72/12)/(1-(1+F72/12)^(-360))) -> 0.0053682162 | G73: =IF(G72=0,1/360,(G72/12)/(1-(1+G72/12)^(-360))) -> 0.0051803693 | H73: =IF(H72=0,1/360,(H72/12)/(1-(1+H72/12)^(-360))) -> 0.0051803693 | I73: =IF(I72=0,1/360,(I72/12)/(1-(1+I72/12)^(-360))) -> 0.0051803693 | J73: =IF(J72=0,1/360,(J72/12)/(1-(1+J72/12)^(-360))) -> 0.0051803693 | ... M73: =IF(M72=0,1/360,(M72/12)/(1-(1+M72/12)^(-360))) -> 0.0051803693
A74: Toetslast studieschuld (termijn × factor) | B74: € p/m | C74: =Invoer!C26*C71 -> 415 | D74: =Invoer!D26*D71 -> 415 | E74: =Invoer!E26*E71 -> 431.6 | F74: =Invoer!F26*F71 -> 415 | G74: =Invoer!G26*G71 -> 0 | H74: =Invoer!H26*H71 -> 156 | I74: =Invoer!I26*I71 -> 431.6 | J74: =Invoer!J26*J71 -> 415 | ... M74: =Invoer!M26*M71 -> 415
A75: Afslag studieschuld op de hypotheek | B75: € | C75: =C74/C73 -> 80110.119 | D75: =D74/D73 -> 80110.119 | E75: =E74/E73 -> 83314.524 | F75: =F74/F73 -> 77306.871 | G75: =G74/G73 -> 0 | H75: =H74/H73 -> 30113.683 | I75: =I74/I73 -> 83314.524 | J75: =J74/J73 -> 80110.119 | ... M75: =M74/M73 -> 80110.119
A76: 6. Leencapaciteit op inkomen (alles als nieuw geld tegen de toetsrente)
A77: Inkomensrij (naar beneden op € 1.000) | B77: € | C77: =INT(C9/1000)*1000 -> 225000 | D77: =INT(D9/1000)*1000 -> 225000 | E77: =INT(E9/1000)*1000 -> 225000 | F77: =INT(F9/1000)*1000 -> 225000 | G77: =INT(G9/1000)*1000 -> 60000 | H77: =INT(H9/1000)*1000 -> 150000 | I77: =INT(I9/1000)*1000 -> 225000 | J77: =INT(J9/1000)*1000 -> 225000 | ... M77: =INT(M9/1000)*1000 -> 225000
A78: Rentekolom (1 = ≤ 1,5% … 10 = 6,0%) | C78: =MIN(10,MAX(1,ROUNDUP(ROUND(C10*100,3)/0.5-0.000000001,0)-2)) -> 8 | D78: =MIN(10,MAX(1,ROUNDUP(ROUND(D10*100,3)/0.5-0.000000001,0)-2)) -> 8 | E78: =MIN(10,MAX(1,ROUNDUP(ROUND(E10*100,3)/0.5-0.000000001,0)-2)) -> 8 | F78: =MIN(10,MAX(1,ROUNDUP(ROUND(F10*100,3)/0.5-0.000000001,0)-2)) -> 8 | G78: =MIN(10,MAX(1,ROUNDUP(ROUND(G10*100,3)/0.5-0.000000001,0)-2)) -> 8 | H78: =MIN(10,MAX(1,ROUNDUP(ROUND(H10*100,3)/0.5-0.000000001,0)-2)) -> 8 | I78: =MIN(10,MAX(1,ROUNDUP(ROUND(I10*100,3)/0.5-0.000000001,0)-2)) -> 8 | J78: =MIN(10,MAX(1,ROUNDUP(ROUND(J10*100,3)/0.5-0.000000001,0)-2)) -> 8 | ... M78: =MIN(10,MAX(1,ROUNDUP(ROUND(M10*100,3)/0.5-0.000000001,0)-2)) -> 8
A79: Inkomen binnen tabelbereik | B79: € | C79: =MIN(MAX(C77,INDEX(T1_Inkomen,1)),INDEX(T1_Inkomen,12)) -> 125000 | D79: =MIN(MAX(D77,INDEX(T1_Inkomen,1)),INDEX(T1_Inkomen,12)) -> 125000 | E79: =MIN(MAX(E77,INDEX(T1_Inkomen,1)),INDEX(T1_Inkomen,12)) -> 125000 | F79: =MIN(MAX(F77,INDEX(T1_Inkomen,1)),INDEX(T1_Inkomen,12)) -> 125000 | G79: =MIN(MAX(G77,INDEX(T1_Inkomen,1)),INDEX(T1_Inkomen,12)) -> 60000 | H79: =MIN(MAX(H77,INDEX(T1_Inkomen,1)),INDEX(T1_Inkomen,12)) -> 125000 | I79: =MIN(MAX(I77,INDEX(T1_Inkomen,1)),INDEX(T1_Inkomen,12)) -> 125000 | J79: =MIN(MAX(J77,INDEX(T1_Inkomen,1)),INDEX(T1_Inkomen,12)) -> 125000 | ... M79: =MIN(MAX(M77,INDEX(T1_Inkomen,1)),INDEX(T1_Inkomen,12)) -> 125000
A80: Tabelrij (interpolatie) | C80: =MIN(MATCH(C79,T1_Inkomen,1),11) -> 11 | D80: =MIN(MATCH(D79,T1_Inkomen,1),11) -> 11 | E80: =MIN(MATCH(E79,T1_Inkomen,1),11) -> 11 | F80: =MIN(MATCH(F79,T1_Inkomen,1),11) -> 11 | G80: =MIN(MATCH(G79,T1_Inkomen,1),11) -> 6 | H80: =MIN(MATCH(H79,T1_Inkomen,1),11) -> 11 | I80: =MIN(MATCH(I79,T1_Inkomen,1),11) -> 11 | J80: =MIN(MATCH(J79,T1_Inkomen,1),11) -> 11 | ... M80: =MIN(MATCH(M79,T1_Inkomen,1),11) -> 11
A81: Woonquote (tabel 1) | B81: % | C81: =INDEX(T1_Tabel,C80,C78)+(C79-INDEX(T1_Inkomen,C80))/(INDEX(T1_Inkomen,C80+1)-INDEX(T1_Inkomen,C80))*(INDEX(T1_Tabel,C80+1,C78)-INDEX(T1_Tabel,C80,C78)) -> 0.292 | D81: =INDEX(T1_Tabel,D80,D78)+(D79-INDEX(T1_Inkomen,D80))/(INDEX(T1_Inkomen,D80+1)-INDEX(T1_Inkomen,D80))*(INDEX(T1_Tabel,D80+1,D78)-INDEX(T1_Tabel,D80,D78)) -> 0.292 | E81: =INDEX(T1_Tabel,E80,E78)+(E79-INDEX(T1_Inkomen,E80))/(INDEX(T1_Inkomen,E80+1)-INDEX(T1_Inkomen,E80))*(INDEX(T1_Tabel,E80+1,E78)-INDEX(T1_Tabel,E80,E78)) -> 0.292 | F81: =INDEX(T1_Tabel,F80,F78)+(F79-INDEX(T1_Inkomen,F80))/(INDEX(T1_Inkomen,F80+1)-INDEX(T1_Inkomen,F80))*(INDEX(T1_Tabel,F80+1,F78)-INDEX(T1_Tabel,F80,F78)) -> 0.292 | G81: =INDEX(T1_Tabel,G80,G78)+(G79-INDEX(T1_Inkomen,G80))/(INDEX(T1_Inkomen,G80+1)-INDEX(T1_Inkomen,G80))*(INDEX(T1_Tabel,G80+1,G78)-INDEX(T1_Tabel,G80,G78)) -> 0.246 | H81: =INDEX(T1_Tabel,H80,H78)+(H79-INDEX(T1_Inkomen,H80))/(INDEX(T1_Inkomen,H80+1)-INDEX(T1_Inkomen,H80))*(INDEX(T1_Tabel,H80+1,H78)-INDEX(T1_Tabel,H80,H78)) -> 0.292 | I81: =INDEX(T1_Tabel,I80,I78)+(I79-INDEX(T1_Inkomen,I80))/(INDEX(T1_Inkomen,I80+1)-INDEX(T1_Inkomen,I80))*(INDEX(T1_Tabel,I80+1,I78)-INDEX(T1_Tabel,I80,I78)) -> 0.292 | J81: =INDEX(T1_Tabel,J80,J78)+(J79-INDEX(T1_Inkomen,J80))/(INDEX(T1_Inkomen,J80+1)-INDEX(T1_Inkomen,J80))*(INDEX(T1_Tabel,J80+1,J78)-INDEX(T1_Tabel,J80,J78)) -> 0.292 | ... M81: =INDEX(T1_Tabel,M80,M78)+(M79-INDEX(T1_Inkomen,M80))/(INDEX(T1_Inkomen,M80+1)-INDEX(T1_Inkomen,M80))*(INDEX(T1_Tabel,M80+1,M78)-INDEX(T1_Tabel,M80,M78)) -> 0.292
A82: Maximale woonlast per maand | B82: € p/m | C82: =C81*C9/12 -> 5475 | D82: =D81*D9/12 -> 5475 | E82: =E81*E9/12 -> 5475 | F82: =F81*F9/12 -> 5475 | G82: =G81*G9/12 -> 1230 | H82: =H81*H9/12 -> 3650 | I82: =I81*I9/12 -> 5475 | J82: =J81*J9/12 -> 5475 | ... M82: =M81*M9/12 -> 5475
A83: Leencapaciteit voor schulden | B83: € | C83: =C82*C11 -> 1056874.5 | D83: =D82*D11 -> 1056874.5 | E83: =E82*E11 -> 1056874.5 | F83: =F82*F11 -> 1019891.9 | G83: =G82*G11 -> 237434.81 | H83: =H82*H11 -> 704582.98 | I83: =I82*I11 -> 1056874.5 | J83: =J82*J11 -> 1056874.5 | ... M83: =M82*M11 -> 1056874.5
A84: Na schulden en tweede woning | B84: € | C84: =MAX(0,C82-C18)*C11 -> 1019588.4 | D84: =MAX(0,D82-D18)*D11 -> 1019588.4 | E84: =MAX(0,E82-E18)*E11 -> 1019588.4 | F84: =MAX(0,F82-F18)*F11 -> 983910.51 | G84: =MAX(0,G82-G18)*G11 -> 237434.81 | H84: =MAX(0,H82-H18)*H11 -> 704582.98 | I84: =MAX(0,I82-I18)*I11 -> 1019588.4 | J84: =MAX(0,J82-J18)*J11 -> 1056874.5 | ... M84: =MAX(0,M82-M18)*M11 -> 1019588.4
A85: Na studieschuld | B85: € | C85: =MAX(0,C84-C75) -> 939478.28 | D85: =MAX(0,D84-D75) -> 939478.28 | E85: =MAX(0,E84-E75) -> 936273.87 | F85: =MAX(0,F84-F75) -> 906603.64 | G85: =MAX(0,G84-G75) -> 237434.81 | H85: =MAX(0,H84-H75) -> 674469.29 | I85: =MAX(0,I84-I75) -> 936273.87 | J85: =MAX(0,J84-J75) -> 976764.35 | ... M85: =MAX(0,M84-M75) -> 939478.28
A86: Alleenstaandenbedrag | B86: € | C86: =IF(C7=0,IF(C9>=Alleenstaand_min,Alleenstaand_bedrag,0),0) -> 0 | D86: =IF(D7=0,IF(D9>=Alleenstaand_min,Alleenstaand_bedrag,0),0) -> 0 | E86: =IF(E7=0,IF(E9>=Alleenstaand_min,Alleenstaand_bedrag,0),0) -> 0 | F86: =IF(F7=0,IF(F9>=Alleenstaand_min,Alleenstaand_bedrag,0),0) -> 0 | G86: =IF(G7=0,IF(G9>=Alleenstaand_min,Alleenstaand_bedrag,0),0) -> 17000 | H86: =IF(H7=0,IF(H9>=Alleenstaand_min,Alleenstaand_bedrag,0),0) -> 0 | I86: =IF(I7=0,IF(I9>=Alleenstaand_min,Alleenstaand_bedrag,0),0) -> 0 | J86: =IF(J7=0,IF(J9>=Alleenstaand_min,Alleenstaand_bedrag,0),0) -> 0 | ... M86: =IF(M7=0,IF(M9>=Alleenstaand_min,Alleenstaand_bedrag,0),0) -> 0
A87: Energielabelbonus | B87: € | C87: =INDEX(Energie_bonus,MATCH(Invoer!C16,Energie_label,0)) -> 10000 | D87: =INDEX(Energie_bonus,MATCH(Invoer!D16,Energie_label,0)) -> 10000 | E87: =INDEX(Energie_bonus,MATCH(Invoer!E16,Energie_label,0)) -> 10000 | F87: =INDEX(Energie_bonus,MATCH(Invoer!F16,Energie_label,0)) -> 10000 | G87: =INDEX(Energie_bonus,MATCH(Invoer!G16,Energie_label,0)) -> 5000 | H87: =INDEX(Energie_bonus,MATCH(Invoer!H16,Energie_label,0)) -> 10000 | I87: =INDEX(Energie_bonus,MATCH(Invoer!I16,Energie_label,0)) -> 10000 | J87: =INDEX(Energie_bonus,MATCH(Invoer!J16,Energie_label,0)) -> 10000 | ... M87: =INDEX(Energie_bonus,MATCH(Invoer!M16,Energie_label,0)) -> 10000
A88: 7. AOW-toets (pensioeninkomen, tabel 2)
A89: Aanvrager 1 binnen 10 jaar van AOW (1 = ja) | C89: =IF(Invoer!C12>=AOW_drempel,1,0) -> 0 | D89: =IF(Invoer!D12>=AOW_drempel,1,0) -> 0 | E89: =IF(Invoer!E12>=AOW_drempel,1,0) -> 0 | F89: =IF(Invoer!F12>=AOW_drempel,1,0) -> 0 | G89: =IF(Invoer!G12>=AOW_drempel,1,0) -> 0 | H89: =IF(Invoer!H12>=AOW_drempel,1,0) -> 0 | I89: =IF(Invoer!I12>=AOW_drempel,1,0) -> 0 | J89: =IF(Invoer!J12>=AOW_drempel,1,0) -> 1 | ... M89: =IF(Invoer!M12>=AOW_drempel,1,0) -> 0
A90: Aanvrager 2 binnen 10 jaar van AOW (1 = ja) | C90: =C7*IF(Invoer!C13>=AOW_drempel,1,0) -> 0 | D90: =D7*IF(Invoer!D13>=AOW_drempel,1,0) -> 0 | E90: =E7*IF(Invoer!E13>=AOW_drempel,1,0) -> 0 | F90: =F7*IF(Invoer!F13>=AOW_drempel,1,0) -> 0 | G90: =G7*IF(Invoer!G13>=AOW_drempel,1,0) -> 0 | H90: =H7*IF(Invoer!H13>=AOW_drempel,1,0) -> 0 | I90: =I7*IF(Invoer!I13>=AOW_drempel,1,0) -> 0 | J90: =J7*IF(Invoer!J13>=AOW_drempel,1,0) -> 0 | ... M90: =M7*IF(Invoer!M13>=AOW_drempel,1,0) -> 0
A91: Pensioeninkomen ontbreekt (1 = ja) | C91: =IF(OR(AND(C89=1,Invoer!C14<=0),AND(C90=1,Invoer!C15<=0)),1,0) -> 0 | D91: =IF(OR(AND(D89=1,Invoer!D14<=0),AND(D90=1,Invoer!D15<=0)),1,0) -> 0 | E91: =IF(OR(AND(E89=1,Invoer!E14<=0),AND(E90=1,Invoer!E15<=0)),1,0) -> 0 | F91: =IF(OR(AND(F89=1,Invoer!F14<=0),AND(F90=1,Invoer!F15<=0)),1,0) -> 0 | G91: =IF(OR(AND(G89=1,Invoer!G14<=0),AND(G90=1,Invoer!G15<=0)),1,0) -> 0 | H91: =IF(OR(AND(H89=1,Invoer!H14<=0),AND(H90=1,Invoer!H15<=0)),1,0) -> 0 | I91: =IF(OR(AND(I89=1,Invoer!I14<=0),AND(I90=1,Invoer!I15<=0)),1,0) -> 0 | J91: =IF(OR(AND(J89=1,Invoer!J14<=0),AND(J90=1,Invoer!J15<=0)),1,0) -> 0 | ... M91: =IF(OR(AND(M89=1,Invoer!M14<=0),AND(M90=1,Invoer!M15<=0)),1,0) -> 0
A92: AOW-toets actief (1 = ja) | C92: =IF(C89+C90>0,1,0)*(1-C91) -> 0 | D92: =IF(D89+D90>0,1,0)*(1-D91) -> 0 | E92: =IF(E89+E90>0,1,0)*(1-E91) -> 0 | F92: =IF(F89+F90>0,1,0)*(1-F91) -> 0 | G92: =IF(G89+G90>0,1,0)*(1-G91) -> 0 | H92: =IF(H89+H90>0,1,0)*(1-H91) -> 0 | I92: =IF(I89+I90>0,1,0)*(1-I91) -> 0 | J92: =IF(J89+J90>0,1,0)*(1-J91) -> 1 | ... M92: =IF(M89+M90>0,1,0)*(1-M91) -> 0
A93: Toetsinkomen in het pensioenscenario | B93: € | C93: =IF(C89=1,Invoer!C14,Invoer!C10)+C7*IF(C90=1,Invoer!C15,Invoer!C11) -> 225000 | D93: =IF(D89=1,Invoer!D14,Invoer!D10)+D7*IF(D90=1,Invoer!D15,Invoer!D11) -> 225000 | E93: =IF(E89=1,Invoer!E14,Invoer!E10)+E7*IF(E90=1,Invoer!E15,Invoer!E11) -> 225000 | F93: =IF(F89=1,Invoer!F14,Invoer!F10)+F7*IF(F90=1,Invoer!F15,Invoer!F11) -> 225000 | G93: =IF(G89=1,Invoer!G14,Invoer!G10)+G7*IF(G90=1,Invoer!G15,Invoer!G11) -> 60000 | H93: =IF(H89=1,Invoer!H14,Invoer!H10)+H7*IF(H90=1,Invoer!H15,Invoer!H11) -> 150000 | I93: =IF(I89=1,Invoer!I14,Invoer!I10)+I7*IF(I90=1,Invoer!I15,Invoer!I11) -> 225000 | J93: =IF(J89=1,Invoer!J14,Invoer!J10)+J7*IF(J90=1,Invoer!J15,Invoer!J11) -> 147000 | ... M93: =IF(M89=1,Invoer!M14,Invoer!M10)+M7*IF(M90=1,Invoer!M15,Invoer!M11) -> 225000
A94: Pensioeninkomen binnen tabelbereik | B94: € | C94: =MIN(MAX(INT(C93/1000)*1000,INDEX(T2_Inkomen,1)),INDEX(T2_Inkomen,12)) -> 110000 | D94: =MIN(MAX(INT(D93/1000)*1000,INDEX(T2_Inkomen,1)),INDEX(T2_Inkomen,12)) -> 110000 | E94: =MIN(MAX(INT(E93/1000)*1000,INDEX(T2_Inkomen,1)),INDEX(T2_Inkomen,12)) -> 110000 | F94: =MIN(MAX(INT(F93/1000)*1000,INDEX(T2_Inkomen,1)),INDEX(T2_Inkomen,12)) -> 110000 | G94: =MIN(MAX(INT(G93/1000)*1000,INDEX(T2_Inkomen,1)),INDEX(T2_Inkomen,12)) -> 60000 | H94: =MIN(MAX(INT(H93/1000)*1000,INDEX(T2_Inkomen,1)),INDEX(T2_Inkomen,12)) -> 110000 | I94: =MIN(MAX(INT(I93/1000)*1000,INDEX(T2_Inkomen,1)),INDEX(T2_Inkomen,12)) -> 110000 | J94: =MIN(MAX(INT(J93/1000)*1000,INDEX(T2_Inkomen,1)),INDEX(T2_Inkomen,12)) -> 110000 | ... M94: =MIN(MAX(INT(M93/1000)*1000,INDEX(T2_Inkomen,1)),INDEX(T2_Inkomen,12)) -> 110000
A95: Tabelrij (interpolatie) | C95: =MIN(MATCH(C94,T2_Inkomen,1),11) -> 11 | D95: =MIN(MATCH(D94,T2_Inkomen,1),11) -> 11 | E95: =MIN(MATCH(E94,T2_Inkomen,1),11) -> 11 | F95: =MIN(MATCH(F94,T2_Inkomen,1),11) -> 11 | G95: =MIN(MATCH(G94,T2_Inkomen,1),11) -> 7 | H95: =MIN(MATCH(H94,T2_Inkomen,1),11) -> 11 | I95: =MIN(MATCH(I94,T2_Inkomen,1),11) -> 11 | J95: =MIN(MATCH(J94,T2_Inkomen,1),11) -> 11 | ... M95: =MIN(MATCH(M94,T2_Inkomen,1),11) -> 11
A96: Woonquote (tabel 2) | B96: % | C96: =INDEX(T2_Tabel,C95,C78)+(C94-INDEX(T2_Inkomen,C95))/(INDEX(T2_Inkomen,C95+1)-INDEX(T2_Inkomen,C95))*(INDEX(T2_Tabel,C95+1,C78)-INDEX(T2_Tabel,C95,C78)) -> 0.375 | D96: =INDEX(T2_Tabel,D95,D78)+(D94-INDEX(T2_Inkomen,D95))/(INDEX(T2_Inkomen,D95+1)-INDEX(T2_Inkomen,D95))*(INDEX(T2_Tabel,D95+1,D78)-INDEX(T2_Tabel,D95,D78)) -> 0.375 | E96: =INDEX(T2_Tabel,E95,E78)+(E94-INDEX(T2_Inkomen,E95))/(INDEX(T2_Inkomen,E95+1)-INDEX(T2_Inkomen,E95))*(INDEX(T2_Tabel,E95+1,E78)-INDEX(T2_Tabel,E95,E78)) -> 0.375 | F96: =INDEX(T2_Tabel,F95,F78)+(F94-INDEX(T2_Inkomen,F95))/(INDEX(T2_Inkomen,F95+1)-INDEX(T2_Inkomen,F95))*(INDEX(T2_Tabel,F95+1,F78)-INDEX(T2_Tabel,F95,F78)) -> 0.375 | G96: =INDEX(T2_Tabel,G95,G78)+(G94-INDEX(T2_Inkomen,G95))/(INDEX(T2_Inkomen,G95+1)-INDEX(T2_Inkomen,G95))*(INDEX(T2_Tabel,G95+1,G78)-INDEX(T2_Tabel,G95,G78)) -> 0.341 | H96: =INDEX(T2_Tabel,H95,H78)+(H94-INDEX(T2_Inkomen,H95))/(INDEX(T2_Inkomen,H95+1)-INDEX(T2_Inkomen,H95))*(INDEX(T2_Tabel,H95+1,H78)-INDEX(T2_Tabel,H95,H78)) -> 0.375 | I96: =INDEX(T2_Tabel,I95,I78)+(I94-INDEX(T2_Inkomen,I95))/(INDEX(T2_Inkomen,I95+1)-INDEX(T2_Inkomen,I95))*(INDEX(T2_Tabel,I95+1,I78)-INDEX(T2_Tabel,I95,I78)) -> 0.375 | J96: =INDEX(T2_Tabel,J95,J78)+(J94-INDEX(T2_Inkomen,J95))/(INDEX(T2_Inkomen,J95+1)-INDEX(T2_Inkomen,J95))*(INDEX(T2_Tabel,J95+1,J78)-INDEX(T2_Tabel,J95,J78)) -> 0.375 | ... M96: =INDEX(T2_Tabel,M95,M78)+(M94-INDEX(T2_Inkomen,M95))/(INDEX(T2_Inkomen,M95+1)-INDEX(T2_Inkomen,M95))*(INDEX(T2_Tabel,M95+1,M78)-INDEX(T2_Tabel,M95,M78)) -> 0.375
A97: Leencapaciteit op pensioeninkomen na schulden en studieschuld | B97: € | C97: =MAX(0,MAX(0,C96*C93/12-C18)*C11-C75) -> 1239891.2 | D97: =MAX(0,MAX(0,D96*D93/12-D18)*D11-D75) -> 1239891.2 | E97: =MAX(0,MAX(0,E96*E93/12-E18)*E11-E75) -> 1236686.8 | F97: =MAX(0,MAX(0,F96*F93/12-F18)*F11-F75) -> 1196504.4 | G97: =MAX(0,MAX(0,G96*G93/12-G18)*G11-G75) -> 329127.12 | H97: =MAX(0,MAX(0,H96*H93/12-H18)*H11-H75) -> 874744.59 | I97: =MAX(0,MAX(0,I96*I93/12-I18)*I11-I75) -> 1236686.8 | J97: =MAX(0,MAX(0,J96*J93/12-J18)*J11-J75) -> 806650.99 | ... M97: =MAX(0,MAX(0,M96*M93/12-M18)*M11-M75) -> 1239891.2
A98: Alleenstaandenbedrag in het pensioenscenario | B98: € | C98: =IF(C7=0,IF(C93>=Alleenstaand_min_AOW,Alleenstaand_bedrag,0),0) -> 0 | D98: =IF(D7=0,IF(D93>=Alleenstaand_min_AOW,Alleenstaand_bedrag,0),0) -> 0 | E98: =IF(E7=0,IF(E93>=Alleenstaand_min_AOW,Alleenstaand_bedrag,0),0) -> 0 | F98: =IF(F7=0,IF(F93>=Alleenstaand_min_AOW,Alleenstaand_bedrag,0),0) -> 0 | G98: =IF(G7=0,IF(G93>=Alleenstaand_min_AOW,Alleenstaand_bedrag,0),0) -> 17000 | H98: =IF(H7=0,IF(H93>=Alleenstaand_min_AOW,Alleenstaand_bedrag,0),0) -> 0 | I98: =IF(I7=0,IF(I93>=Alleenstaand_min_AOW,Alleenstaand_bedrag,0),0) -> 0 | J98: =IF(J7=0,IF(J93>=Alleenstaand_min_AOW,Alleenstaand_bedrag,0),0) -> 0 | ... M98: =IF(M7=0,IF(M93>=Alleenstaand_min_AOW,Alleenstaand_bedrag,0),0) -> 0
A99: Pensioenscenario bindend (1 = ja) | C99: =IF(AND(C92=1,C97+C98<C85+C86),1,0) -> 0 | D99: =IF(AND(D92=1,D97+D98<D85+D86),1,0) -> 0 | E99: =IF(AND(E92=1,E97+E98<E85+E86),1,0) -> 0 | F99: =IF(AND(F92=1,F97+F98<F85+F86),1,0) -> 0 | G99: =IF(AND(G92=1,G97+G98<G85+G86),1,0) -> 0 | H99: =IF(AND(H92=1,H97+H98<H85+H86),1,0) -> 0 | I99: =IF(AND(I92=1,I97+I98<I85+I86),1,0) -> 0 | J99: =IF(AND(J92=1,J97+J98<J85+J86),1,0) -> 1 | ... M99: =IF(AND(M92=1,M97+M98<M85+M86),1,0) -> 0
A100: Leencapaciteit na AOW-toets | B100: € | C100: =IF(C99=1,C97+C98-C86,C85) -> 939478.28 | D100: =IF(D99=1,D97+D98-D86,D85) -> 939478.28 | E100: =IF(E99=1,E97+E98-E86,E85) -> 936273.87 | F100: =IF(F99=1,F97+F98-F86,F85) -> 906603.64 | G100: =IF(G99=1,G97+G98-G86,G85) -> 237434.81 | H100: =IF(H99=1,H97+H98-H86,H85) -> 674469.29 | I100: =IF(I99=1,I97+I98-I86,I85) -> 936273.87 | J100: =IF(J99=1,J97+J98-J86,J85) -> 806650.99 | ... M100: =IF(M99=1,M97+M98-M86,M85) -> 939478.28
A101: Maximale hypotheek o.b.v. inkomen (alles tegen toetsrente) | B101: € | C101: =MAX(0,C100+C87+C86) -> 949478.28 | D101: =MAX(0,D100+D87+D86) -> 949478.28 | E101: =MAX(0,E100+E87+E86) -> 946273.87 | F101: =MAX(0,F100+F87+F86) -> 916603.64 | G101: =MAX(0,G100+G87+G86) -> 259434.81 | H101: =MAX(0,H100+H87+H86) -> 684469.29 | I101: =MAX(0,I100+I87+I86) -> 946273.87 | J101: =MAX(0,J100+J87+J86) -> 816650.99 | ... M101: =MAX(0,M100+M87+M86) -> 949478.28
...

Sheet Solver
A1: Solver: samengestelde toets met gewogen toetsrente
A2: De woonquote hangt af van de gewogen toetsrente van alle leningdelen, en die beweegt mee met het nieuwe bedrag. Per rentekolom wordt het bereik van bedragen bepaald waarin die kolom geldt; het hoogste haalbare bedrag wint.
A4: Stap | B4: Eenheid | C4: =Invoer!C4 -> 1 | D4: =Invoer!D4 -> 2 | E4: =Invoer!E4 -> 3 | F4: =Invoer!F4 -> 4 | G4: =Invoer!G4 -> 5 | H4: =Invoer!H4 -> 6 | I4: =Invoer!I4 -> 7 | J4: =Invoer!J4 -> 8 | ... M4: =Invoer!M4 -> 11
A5: Blok A: inkomensscenario (tabel 1)
A6: Toetsinkomen | B6: € | C6: =Berekening!C9 -> 225000 | D6: =Berekening!D9 -> 225000 | E6: =Berekening!E9 -> 225000 | F6: =Berekening!F9 -> 225000 | G6: =Berekening!G9 -> 60000 | H6: =Berekening!H9 -> 150000 | I6: =Berekening!I9 -> 225000 | J6: =Berekening!J9 -> 225000 | ... M6: =Berekening!M9 -> 225000
A7: Bonussen buiten de woonlast (energie + alleenstaand) | B7: € | C7: =Berekening!C87+Berekening!C86 -> 10000 | D7: =Berekening!D87+Berekening!D86 -> 10000 | E7: =Berekening!E87+Berekening!E86 -> 10000 | F7: =Berekening!F87+Berekening!F86 -> 10000 | G7: =Berekening!G87+Berekening!G86 -> 22000 | H7: =Berekening!H87+Berekening!H86 -> 10000 | I7: =Berekening!I87+Berekening!I86 -> 10000 | J7: =Berekening!J87+Berekening!J86 -> 10000 | ... M7: =Berekening!M87+Berekening!M86 -> 10000
A8: Kolom 1: woonquote | B8: % | C8: =INDEX(T1_Tabel,Berekening!C80,1)+(Berekening!C79-INDEX(T1_Inkomen,Berekening!C80))/(INDEX(T1_Inkomen,Berekening!C80+1)-INDEX(T1_Inkomen,Berekening!C80))*(INDEX(T1_Tabel,Berekening!C80+1,1)-INDEX(T1_Tabel,Berekening!C80,1)) -> 0.222 | D8: =INDEX(T1_Tabel,Berekening!D80,1)+(Berekening!D79-INDEX(T1_Inkomen,Berekening!D80))/(INDEX(T1_Inkomen,Berekening!D80+1)-INDEX(T1_Inkomen,Berekening!D80))*(INDEX(T1_Tabel,Berekening!D80+1,1)-INDEX(T1_Tabel,Berekening!D80,1)) -> 0.222 | E8: =INDEX(T1_Tabel,Berekening!E80,1)+(Berekening!E79-INDEX(T1_Inkomen,Berekening!E80))/(INDEX(T1_Inkomen,Berekening!E80+1)-INDEX(T1_Inkomen,Berekening!E80))*(INDEX(T1_Tabel,Berekening!E80+1,1)-INDEX(T1_Tabel,Berekening!E80,1)) -> 0.222 | F8: =INDEX(T1_Tabel,Berekening!F80,1)+(Berekening!F79-INDEX(T1_Inkomen,Berekening!F80))/(INDEX(T1_Inkomen,Berekening!F80+1)-INDEX(T1_Inkomen,Berekening!F80))*(INDEX(T1_Tabel,Berekening!F80+1,1)-INDEX(T1_Tabel,Berekening!F80,1)) -> 0.222 | G8: =INDEX(T1_Tabel,Berekening!G80,1)+(Berekening!G79-INDEX(T1_Inkomen,Berekening!G80))/(INDEX(T1_Inkomen,Berekening!G80+1)-INDEX(T1_Inkomen,Berekening!G80))*(INDEX(T1_Tabel,Berekening!G80+1,1)-INDEX(T1_Tabel,Berekening!G80,1)) -> 0.177 | H8: =INDEX(T1_Tabel,Berekening!H80,1)+(Berekening!H79-INDEX(T1_Inkomen,Berekening!H80))/(INDEX(T1_Inkomen,Berekening!H80+1)-INDEX(T1_Inkomen,Berekening!H80))*(INDEX(T1_Tabel,Berekening!H80+1,1)-INDEX(T1_Tabel,Berekening!H80,1)) -> 0.222 | I8: =INDEX(T1_Tabel,Berekening!I80,1)+(Berekening!I79-INDEX(T1_Inkomen,Berekening!I80))/(INDEX(T1_Inkomen,Berekening!I80+1)-INDEX(T1_Inkomen,Berekening!I80))*(INDEX(T1_Tabel,Berekening!I80+1,1)-INDEX(T1_Tabel,Berekening!I80,1)) -> 0.222 | J8: =INDEX(T1_Tabel,Berekening!J80,1)+(Berekening!J79-INDEX(T1_Inkomen,Berekening!J80))/(INDEX(T1_Inkomen,Berekening!J80+1)-INDEX(T1_Inkomen,Berekening!J80))*(INDEX(T1_Tabel,Berekening!J80+1,1)-INDEX(T1_Tabel,Berekening!J80,1)) -> 0.222 | ... M8: =INDEX(T1_Tabel,Berekening!M80,1)+(Berekening!M79-INDEX(T1_Inkomen,Berekening!M80))/(INDEX(T1_Inkomen,Berekening!M80+1)-INDEX(T1_Inkomen,Berekening!M80))*(INDEX(T1_Tabel,Berekening!M80+1,1)-INDEX(T1_Tabel,Berekening!M80,1)) -> 0.222
A9: Kolom 1: bedrag als de woonquote van deze kolom geldt | B9: € | C9: =MAX(0,(C8*C6/12-Berekening!C18-Berekening!C44)*Berekening!C11-Berekening!C75+C7) -> 140141.65 | D9: =MAX(0,(D8*D6/12-Berekening!D18-Berekening!D44)*Berekening!D11-Berekening!D75+D7) -> 169193.2 | E9: =MAX(0,(E8*E6/12-Berekening!E18-Berekening!E44)*Berekening!E11-Berekening!E75+E7) -> 17494.106 | F9: =MAX(0,(F8*F6/12-Berekening!F18-Berekening!F44)*Berekening!F11-Berekening!F75+F7) -> 135587.68 | G9: =MAX(0,(G8*G6/12-Berekening!G18-Berekening!G44)*Berekening!G11-Berekening!G75+G7) -> 192837.24 | H9: =MAX(0,(H8*H6/12-Berekening!H18-Berekening!H44)*Berekening!H11-Berekening!H75+H7) -> 515562.42 | I9: =MAX(0,(I8*I6/12-Berekening!I18-Berekening!I44)*Berekening!I11-Berekening!I75+I7) -> 692913.56 | J9: =MAX(0,(J8*J6/12-Berekening!J18-Berekening!J44)*Berekening!J11-Berekening!J75+J7) -> 177427.72 | ... M9: =MAX(0,(M8*M6/12-Berekening!M18-Berekening!M44)*Berekening!M11-Berekening!M75+M7) -> 140141.65
A10: Kolom 1: laagste bedrag waarbij de gewogen rente in deze kolom valt | B10: € | C10: =MAX(0,IF((INDEX(T1_Rente,1)+0.000005)>Berekening!C10,(Berekening!C45-(INDEX(T1_Rente,1)+0.000005)*Berekening!C46)/(360*((INDEX(T1_Rente,1)+0.000005)-Berekening!C10)),IF((INDEX(T1_Rente,1)+0.000005)=Berekening!C10,IF(Berekening!C45-(INDEX(T1_Rente,1)+0.000005)*Berekening!C46<=0,-1000000000000,1000000000000),-1000000000000))) -> 0 | D10: =MAX(0,IF((INDEX(T1_Rente,1)+0.000005)>Berekening!D10,(Berekening!D45-(INDEX(T1_Rente,1)+0.000005)*Berekening!D46)/(360*((INDEX(T1_Rente,1)+0.000005)-Berekening!D10)),IF((INDEX(T1_Rente,1)+0.000005)=Berekening!D10,IF(Berekening!D45-(INDEX(T1_Rente,1)+0.000005)*Berekening!D46<=0,-1000000000000,1000000000000),-1000000000000))) -> 0 | E10: =MAX(0,IF((INDEX(T1_Rente,1)+0.000005)>Berekening!E10,(Berekening!E45-(INDEX(T1_Rente,1)+0.000005)*Berekening!E46)/(360*((INDEX(T1_Rente,1)+0.000005)-Berekening!E10)),IF((INDEX(T1_Rente,1)+0.000005)=Berekening!E10,IF(Berekening!E45-(INDEX(T1_Rente,1)+0.000005)*Berekening!E46<=0,-1000000000000,1000000000000),-1000000000000))) -> 0 | F10: =MAX(0,IF((INDEX(T1_Rente,1)+0.000005)>Berekening!F10,(Berekening!F45-(INDEX(T1_Rente,1)+0.000005)*Berekening!F46)/(360*((INDEX(T1_Rente,1)+0.000005)-Berekening!F10)),IF((INDEX(T1_Rente,1)+0.000005)=Berekening!F10,IF(Berekening!F45-(INDEX(T1_Rente,1)+0.000005)*Berekening!F46<=0,-1000000000000,1000000000000),-1000000000000))) -> 0 | G10: =MAX(0,IF((INDEX(T1_Rente,1)+0.000005)>Berekening!G10,(Berekening!G45-(INDEX(T1_Rente,1)+0.000005)*Berekening!G46)/(360*((INDEX(T1_Rente,1)+0.000005)-Berekening!G10)),IF((INDEX(T1_Rente,1)+0.000005)=Berekening!G10,IF(Berekening!G45-(INDEX(T1_Rente,1)+0.000005)*Berekening!G46<=0,-1000000000000,1000000000000),-1000000000000))) -> 0 | H10: =MAX(0,IF((INDEX(T1_Rente,1)+0.000005)>Berekening!H10,(Berekening!H45-(INDEX(T1_Rente,1)+0.000005)*Berekening!H46)/(360*((INDEX(T1_Rente,1)+0.000005)-Berekening!H10)),IF((INDEX(T1_Rente,1)+0.000005)=Berekening!H10,IF(Berekening!H45-(INDEX(T1_Rente,1)+0.000005)*Berekening!H46<=0,-1000000000000,1000000000000),-1000000000000))) -> 0 | I10: =MAX(0,IF((INDEX(T1_Rente,1)+0.000005)>Berekening!I10,(Berekening!I45-(INDEX(T1_Rente,1)+0.000005)*Berekening!I46)/(360*((INDEX(T1_Rente,1)+0.000005)-Berekening!I10)),IF((INDEX(T1_Rente,1)+0.000005)=Berekening!I10,IF(Berekening!I45-(INDEX(T1_Rente,1)+0.000005)*Berekening!I46<=0,-1000000000000,1000000000000),-1000000000000))) -> 0 | J10: =MAX(0,IF((INDEX(T1_Rente,1)+0.000005)>Berekening!J10,(Berekening!J45-(INDEX(T1_Rente,1)+0.000005)*Berekening!J46)/(360*((INDEX(T1_Rente,1)+0.000005)-Berekening!J10)),IF((INDEX(T1_Rente,1)+0.000005)=Berekening!J10,IF(Berekening!J45-(INDEX(T1_Rente,1)+0.000005)*Berekening!J46<=0,-1000000000000,1000000000000),-1000000000000))) -> 0 | ... M10: =MAX(0,IF((INDEX(T1_Rente,1)+0.000005)>Berekening!M10,(Berekening!M45-(INDEX(T1_Rente,1)+0.000005)*Berekening!M46)/(360*((INDEX(T1_Rente,1)+0.000005)-Berekening!M10)),IF((INDEX(T1_Rente,1)+0.000005)=Berekening!M10,IF(Berekening!M45-(INDEX(T1_Rente,1)+0.000005)*Berekening!M46<=0,-1000000000000,1000000000000),-1000000000000))) -> 0
A11: Kolom 1: hoogste bedrag waarbij de gewogen rente in deze kolom valt | B11: € | C11: =MIN(1000000000000,IF((INDEX(T1_Rente,1)+0.000005)<Berekening!C10,(Berekening!C45-(INDEX(T1_Rente,1)+0.000005)*Berekening!C46)/(360*((INDEX(T1_Rente,1)+0.000005)-Berekening!C10)),1000000000000)) -> -278643.49 | D11: =MIN(1000000000000,IF((INDEX(T1_Rente,1)+0.000005)<Berekening!D10,(Berekening!D45-(INDEX(T1_Rente,1)+0.000005)*Berekening!D46)/(360*((INDEX(T1_Rente,1)+0.000005)-Berekening!D10)),1000000000000)) -> -334492.74 | E11: =MIN(1000000000000,IF((INDEX(T1_Rente,1)+0.000005)<Berekening!E10,(Berekening!E45-(INDEX(T1_Rente,1)+0.000005)*Berekening!E46)/(360*((INDEX(T1_Rente,1)+0.000005)-Berekening!E10)),1000000000000)) -> -628525.35 | F11: =MIN(1000000000000,IF((INDEX(T1_Rente,1)+0.000005)<Berekening!F10,(Berekening!F45-(INDEX(T1_Rente,1)+0.000005)*Berekening!F46)/(360*((INDEX(T1_Rente,1)+0.000005)-Berekening!F10)),1000000000000)) -> -253960.11 | G11: =MIN(1000000000000,IF((INDEX(T1_Rente,1)+0.000005)<Berekening!G10,(Berekening!G45-(INDEX(T1_Rente,1)+0.000005)*Berekening!G46)/(360*((INDEX(T1_Rente,1)+0.000005)-Berekening!G10)),1000000000000)) -> 0 | H11: =MIN(1000000000000,IF((INDEX(T1_Rente,1)+0.000005)<Berekening!H10,(Berekening!H45-(INDEX(T1_Rente,1)+0.000005)*Berekening!H46)/(360*((INDEX(T1_Rente,1)+0.000005)-Berekening!H10)),1000000000000)) -> 0 | I11: =MIN(1000000000000,IF((INDEX(T1_Rente,1)+0.000005)<Berekening!I10,(Berekening!I45-(INDEX(T1_Rente,1)+0.000005)*Berekening!I46)/(360*((INDEX(T1_Rente,1)+0.000005)-Berekening!I10)),1000000000000)) -> 0 | J11: =MIN(1000000000000,IF((INDEX(T1_Rente,1)+0.000005)<Berekening!J10,(Berekening!J45-(INDEX(T1_Rente,1)+0.000005)*Berekening!J46)/(360*((INDEX(T1_Rente,1)+0.000005)-Berekening!J10)),1000000000000)) -> -278643.49 | ... M11: =MIN(1000000000000,IF((INDEX(T1_Rente,1)+0.000005)<Berekening!M10,(Berekening!M45-(INDEX(T1_Rente,1)+0.000005)*Berekening!M46)/(360*((INDEX(T1_Rente,1)+0.000005)-Berekening!M10)),1000000000000)) -> -278643.49
A12: Kolom 1: haalbaar bedrag (−1 = onmogelijk) | B12: € | C12: =IF(C10>C11,-1,IF(C9<C10-0.000000001,-1,IF(C9>C11,MAX(C10,C11-1),C9))) -> -1 | D12: =IF(D10>D11,-1,IF(D9<D10-0.000000001,-1,IF(D9>D11,MAX(D10,D11-1),D9))) -> -1 | E12: =IF(E10>E11,-1,IF(E9<E10-0.000000001,-1,IF(E9>E11,MAX(E10,E11-1),E9))) -> -1 | F12: =IF(F10>F11,-1,IF(F9<F10-0.000000001,-1,IF(F9>F11,MAX(F10,F11-1),F9))) -> -1 | G12: =IF(G10>G11,-1,IF(G9<G10-0.000000001,-1,IF(G9>G11,MAX(G10,G11-1),G9))) -> 0 | H12: =IF(H10>H11,-1,IF(H9<H10-0.000000001,-1,IF(H9>H11,MAX(H10,H11-1),H9))) -> 0 | I12: =IF(I10>I11,-1,IF(I9<I10-0.000000001,-1,IF(I9>I11,MAX(I10,I11-1),I9))) -> 0 | J12: =IF(J10>J11,-1,IF(J9<J10-0.000000001,-1,IF(J9>J11,MAX(J10,J11-1),J9))) -> -1 | ... M12: =IF(M10>M11,-1,IF(M9<M10-0.000000001,-1,IF(M9>M11,MAX(M10,M11-1),M9))) -> -1
A13: Kolom 2: woonquote | B13: % | C13: =INDEX(T1_Tabel,Berekening!C80,2)+(Berekening!C79-INDEX(T1_Inkomen,Berekening!C80))/(INDEX(T1_Inkomen,Berekening!C80+1)-INDEX(T1_Inkomen,Berekening!C80))*(INDEX(T1_Tabel,Berekening!C80+1,2)-INDEX(T1_Tabel,Berekening!C80,2)) -> 0.233 | D13: =INDEX(T1_Tabel,Berekening!D80,2)+(Berekening!D79-INDEX(T1_Inkomen,Berekening!D80))/(INDEX(T1_Inkomen,Berekening!D80+1)-INDEX(T1_Inkomen,Berekening!D80))*(INDEX(T1_Tabel,Berekening!D80+1,2)-INDEX(T1_Tabel,Berekening!D80,2)) -> 0.233 | E13: =INDEX(T1_Tabel,Berekening!E80,2)+(Berekening!E79-INDEX(T1_Inkomen,Berekening!E80))/(INDEX(T1_Inkomen,Berekening!E80+1)-INDEX(T1_Inkomen,Berekening!E80))*(INDEX(T1_Tabel,Berekening!E80+1,2)-INDEX(T1_Tabel,Berekening!E80,2)) -> 0.233 | F13: =INDEX(T1_Tabel,Berekening!F80,2)+(Berekening!F79-INDEX(T1_Inkomen,Berekening!F80))/(INDEX(T1_Inkomen,Berekening!F80+1)-INDEX(T1_Inkomen,Berekening!F80))*(INDEX(T1_Tabel,Berekening!F80+1,2)-INDEX(T1_Tabel,Berekening!F80,2)) -> 0.233 | G13: =INDEX(T1_Tabel,Berekening!G80,2)+(Berekening!G79-INDEX(T1_Inkomen,Berekening!G80))/(INDEX(T1_Inkomen,Berekening!G80+1)-INDEX(T1_Inkomen,Berekening!G80))*(INDEX(T1_Tabel,Berekening!G80+1,2)-INDEX(T1_Tabel,Berekening!G80,2)) -> 0.187 | H13: =INDEX(T1_Tabel,Berekening!H80,2)+(Berekening!H79-INDEX(T1_Inkomen,Berekening!H80))/(INDEX(T1_Inkomen,Berekening!H80+1)-INDEX(T1_Inkomen,Berekening!H80))*(INDEX(T1_Tabel,Berekening!H80+1,2)-INDEX(T1_Tabel,Berekening!H80,2)) -> 0.233 | I13: =INDEX(T1_Tabel,Berekening!I80,2)+(Berekening!I79-INDEX(T1_Inkomen,Berekening!I80))/(INDEX(T1_Inkomen,Berekening!I80+1)-INDEX(T1_Inkomen,Berekening!I80))*(INDEX(T1_Tabel,Berekening!I80+1,2)-INDEX(T1_Tabel,Berekening!I80,2)) -> 0.233 | J13: =INDEX(T1_Tabel,Berekening!J80,2)+(Berekening!J79-INDEX(T1_Inkomen,Berekening!J80))/(INDEX(T1_Inkomen,Berekening!J80+1)-INDEX(T1_Inkomen,Berekening!J80))*(INDEX(T1_Tabel,Berekening!J80+1,2)-INDEX(T1_Tabel,Berekening!J80,2)) -> 0.233 | ... M13: =INDEX(T1_Tabel,Berekening!M80,2)+(Berekening!M79-INDEX(T1_Inkomen,Berekening!M80))/(INDEX(T1_Inkomen,Berekening!M80+1)-INDEX(T1_Inkomen,Berekening!M80))*(INDEX(T1_Tabel,Berekening!M80+1,2)-INDEX(T1_Tabel,Berekening!M80,2)) -> 0.233
A14: Kolom 2: bedrag als de woonquote van deze kolom geldt | B14: € | C14: =MAX(0,(C13*C6/12-Berekening!C18-Berekening!C44)*Berekening!C11-Berekening!C75+C7) -> 179955.41 | D14: =MAX(0,(D13*D6/12-Berekening!D18-Berekening!D44)*Berekening!D11-Berekening!D75+D7) -> 209006.96 | E14: =MAX(0,(E13*E6/12-Berekening!E18-Berekening!E44)*Berekening!E11-Berekening!E75+E7) -> 57307.87 | F14: =MAX(0,(F13*F6/12-Berekening!F18-Berekening!F44)*Berekening!F11-Berekening!F75+F7) -> 174008.26 | G14: =MAX(0,(G13*G6/12-Berekening!G18-Berekening!G44)*Berekening!G11-Berekening!G75+G7) -> 202489.06 | H14: =MAX(0,(H13*H6/12-Berekening!H18-Berekening!H44)*Berekening!H11-Berekening!H75+H7) -> 542104.93 | I14: =MAX(0,(I13*I6/12-Berekening!I18-Berekening!I44)*Berekening!I11-Berekening!I75+I7) -> 732727.32 | J14: =MAX(0,(J13*J6/12-Berekening!J18-Berekening!J44)*Berekening!J11-Berekening!J75+J7) -> 217241.48 | ... M14: =MAX(0,(M13*M6/12-Berekening!M18-Berekening!M44)*Berekening!M11-Berekening!M75+M7) -> 179955.41
A15: Kolom 2: laagste bedrag waarbij de gewogen rente in deze kolom valt | B15: € | C15: =MAX(0,IF((INDEX(T1_Rente,2)+0.000005)>Berekening!C10,(Berekening!C45-(INDEX(T1_Rente,2)+0.000005)*Berekening!C46)/(360*((INDEX(T1_Rente,2)+0.000005)-Berekening!C10)),IF((INDEX(T1_Rente,2)+0.000005)=Berekening!C10,IF(Berekening!C45-(INDEX(T1_Rente,2)+0.000005)*Berekening!C46<=0,-1000000000000,1000000000000),-1000000000000)),IF((INDEX(T1_Rente,2)-0.005+0.000005)<Berekening!C10,(Berekening!C45-(INDEX(T1_Rente,2)-0.005+0.000005)*Berekening!C46)/(360*((INDEX(T1_Rente,2)-0.005+0.000005)-Berekening!C10)),IF((INDEX(T1_Rente,2)-0.005+0.000005)=Berekening!C10,IF(Berekening!C45-(INDEX(T1_Rente,2)-0.005+0.000005)*Berekening!C46>0,-1000000000000,1000000000000),-1000000000000))) -> 0 | D15: =MAX(0,IF((INDEX(T1_Rente,2)+0.000005)>Berekening!D10,(Berekening!D45-(INDEX(T1_Rente,2)+0.000005)*Berekening!D46)/(360*((INDEX(T1_Rente,2)+0.000005)-Berekening!D10)),IF((INDEX(T1_Rente,2)+0.000005)=Berekening!D10,IF(Berekening!D45-(INDEX(T1_Rente,2)+0.000005)*Berekening!D46<=0,-1000000000000,1000000000000),-1000000000000)),IF((INDEX(T1_Rente,2)-0.005+0.000005)<Berekening!D10,(Berekening!D45-(INDEX(T1_Rente,2)-0.005+0.000005)*Berekening!D46)/(360*((INDEX(T1_Rente,2)-0.005+0.000005)-Berekening!D10)),IF((INDEX(T1_Rente,2)-0.005+0.000005)=Berekening!D10,IF(Berekening!D45-(INDEX(T1_Rente,2)-0.005+0.000005)*Berekening!D46>0,-1000000000000,1000000000000),-1000000000000))) -> 0 | E15: =MAX(0,IF((INDEX(T1_Rente,2)+0.000005)>Berekening!E10,(Berekening!E45-(INDEX(T1_Rente,2)+0.000005)*Berekening!E46)/(360*((INDEX(T1_Rente,2)+0.000005)-Berekening!E10)),IF((INDEX(T1_Rente,2)+0.000005)=Berekening!E10,IF(Berekening!E45-(INDEX(T1_Rente,2)+0.000005)*Berekening!E46<=0,-1000000000000,1000000000000),-1000000000000)),IF((INDEX(T1_Rente,2)-0.005+0.000005)<Berekening!E10,(Berekening!E45-(INDEX(T1_Rente,2)-0.005+0.000005)*Berekening!E46)/(360*((INDEX(T1_Rente,2)-0.005+0.000005)-Berekening!E10)),IF((INDEX(T1_Rente,2)-0.005+0.000005)=Berekening!E10,IF(Berekening!E45-(INDEX(T1_Rente,2)-0.005+0.000005)*Berekening!E46>0,-1000000000000,1000000000000),-1000000000000))) -> 0 | F15: =MAX(0,IF((INDEX(T1_Rente,2)+0.000005)>Berekening!F10,(Berekening!F45-(INDEX(T1_Rente,2)+0.000005)*Berekening!F46)/(360*((INDEX(T1_Rente,2)+0.000005)-Berekening!F10)),IF((INDEX(T1_Rente,2)+0.000005)=Berekening!F10,IF(Berekening!F45-(INDEX(T1_Rente,2)+0.000005)*Berekening!F46<=0,-1000000000000,1000000000000),-1000000000000)),IF((INDEX(T1_Rente,2)-0.005+0.000005)<Berekening!F10,(Berekening!F45-(INDEX(T1_Rente,2)-0.005+0.000005)*Berekening!F46)/(360*((INDEX(T1_Rente,2)-0.005+0.000005)-Berekening!F10)),IF((INDEX(T1_Rente,2)-0.005+0.000005)=Berekening!F10,IF(Berekening!F45-(INDEX(T1_Rente,2)-0.005+0.000005)*Berekening!F46>0,-1000000000000,1000000000000),-1000000000000))) -> 0 | G15: =MAX(0,IF((INDEX(T1_Rente,2)+0.000005)>Berekening!G10,(Berekening!G45-(INDEX(T1_Rente,2)+0.000005)*Berekening!G46)/(360*((INDEX(T1_Rente,2)+0.000005)-Berekening!G10)),IF((INDEX(T1_Rente,2)+0.000005)=Berekening!G10,IF(Berekening!G45-(INDEX(T1_Rente,2)+0.000005)*Berekening!G46<=0,-1000000000000,1000000000000),-1000000000000)),IF((INDEX(T1_Rente,2)-0.005+0.000005)<Berekening!G10,(Berekening!G45-(INDEX(T1_Rente,2)-0.005+0.000005)*Berekening!G46)/(360*((INDEX(T1_Rente,2)-0.005+0.000005)-Berekening!G10)),IF((INDEX(T1_Rente,2)-0.005+0.000005)=Berekening!G10,IF(Berekening!G45-(INDEX(T1_Rente,2)-0.005+0.000005)*Berekening!G46>0,-1000000000000,1000000000000),-1000000000000))) -> 0 | H15: =MAX(0,IF((INDEX(T1_Rente,2)+0.000005)>Berekening!H10,(Berekening!H45-(INDEX(T1_Rente,2)+0.000005)*Berekening!H46)/(360*((INDEX(T1_Rente,2)+0.000005)-Berekening!H10)),IF((INDEX(T1_Rente,2)+0.000005)=Berekening!H10,IF(Berekening!H45-(INDEX(T1_Rente,2)+0.000005)*Berekening!H46<=0,-1000000000000,1000000000000),-1000000000000)),IF((INDEX(T1_Rente,2)-0.005+0.000005)<Berekening!H10,(Berekening!H45-(INDEX(T1_Rente,2)-0.005+0.000005)*Berekening!H46)/(360*((INDEX(T1_Rente,2)-0.005+0.000005)-Berekening!H10)),IF((INDEX(T1_Rente,2)-0.005+0.000005)=Berekening!H10,IF(Berekening!H45-(INDEX(T1_Rente,2)-0.005+0.000005)*Berekening!H46>0,-1000000000000,1000000000000),-1000000000000))) -> 0 | I15: =MAX(0,IF((INDEX(T1_Rente,2)+0.000005)>Berekening!I10,(Berekening!I45-(INDEX(T1_Rente,2)+0.000005)*Berekening!I46)/(360*((INDEX(T1_Rente,2)+0.000005)-Berekening!I10)),IF((INDEX(T1_Rente,2)+0.000005)=Berekening!I10,IF(Berekening!I45-(INDEX(T1_Rente,2)+0.000005)*Berekening!I46<=0,-1000000000000,1000000000000),-1000000000000)),IF((INDEX(T1_Rente,2)-0.005+0.000005)<Berekening!I10,(Berekening!I45-(INDEX(T1_Rente,2)-0.005+0.000005)*Berekening!I46)/(360*((INDEX(T1_Rente,2)-0.005+0.000005)-Berekening!I10)),IF((INDEX(T1_Rente,2)-0.005+0.000005)=Berekening!I10,IF(Berekening!I45-(INDEX(T1_Rente,2)-0.005+0.000005)*Berekening!I46>0,-1000000000000,1000000000000),-1000000000000))) -> 0 | J15: =MAX(0,IF((INDEX(T1_Rente,2)+0.000005)>Berekening!J10,(Berekening!J45-(INDEX(T1_Rente,2)+0.000005)*Berekening!J46)/(360*((INDEX(T1_Rente,2)+0.000005)-Berekening!J10)),IF((INDEX(T1_Rente,2)+0.000005)=Berekening!J10,IF(Berekening!J45-(INDEX(T1_Rente,2)+0.000005)*Berekening!J46<=0,-1000000000000,1000000000000),-1000000000000)),IF((INDEX(T1_Rente,2)-0.005+0.000005)<Berekening!J10,(Berekening!J45-(INDEX(T1_Rente,2)-0.005+0.000005)*Berekening!J46)/(360*((INDEX(T1_Rente,2)-0.005+0.000005)-Berekening!J10)),IF((INDEX(T1_Rente,2)-0.005+0.000005)=Berekening!J10,IF(Berekening!J45-(INDEX(T1_Rente,2)-0.005+0.000005)*Berekening!J46>0,-1000000000000,1000000000000),-1000000000000))) -> 0 | ... M15: =MAX(0,IF((INDEX(T1_Rente,2)+0.000005)>Berekening!M10,(Berekening!M45-(INDEX(T1_Rente,2)+0.000005)*Berekening!M46)/(360*((INDEX(T1_Rente,2)+0.000005)-Berekening!M10)),IF((INDEX(T1_Rente,2)+0.000005)=Berekening!M10,IF(Berekening!M45-(INDEX(T1_Rente,2)+0.000005)*Berekening!M46<=0,-1000000000000,1000000000000),-1000000000000)),IF((INDEX(T1_Rente,2)-0.005+0.000005)<Berekening!M10,(Berekening!M45-(INDEX(T1_Rente,2)-0.005+0.000005)*Berekening!M46)/(360*((INDEX(T1_Rente,2)-0.005+0.000005)-Berekening!M10)),IF((INDEX(T1_Rente,2)-0.005+0.000005)=Berekening!M10,IF(Berekening!M45-(INDEX(T1_Rente,2)-0.005+0.000005)*Berekening!M46>0,-1000000000000,1000000000000),-1000000000000))) -> 0
A16: Kolom 2: hoogste bedrag waarbij de gewogen rente in deze kolom valt | B16: € | C16: =MIN(1000000000000,IF((INDEX(T1_Rente,2)+0.000005)<Berekening!C10,(Berekening!C45-(INDEX(T1_Rente,2)+0.000005)*Berekening!C46)/(360*((INDEX(T1_Rente,2)+0.000005)-Berekening!C10)),1000000000000),IF((INDEX(T1_Rente,2)-0.005+0.000005)>Berekening!C10,(Berekening!C45-(INDEX(T1_Rente,2)-0.005+0.000005)*Berekening!C46)/(360*((INDEX(T1_Rente,2)-0.005+0.000005)-Berekening!C10)),1000000000000)) -> -223948.47 | D16: =MIN(1000000000000,IF((INDEX(T1_Rente,2)+0.000005)<Berekening!D10,(Berekening!D45-(INDEX(T1_Rente,2)+0.000005)*Berekening!D46)/(360*((INDEX(T1_Rente,2)+0.000005)-Berekening!D10)),1000000000000),IF((INDEX(T1_Rente,2)-0.005+0.000005)>Berekening!D10,(Berekening!D45-(INDEX(T1_Rente,2)-0.005+0.000005)*Berekening!D46)/(360*((INDEX(T1_Rente,2)-0.005+0.000005)-Berekening!D10)),1000000000000)) -> -280717.48 | E16: =MIN(1000000000000,IF((INDEX(T1_Rente,2)+0.000005)<Berekening!E10,(Berekening!E45-(INDEX(T1_Rente,2)+0.000005)*Berekening!E46)/(360*((INDEX(T1_Rente,2)+0.000005)-Berekening!E10)),1000000000000),IF((INDEX(T1_Rente,2)-0.005+0.000005)>Berekening!E10,(Berekening!E45-(INDEX(T1_Rente,2)-0.005+0.000005)*Berekening!E46)/(360*((INDEX(T1_Rente,2)-0.005+0.000005)-Berekening!E10)),1000000000000)) -> -638876.23 | F16: =MIN(1000000000000,IF((INDEX(T1_Rente,2)+0.000005)<Berekening!F10,(Berekening!F45-(INDEX(T1_Rente,2)+0.000005)*Berekening!F46)/(360*((INDEX(T1_Rente,2)+0.000005)-Berekening!F10)),1000000000000),IF((INDEX(T1_Rente,2)-0.005+0.000005)>Berekening!F10,(Berekening!F45-(INDEX(T1_Rente,2)-0.005+0.000005)*Berekening!F46)/(360*((INDEX(T1_Rente,2)-0.005+0.000005)-Berekening!F10)),1000000000000)) -> -200803.27 | G16: =MIN(1000000000000,IF((INDEX(T1_Rente,2)+0.000005)<Berekening!G10,(Berekening!G45-(INDEX(T1_Rente,2)+0.000005)*Berekening!G46)/(360*((INDEX(T1_Rente,2)+0.000005)-Berekening!G10)),1000000000000),IF((INDEX(T1_Rente,2)-0.005+0.000005)>Berekening!G10,(Berekening!G45-(INDEX(T1_Rente,2)-0.005+0.000005)*Berekening!G46)/(360*((INDEX(T1_Rente,2)-0.005+0.000005)-Berekening!G10)),1000000000000)) -> 0 | H16: =MIN(1000000000000,IF((INDEX(T1_Rente,2)+0.000005)<Berekening!H10,(Berekening!H45-(INDEX(T1_Rente,2)+0.000005)*Berekening!H46)/(360*((INDEX(T1_Rente,2)+0.000005)-Berekening!H10)),1000000000000),IF((INDEX(T1_Rente,2)-0.005+0.000005)>Berekening!H10,(Berekening!H45-(INDEX(T1_Rente,2)-0.005+0.000005)*Berekening!H46)/(360*((INDEX(T1_Rente,2)-0.005+0.000005)-Berekening!H10)),1000000000000)) -> 0 | I16: =MIN(1000000000000,IF((INDEX(T1_Rente,2)+0.000005)<Berekening!I10,(Berekening!I45-(INDEX(T1_Rente,2)+0.000005)*Berekening!I46)/(360*((INDEX(T1_Rente,2)+0.000005)-Berekening!I10)),1000000000000),IF((INDEX(T1_Rente,2)-0.005+0.000005)>Berekening!I10,(Berekening!I45-(INDEX(T1_Rente,2)-0.005+0.000005)*Berekening!I46)/(360*((INDEX(T1_Rente,2)-0.005+0.000005)-Berekening!I10)),1000000000000)) -> 0 | J16: =MIN(1000000000000,IF((INDEX(T1_Rente,2)+0.000005)<Berekening!J10,(Berekening!J45-(INDEX(T1_Rente,2)+0.000005)*Berekening!J46)/(360*((INDEX(T1_Rente,2)+0.000005)-Berekening!J10)),1000000000000),IF((INDEX(T1_Rente,2)-0.005+0.000005)>Berekening!J10,(Berekening!J45-(INDEX(T1_Rente,2)-0.005+0.000005)*Berekening!J46)/(360*((INDEX(T1_Rente,2)-0.005+0.000005)-Berekening!J10)),1000000000000)) -> -223948.47 | ... M16: =MIN(1000000000000,IF((INDEX(T1_Rente,2)+0.000005)<Berekening!M10,(Berekening!M45-(INDEX(T1_Rente,2)+0.000005)*Berekening!M46)/(360*((INDEX(T1_Rente,2)+0.000005)-Berekening!M10)),1000000000000),IF((INDEX(T1_Rente,2)-0.005+0.000005)>Berekening!M10,(Berekening!M45-(INDEX(T1_Rente,2)-0.005+0.000005)*Berekening!M46)/(360*((INDEX(T1_Rente,2)-0.005+0.000005)-Berekening!M10)),1000000000000)) -> -223948.47
A17: Kolom 2: haalbaar bedrag (−1 = onmogelijk) | B17: € | C17: =IF(C15>C16,-1,IF(C14<C15-0.000000001,-1,IF(C14>C16,MAX(C15,C16-1),C14))) -> -1 | D17: =IF(D15>D16,-1,IF(D14<D15-0.000000001,-1,IF(D14>D16,MAX(D15,D16-1),D14))) -> -1 | E17: =IF(E15>E16,-1,IF(E14<E15-0.000000001,-1,IF(E14>E16,MAX(E15,E16-1),E14))) -> -1 | F17: =IF(F15>F16,-1,IF(F14<F15-0.000000001,-1,IF(F14>F16,MAX(F15,F16-1),F14))) -> -1 | G17: =IF(G15>G16,-1,IF(G14<G15-0.000000001,-1,IF(G14>G16,MAX(G15,G16-1),G14))) -> 0 | H17: =IF(H15>H16,-1,IF(H14<H15-0.000000001,-1,IF(H14>H16,MAX(H15,H16-1),H14))) -> 0 | I17: =IF(I15>I16,-1,IF(I14<I15-0.000000001,-1,IF(I14>I16,MAX(I15,I16-1),I14))) -> 0 | J17: =IF(J15>J16,-1,IF(J14<J15-0.000000001,-1,IF(J14>J16,MAX(J15,J16-1),J14))) -> -1 | ... M17: =IF(M15>M16,-1,IF(M14<M15-0.000000001,-1,IF(M14>M16,MAX(M15,M16-1),M14))) -> -1
A18: Kolom 3: woonquote | B18: % | C18: =INDEX(T1_Tabel,Berekening!C80,3)+(Berekening!C79-INDEX(T1_Inkomen,Berekening!C80))/(INDEX(T1_Inkomen,Berekening!C80+1)-INDEX(T1_Inkomen,Berekening!C80))*(INDEX(T1_Tabel,Berekening!C80+1,3)-INDEX(T1_Tabel,Berekening!C80,3)) -> 0.244 | D18: =INDEX(T1_Tabel,Berekening!D80,3)+(Berekening!D79-INDEX(T1_Inkomen,Berekening!D80))/(INDEX(T1_Inkomen,Berekening!D80+1)-INDEX(T1_Inkomen,Berekening!D80))*(INDEX(T1_Tabel,Berekening!D80+1,3)-INDEX(T1_Tabel,Berekening!D80,3)) -> 0.244 | E18: =INDEX(T1_Tabel,Berekening!E80,3)+(Berekening!E79-INDEX(T1_Inkomen,Berekening!E80))/(INDEX(T1_Inkomen,Berekening!E80+1)-INDEX(T1_Inkomen,Berekening!E80))*(INDEX(T1_Tabel,Berekening!E80+1,3)-INDEX(T1_Tabel,Berekening!E80,3)) -> 0.244 | F18: =INDEX(T1_Tabel,Berekening!F80,3)+(Berekening!F79-INDEX(T1_Inkomen,Berekening!F80))/(INDEX(T1_Inkomen,Berekening!F80+1)-INDEX(T1_Inkomen,Berekening!F80))*(INDEX(T1_Tabel,Berekening!F80+1,3)-INDEX(T1_Tabel,Berekening!F80,3)) -> 0.244 | G18: =INDEX(T1_Tabel,Berekening!G80,3)+(Berekening!G79-INDEX(T1_Inkomen,Berekening!G80))/(INDEX(T1_Inkomen,Berekening!G80+1)-INDEX(T1_Inkomen,Berekening!G80))*(INDEX(T1_Tabel,Berekening!G80+1,3)-INDEX(T1_Tabel,Berekening!G80,3)) -> 0.197 | H18: =INDEX(T1_Tabel,Berekening!H80,3)+(Berekening!H79-INDEX(T1_Inkomen,Berekening!H80))/(INDEX(T1_Inkomen,Berekening!H80+1)-INDEX(T1_Inkomen,Berekening!H80))*(INDEX(T1_Tabel,Berekening!H80+1,3)-INDEX(T1_Tabel,Berekening!H80,3)) -> 0.244 | I18: =INDEX(T1_Tabel,Berekening!I80,3)+(Berekening!I79-INDEX(T1_Inkomen,Berekening!I80))/(INDEX(T1_Inkomen,Berekening!I80+1)-INDEX(T1_Inkomen,Berekening!I80))*(INDEX(T1_Tabel,Berekening!I80+1,3)-INDEX(T1_Tabel,Berekening!I80,3)) -> 0.244 | J18: =INDEX(T1_Tabel,Berekening!J80,3)+(Berekening!J79-INDEX(T1_Inkomen,Berekening!J80))/(INDEX(T1_Inkomen,Berekening!J80+1)-INDEX(T1_Inkomen,Berekening!J80))*(INDEX(T1_Tabel,Berekening!J80+1,3)-INDEX(T1_Tabel,Berekening!J80,3)) -> 0.244 | ... M18: =INDEX(T1_Tabel,Berekening!M80,3)+(Berekening!M79-INDEX(T1_Inkomen,Berekening!M80))/(INDEX(T1_Inkomen,Berekening!M80+1)-INDEX(T1_Inkomen,Berekening!M80))*(INDEX(T1_Tabel,Berekening!M80+1,3)-INDEX(T1_Tabel,Berekening!M80,3)) -> 0.244
A19: Kolom 3: bedrag als de woonquote van deze kolom geldt | B19: € | C19: =MAX(0,(C18*C6/12-Berekening!C18-Berekening!C44)*Berekening!C11-Berekening!C75+C7) -> 219769.18 | D19: =MAX(0,(D18*D6/12-Berekening!D18-Berekening!D44)*Berekening!D11-Berekening!D75+D7) -> 248820.73 | E19: =MAX(0,(E18*E6/12-Berekening!E18-Berekening!E44)*Berekening!E11-Berekening!E75+E7) -> 97121.634 | F19: =MAX(0,(F18*F6/12-Berekening!F18-Berekening!F44)*Berekening!F11-Berekening!F75+F7) -> 212428.84 | G19: =MAX(0,(G18*G6/12-Berekening!G18-Berekening!G44)*Berekening!G11-Berekening!G75+G7) -> 212140.89 | H19: =MAX(0,(H18*H6/12-Berekening!H18-Berekening!H44)*Berekening!H11-Berekening!H75+H7) -> 568647.44 | I19: =MAX(0,(I18*I6/12-Berekening!I18-Berekening!I44)*Berekening!I11-Berekening!I75+I7) -> 772541.08 | J19: =MAX(0,(J18*J6/12-Berekening!J18-Berekening!J44)*Berekening!J11-Berekening!J75+J7) -> 257055.25 | ... M19: =MAX(0,(M18*M6/12-Berekening!M18-Berekening!M44)*Berekening!M11-Berekening!M75+M7) -> 219769.18
A20: Kolom 3: laagste bedrag waarbij de gewogen rente in deze kolom valt | B20: € | C20: =MAX(0,IF((INDEX(T1_Rente,3)+0.000005)>Berekening!C10,(Berekening!C45-(INDEX(T1_Rente,3)+0.000005)*Berekening!C46)/(360*((INDEX(T1_Rente,3)+0.000005)-Berekening!C10)),IF((INDEX(T1_Rente,3)+0.000005)=Berekening!C10,IF(Berekening!C45-(INDEX(T1_Rente,3)+0.000005)*Berekening!C46<=0,-1000000000000,1000000000000),-1000000000000)),IF((INDEX(T1_Rente,3)-0.005+0.000005)<Berekening!C10,(Berekening!C45-(INDEX(T1_Rente,3)-0.005+0.000005)*Berekening!C46)/(360*((INDEX(T1_Rente,3)-0.005+0.000005)-Berekening!C10)),IF((INDEX(T1_Rente,3)-0.005+0.000005)=Berekening!C10,IF(Berekening!C45-(INDEX(T1_Rente,3)-0.005+0.000005)*Berekening!C46>0,-1000000000000,1000000000000),-1000000000000))) -> 0 | D20: =MAX(0,IF((INDEX(T1_Rente,3)+0.000005)>Berekening!D10,(Berekening!D45-(INDEX(T1_Rente,3)+0.000005)*Berekening!D46)/(360*((INDEX(T1_Rente,3)+0.000005)-Berekening!D10)),IF((INDEX(T1_Rente,3)+0.000005)=Berekening!D10,IF(Berekening!D45-(INDEX(T1_Rente,3)+0.000005)*Berekening!D46<=0,-1000000000000,1000000000000),-1000000000000)),IF((INDEX(T1_Rente,3)-0.005+0.000005)<Berekening!D10,(Berekening!D45-(INDEX(T1_Rente,3)-0.005+0.000005)*Berekening!D46)/(360*((INDEX(T1_Rente,3)-0.005+0.000005)-Berekening!D10)),IF((INDEX(T1_Rente,3)-0.005+0.000005)=Berekening!D10,IF(Berekening!D45-(INDEX(T1_Rente,3)-0.005+0.000005)*Berekening!D46>0,-1000000000000,1000000000000),-1000000000000))) -> 0 | E20: =MAX(0,IF((INDEX(T1_Rente,3)+0.000005)>Berekening!E10,(Berekening!E45-(INDEX(T1_Rente,3)+0.000005)*Berekening!E46)/(360*((INDEX(T1_Rente,3)+0.000005)-Berekening!E10)),IF((INDEX(T1_Rente,3)+0.000005)=Berekening!E10,IF(Berekening!E45-(INDEX(T1_Rente,3)+0.000005)*Berekening!E46<=0,-1000000000000,1000000000000),-1000000000000)),IF((INDEX(T1_Rente,3)-0.005+0.000005)<Berekening!E10,(Berekening!E45-(INDEX(T1_Rente,3)-0.005+0.000005)*Berekening!E46)/(360*((INDEX(T1_Rente,3)-0.005+0.000005)-Berekening!E10)),IF((INDEX(T1_Rente,3)-0.005+0.000005)=Berekening!E10,IF(Berekening!E45-(INDEX(T1_Rente,3)-0.005+0.000005)*Berekening!E46>0,-1000000000000,1000000000000),-1000000000000))) -> 0 | F20: =MAX(0,IF((INDEX(T1_Rente,3)+0.000005)>Berekening!F10,(Berekening!F45-(INDEX(T1_Rente,3)+0.000005)*Berekening!F46)/(360*((INDEX(T1_Rente,3)+0.000005)-Berekening!F10)),IF((INDEX(T1_Rente,3)+0.000005)=Berekening!F10,IF(Berekening!F45-(INDEX(T1_Rente,3)+0.000005)*Berekening!F46<=0,-1000000000000,1000000000000),-1000000000000)),IF((INDEX(T1_Rente,3)-0.005+0.000005)<Berekening!F10,(Berekening!F45-(INDEX(T1_Rente,3)-0.005+0.000005)*Berekening!F46)/(360*((INDEX(T1_Rente,3)-0.005+0.000005)-Berekening!F10)),IF((INDEX(T1_Rente,3)-0.005+0.000005)=Berekening!F10,IF(Berekening!F45-(INDEX(T1_Rente,3)-0.005+0.000005)*Berekening!F46>0,-1000000000000,1000000000000),-1000000000000))) -> 0 | G20: =MAX(0,IF((INDEX(T1_Rente,3)+0.000005)>Berekening!G10,(Berekening!G45-(INDEX(T1_Rente,3)+0.000005)*Berekening!G46)/(360*((INDEX(T1_Rente,3)+0.000005)-Berekening!G10)),IF((INDEX(T1_Rente,3)+0.000005)=Berekening!G10,IF(Berekening!G45-(INDEX(T1_Rente,3)+0.000005)*Berekening!G46<=0,-1000000000000,1000000000000),-1000000000000)),IF((INDEX(T1_Rente,3)-0.005+0.000005)<Berekening!G10,(Berekening!G45-(INDEX(T1_Rente,3)-0.005+0.000005)*Berekening!G46)/(360*((INDEX(T1_Rente,3)-0.005+0.000005)-Berekening!G10)),IF((INDEX(T1_Rente,3)-0.005+0.000005)=Berekening!G10,IF(Berekening!G45-(INDEX(T1_Rente,3)-0.005+0.000005)*Berekening!G46>0,-1000000000000,1000000000000),-1000000000000))) -> 0 | H20: =MAX(0,IF((INDEX(T1_Rente,3)+0.000005)>Berekening!H10,(Berekening!H45-(INDEX(T1_Rente,3)+0.000005)*Berekening!H46)/(360*((INDEX(T1_Rente,3)+0.000005)-Berekening!H10)),IF((INDEX(T1_Rente,3)+0.000005)=Berekening!H10,IF(Berekening!H45-(INDEX(T1_Rente,3)+0.000005)*Berekening!H46<=0,-1000000000000,1000000000000),-1000000000000)),IF((INDEX(T1_Rente,3)-0.005+0.000005)<Berekening!H10,(Berekening!H45-(INDEX(T1_Rente,3)-0.005+0.000005)*Berekening!H46)/(360*((INDEX(T1_Rente,3)-0.005+0.000005)-Berekening!H10)),IF((INDEX(T1_Rente,3)-0.005+0.000005)=Berekening!H10,IF(Berekening!H45-(INDEX(T1_Rente,3)-0.005+0.000005)*Berekening!H46>0,-1000000000000,1000000000000),-1000000000000))) -> 0 | I20: =MAX(0,IF((INDEX(T1_Rente,3)+0.000005)>Berekening!I10,(Berekening!I45-(INDEX(T1_Rente,3)+0.000005)*Berekening!I46)/(360*((INDEX(T1_Rente,3)+0.000005)-Berekening!I10)),IF((INDEX(T1_Rente,3)+0.000005)=Berekening!I10,IF(Berekening!I45-(INDEX(T1_Rente,3)+0.000005)*Berekening!I46<=0,-1000000000000,1000000000000),-1000000000000)),IF((INDEX(T1_Rente,3)-0.005+0.000005)<Berekening!I10,(Berekening!I45-(INDEX(T1_Rente,3)-0.005+0.000005)*Berekening!I46)/(360*((INDEX(T1_Rente,3)-0.005+0.000005)-Berekening!I10)),IF((INDEX(T1_Rente,3)-0.005+0.000005)=Berekening!I10,IF(Berekening!I45-(INDEX(T1_Rente,3)-0.005+0.000005)*Berekening!I46>0,-1000000000000,1000000000000),-1000000000000))) -> 0 | J20: =MAX(0,IF((INDEX(T1_Rente,3)+0.000005)>Berekening!J10,(Berekening!J45-(INDEX(T1_Rente,3)+0.000005)*Berekening!J46)/(360*((INDEX(T1_Rente,3)+0.000005)-Berekening!J10)),IF((INDEX(T1_Rente,3)+0.000005)=Berekening!J10,IF(Berekening!J45-(INDEX(T1_Rente,3)+0.000005)*Berekening!J46<=0,-1000000000000,1000000000000),-1000000000000)),IF((INDEX(T1_Rente,3)-0.005+0.000005)<Berekening!J10,(Berekening!J45-(INDEX(T1_Rente,3)-0.005+0.000005)*Berekening!J46)/(360*((INDEX(T1_Rente,3)-0.005+0.000005)-Berekening!J10)),IF((INDEX(T1_Rente,3)-0.005+0.000005)=Berekening!J10,IF(Berekening!J45-(INDEX(T1_Rente,3)-0.005+0.000005)*Berekening!J46>0,-1000000000000,1000000000000),-1000000000000))) -> 0 | ... M20: =MAX(0,IF((INDEX(T1_Rente,3)+0.000005)>Berekening!M10,(Berekening!M45-(INDEX(T1_Rente,3)+0.000005)*Berekening!M46)/(360*((INDEX(T1_Rente,3)+0.000005)-Berekening!M10)),IF((INDEX(T1_Rente,3)+0.000005)=Berekening!M10,IF(Berekening!M45-(INDEX(T1_Rente,3)+0.000005)*Berekening!M46<=0,-1000000000000,1000000000000),-1000000000000)),IF((INDEX(T1_Rente,3)-0.005+0.000005)<Berekening!M10,(Berekening!M45-(INDEX(T1_Rente,3)-0.005+0.000005)*Berekening!M46)/(360*((INDEX(T1_Rente,3)-0.005+0.000005)-Berekening!M10)),IF((INDEX(T1_Rente,3)-0.005+0.000005)=Berekening!M10,IF(Berekening!M45-(INDEX(T1_Rente,3)-0.005+0.000005)*Berekening!M46>0,-1000000000000,1000000000000),-1000000000000))) -> 0
A21: Kolom 3: hoogste bedrag waarbij de gewogen rente in deze kolom valt | B21: € | C21: =MIN(1000000000000,IF((INDEX(T1_Rente,3)+0.000005)<Berekening!C10,(Berekening!C45-(INDEX(T1_Rente,3)+0.000005)*Berekening!C46)/(360*((INDEX(T1_Rente,3)+0.000005)-Berekening!C10)),1000000000000),IF((INDEX(T1_Rente,3)-0.005+0.000005)>Berekening!C10,(Berekening!C45-(INDEX(T1_Rente,3)-0.005+0.000005)*Berekening!C46)/(360*((INDEX(T1_Rente,3)-0.005+0.000005)-Berekening!C10)),1000000000000)) -> -144272.85 | D21: =MIN(1000000000000,IF((INDEX(T1_Rente,3)+0.000005)<Berekening!D10,(Berekening!D45-(INDEX(T1_Rente,3)+0.000005)*Berekening!D46)/(360*((INDEX(T1_Rente,3)+0.000005)-Berekening!D10)),1000000000000),IF((INDEX(T1_Rente,3)-0.005+0.000005)>Berekening!D10,(Berekening!D45-(INDEX(T1_Rente,3)-0.005+0.000005)*Berekening!D46)/(360*((INDEX(T1_Rente,3)-0.005+0.000005)-Berekening!D10)),1000000000000)) -> -202381.69 | E21: =MIN(1000000000000,IF((INDEX(T1_Rente,3)+0.000005)<Berekening!E10,(Berekening!E45-(INDEX(T1_Rente,3)+0.000005)*Berekening!E46)/(360*((INDEX(T1_Rente,3)+0.000005)-Berekening!E10)),1000000000000),IF((INDEX(T1_Rente,3)-0.005+0.000005)>Berekening!E10,(Berekening!E45-(INDEX(T1_Rente,3)-0.005+0.000005)*Berekening!E46)/(360*((INDEX(T1_Rente,3)-0.005+0.000005)-Berekening!E10)),1000000000000)) -> -653954.6 | F21: =MIN(1000000000000,IF((INDEX(T1_Rente,3)+0.000005)<Berekening!F10,(Berekening!F45-(INDEX(T1_Rente,3)+0.000005)*Berekening!F46)/(360*((INDEX(T1_Rente,3)+0.000005)-Berekening!F10)),1000000000000),IF((INDEX(T1_Rente,3)-0.005+0.000005)>Berekening!F10,(Berekening!F45-(INDEX(T1_Rente,3)-0.005+0.000005)*Berekening!F46)/(360*((INDEX(T1_Rente,3)-0.005+0.000005)-Berekening!F10)),1000000000000)) -> -126379.44 | G21: =MIN(1000000000000,IF((INDEX(T1_Rente,3)+0.000005)<Berekening!G10,(Berekening!G45-(INDEX(T1_Rente,3)+0.000005)*Berekening!G46)/(360*((INDEX(T1_Rente,3)+0.000005)-Berekening!G10)),1000000000000),IF((INDEX(T1_Rente,3)-0.005+0.000005)>Berekening!G10,(Berekening!G45-(INDEX(T1_Rente,3)-0.005+0.000005)*Berekening!G46)/(360*((INDEX(T1_Rente,3)-0.005+0.000005)-Berekening!G10)),1000000000000)) -> 0 | H21: =MIN(1000000000000,IF((INDEX(T1_Rente,3)+0.000005)<Berekening!H10,(Berekening!H45-(INDEX(T1_Rente,3)+0.000005)*Berekening!H46)/(360*((INDEX(T1_Rente,3)+0.000005)-Berekening!H10)),1000000000000),IF((INDEX(T1_Rente,3)-0.005+0.000005)>Berekening!H10,(Berekening!H45-(INDEX(T1_Rente,3)-0.005+0.000005)*Berekening!H46)/(360*((INDEX(T1_Rente,3)-0.005+0.000005)-Berekening!H10)),1000000000000)) -> 0 | I21: =MIN(1000000000000,IF((INDEX(T1_Rente,3)+0.000005)<Berekening!I10,(Berekening!I45-(INDEX(T1_Rente,3)+0.000005)*Berekening!I46)/(360*((INDEX(T1_Rente,3)+0.000005)-Berekening!I10)),1000000000000),IF((INDEX(T1_Rente,3)-0.005+0.000005)>Berekening!I10,(Berekening!I45-(INDEX(T1_Rente,3)-0.005+0.000005)*Berekening!I46)/(360*((INDEX(T1_Rente,3)-0.005+0.000005)-Berekening!I10)),1000000000000)) -> 0 | J21: =MIN(1000000000000,IF((INDEX(T1_Rente,3)+0.000005)<Berekening!J10,(Berekening!J45-(INDEX(T1_Rente,3)+0.000005)*Berekening!J46)/(360*((INDEX(T1_Rente,3)+0.000005)-Berekening!J10)),1000000000000),IF((INDEX(T1_Rente,3)-0.005+0.000005)>Berekening!J10,(Berekening!J45-(INDEX(T1_Rente,3)-0.005+0.000005)*Berekening!J46)/(360*((INDEX(T1_Rente,3)-0.005+0.000005)-Berekening!J10)),1000000000000)) -> -144272.85 | ... M21: =MIN(1000000000000,IF((INDEX(T1_Rente,3)+0.000005)<Berekening!M10,(Berekening!M45-(INDEX(T1_Rente,3)+0.000005)*Berekening!M46)/(360*((INDEX(T1_Rente,3)+0.000005)-Berekening!M10)),1000000000000),IF((INDEX(T1_Rente,3)-0.005+0.000005)>Berekening!M10,(Berekening!M45-(INDEX(T1_Rente,3)-0.005+0.000005)*Berekening!M46)/(360*((INDEX(T1_Rente,3)-0.005+0.000005)-Berekening!M10)),1000000000000)) -> -144272.85
A22: Kolom 3: haalbaar bedrag (−1 = onmogelijk) | B22: € | C22: =IF(C20>C21,-1,IF(C19<C20-0.000000001,-1,IF(C19>C21,MAX(C20,C21-1),C19))) -> -1 | D22: =IF(D20>D21,-1,IF(D19<D20-0.000000001,-1,IF(D19>D21,MAX(D20,D21-1),D19))) -> -1 | E22: =IF(E20>E21,-1,IF(E19<E20-0.000000001,-1,IF(E19>E21,MAX(E20,E21-1),E19))) -> -1 | F22: =IF(F20>F21,-1,IF(F19<F20-0.000000001,-1,IF(F19>F21,MAX(F20,F21-1),F19))) -> -1 | G22: =IF(G20>G21,-1,IF(G19<G20-0.000000001,-1,IF(G19>G21,MAX(G20,G21-1),G19))) -> 0 | H22: =IF(H20>H21,-1,IF(H19<H20-0.000000001,-1,IF(H19>H21,MAX(H20,H21-1),H19))) -> 0 | I22: =IF(I20>I21,-1,IF(I19<I20-0.000000001,-1,IF(I19>I21,MAX(I20,I21-1),I19))) -> 0 | J22: =IF(J20>J21,-1,IF(J19<J20-0.000000001,-1,IF(J19>J21,MAX(J20,J21-1),J19))) -> -1 | ... M22: =IF(M20>M21,-1,IF(M19<M20-0.000000001,-1,IF(M19>M21,MAX(M20,M21-1),M19))) -> -1
A23: Kolom 4: woonquote | B23: % | C23: =INDEX(T1_Tabel,Berekening!C80,4)+(Berekening!C79-INDEX(T1_Inkomen,Berekening!C80))/(INDEX(T1_Inkomen,Berekening!C80+1)-INDEX(T1_Inkomen,Berekening!C80))*(INDEX(T1_Tabel,Berekening!C80+1,4)-INDEX(T1_Tabel,Berekening!C80,4)) -> 0.255 | D23: =INDEX(T1_Tabel,Berekening!D80,4)+(Berekening!D79-INDEX(T1_Inkomen,Berekening!D80))/(INDEX(T1_Inkomen,Berekening!D80+1)-INDEX(T1_Inkomen,Berekening!D80))*(INDEX(T1_Tabel,Berekening!D80+1,4)-INDEX(T1_Tabel,Berekening!D80,4)) -> 0.255 | E23: =INDEX(T1_Tabel,Berekening!E80,4)+(Berekening!E79-INDEX(T1_Inkomen,Berekening!E80))/(INDEX(T1_Inkomen,Berekening!E80+1)-INDEX(T1_Inkomen,Berekening!E80))*(INDEX(T1_Tabel,Berekening!E80+1,4)-INDEX(T1_Tabel,Berekening!E80,4)) -> 0.255 | F23: =INDEX(T1_Tabel,Berekening!F80,4)+(Berekening!F79-INDEX(T1_Inkomen,Berekening!F80))/(INDEX(T1_Inkomen,Berekening!F80+1)-INDEX(T1_Inkomen,Berekening!F80))*(INDEX(T1_Tabel,Berekening!F80+1,4)-INDEX(T1_Tabel,Berekening!F80,4)) -> 0.255 | G23: =INDEX(T1_Tabel,Berekening!G80,4)+(Berekening!G79-INDEX(T1_Inkomen,Berekening!G80))/(INDEX(T1_Inkomen,Berekening!G80+1)-INDEX(T1_Inkomen,Berekening!G80))*(INDEX(T1_Tabel,Berekening!G80+1,4)-INDEX(T1_Tabel,Berekening!G80,4)) -> 0.207 | H23: =INDEX(T1_Tabel,Berekening!H80,4)+(Berekening!H79-INDEX(T1_Inkomen,Berekening!H80))/(INDEX(T1_Inkomen,Berekening!H80+1)-INDEX(T1_Inkomen,Berekening!H80))*(INDEX(T1_Tabel,Berekening!H80+1,4)-INDEX(T1_Tabel,Berekening!H80,4)) -> 0.255 | I23: =INDEX(T1_Tabel,Berekening!I80,4)+(Berekening!I79-INDEX(T1_Inkomen,Berekening!I80))/(INDEX(T1_Inkomen,Berekening!I80+1)-INDEX(T1_Inkomen,Berekening!I80))*(INDEX(T1_Tabel,Berekening!I80+1,4)-INDEX(T1_Tabel,Berekening!I80,4)) -> 0.255 | J23: =INDEX(T1_Tabel,Berekening!J80,4)+(Berekening!J79-INDEX(T1_Inkomen,Berekening!J80))/(INDEX(T1_Inkomen,Berekening!J80+1)-INDEX(T1_Inkomen,Berekening!J80))*(INDEX(T1_Tabel,Berekening!J80+1,4)-INDEX(T1_Tabel,Berekening!J80,4)) -> 0.255 | ... M23: =INDEX(T1_Tabel,Berekening!M80,4)+(Berekening!M79-INDEX(T1_Inkomen,Berekening!M80))/(INDEX(T1_Inkomen,Berekening!M80+1)-INDEX(T1_Inkomen,Berekening!M80))*(INDEX(T1_Tabel,Berekening!M80+1,4)-INDEX(T1_Tabel,Berekening!M80,4)) -> 0.255
A24: Kolom 4: bedrag als de woonquote van deze kolom geldt | B24: € | C24: =MAX(0,(C23*C6/12-Berekening!C18-Berekening!C44)*Berekening!C11-Berekening!C75+C7) -> 259582.94 | D24: =MAX(0,(D23*D6/12-Berekening!D18-Berekening!D44)*Berekening!D11-Berekening!D75+D7) -> 288634.49 | E24: =MAX(0,(E23*E6/12-Berekening!E18-Berekening!E44)*Berekening!E11-Berekening!E75+E7) -> 136935.4 | F24: =MAX(0,(F23*F6/12-Berekening!F18-Berekening!F44)*Berekening!F11-Berekening!F75+F7) -> 250849.43 | G24: =MAX(0,(G23*G6/12-Berekening!G18-Berekening!G44)*Berekening!G11-Berekening!G75+G7) -> 221792.71 | H24: =MAX(0,(H23*H6/12-Berekening!H18-Berekening!H44)*Berekening!H11-Berekening!H75+H7) -> 595189.94 | I24: =MAX(0,(I23*I6/12-Berekening!I18-Berekening!I44)*Berekening!I11-Berekening!I75+I7) -> 812354.85 | J24: =MAX(0,(J23*J6/12-Berekening!J18-Berekening!J44)*Berekening!J11-Berekening!J75+J7) -> 296869.01 | ... M24: =MAX(0,(M23*M6/12-Berekening!M18-Berekening!M44)*Berekening!M11-Berekening!M75+M7) -> 259582.94
A25: Kolom 4: laagste bedrag waarbij de gewogen rente in deze kolom valt | B25: € | C25: =MAX(0,IF((INDEX(T1_Rente,4)+0.000005)>Berekening!C10,(Berekening!C45-(INDEX(T1_Rente,4)+0.000005)*Berekening!C46)/(360*((INDEX(T1_Rente,4)+0.000005)-Berekening!C10)),IF((INDEX(T1_Rente,4)+0.000005)=Berekening!C10,IF(Berekening!C45-(INDEX(T1_Rente,4)+0.000005)*Berekening!C46<=0,-1000000000000,1000000000000),-1000000000000)),IF((INDEX(T1_Rente,4)-0.005+0.000005)<Berekening!C10,(Berekening!C45-(INDEX(T1_Rente,4)-0.005+0.000005)*Berekening!C46)/(360*((INDEX(T1_Rente,4)-0.005+0.000005)-Berekening!C10)),IF((INDEX(T1_Rente,4)-0.005+0.000005)=Berekening!C10,IF(Berekening!C45-(INDEX(T1_Rente,4)-0.005+0.000005)*Berekening!C46>0,-1000000000000,1000000000000),-1000000000000))) -> 0 | D25: =MAX(0,IF((INDEX(T1_Rente,4)+0.000005)>Berekening!D10,(Berekening!D45-(INDEX(T1_Rente,4)+0.000005)*Berekening!D46)/(360*((INDEX(T1_Rente,4)+0.000005)-Berekening!D10)),IF((INDEX(T1_Rente,4)+0.000005)=Berekening!D10,IF(Berekening!D45-(INDEX(T1_Rente,4)+0.000005)*Berekening!D46<=0,-1000000000000,1000000000000),-1000000000000)),IF((INDEX(T1_Rente,4)-0.005+0.000005)<Berekening!D10,(Berekening!D45-(INDEX(T1_Rente,4)-0.005+0.000005)*Berekening!D46)/(360*((INDEX(T1_Rente,4)-0.005+0.000005)-Berekening!D10)),IF((INDEX(T1_Rente,4)-0.005+0.000005)=Berekening!D10,IF(Berekening!D45-(INDEX(T1_Rente,4)-0.005+0.000005)*Berekening!D46>0,-1000000000000,1000000000000),-1000000000000))) -> 0 | E25: =MAX(0,IF((INDEX(T1_Rente,4)+0.000005)>Berekening!E10,(Berekening!E45-(INDEX(T1_Rente,4)+0.000005)*Berekening!E46)/(360*((INDEX(T1_Rente,4)+0.000005)-Berekening!E10)),IF((INDEX(T1_Rente,4)+0.000005)=Berekening!E10,IF(Berekening!E45-(INDEX(T1_Rente,4)+0.000005)*Berekening!E46<=0,-1000000000000,1000000000000),-1000000000000)),IF((INDEX(T1_Rente,4)-0.005+0.000005)<Berekening!E10,(Berekening!E45-(INDEX(T1_Rente,4)-0.005+0.000005)*Berekening!E46)/(360*((INDEX(T1_Rente,4)-0.005+0.000005)-Berekening!E10)),IF((INDEX(T1_Rente,4)-0.005+0.000005)=Berekening!E10,IF(Berekening!E45-(INDEX(T1_Rente,4)-0.005+0.000005)*Berekening!E46>0,-1000000000000,1000000000000),-1000000000000))) -> 0 | F25: =MAX(0,IF((INDEX(T1_Rente,4)+0.000005)>Berekening!F10,(Berekening!F45-(INDEX(T1_Rente,4)+0.000005)*Berekening!F46)/(360*((INDEX(T1_Rente,4)+0.000005)-Berekening!F10)),IF((INDEX(T1_Rente,4)+0.000005)=Berekening!F10,IF(Berekening!F45-(INDEX(T1_Rente,4)+0.000005)*Berekening!F46<=0,-1000000000000,1000000000000),-1000000000000)),IF((INDEX(T1_Rente,4)-0.005+0.000005)<Berekening!F10,(Berekening!F45-(INDEX(T1_Rente,4)-0.005+0.000005)*Berekening!F46)/(360*((INDEX(T1_Rente,4)-0.005+0.000005)-Berekening!F10)),IF((INDEX(T1_Rente,4)-0.005+0.000005)=Berekening!F10,IF(Berekening!F45-(INDEX(T1_Rente,4)-0.005+0.000005)*Berekening!F46>0,-1000000000000,1000000000000),-1000000000000))) -> 0 | G25: =MAX(0,IF((INDEX(T1_Rente,4)+0.000005)>Berekening!G10,(Berekening!G45-(INDEX(T1_Rente,4)+0.000005)*Berekening!G46)/(360*((INDEX(T1_Rente,4)+0.000005)-Berekening!G10)),IF((INDEX(T1_Rente,4)+0.000005)=Berekening!G10,IF(Berekening!G45-(INDEX(T1_Rente,4)+0.000005)*Berekening!G46<=0,-1000000000000,1000000000000),-1000000000000)),IF((INDEX(T1_Rente,4)-0.005+0.000005)<Berekening!G10,(Berekening!G45-(INDEX(T1_Rente,4)-0.005+0.000005)*Berekening!G46)/(360*((INDEX(T1_Rente,4)-0.005+0.000005)-Berekening!G10)),IF((INDEX(T1_Rente,4)-0.005+0.000005)=Berekening!G10,IF(Berekening!G45-(INDEX(T1_Rente,4)-0.005+0.000005)*Berekening!G46>0,-1000000000000,1000000000000),-1000000000000))) -> 0 | H25: =MAX(0,IF((INDEX(T1_Rente,4)+0.000005)>Berekening!H10,(Berekening!H45-(INDEX(T1_Rente,4)+0.000005)*Berekening!H46)/(360*((INDEX(T1_Rente,4)+0.000005)-Berekening!H10)),IF((INDEX(T1_Rente,4)+0.000005)=Berekening!H10,IF(Berekening!H45-(INDEX(T1_Rente,4)+0.000005)*Berekening!H46<=0,-1000000000000,1000000000000),-1000000000000)),IF((INDEX(T1_Rente,4)-0.005+0.000005)<Berekening!H10,(Berekening!H45-(INDEX(T1_Rente,4)-0.005+0.000005)*Berekening!H46)/(360*((INDEX(T1_Rente,4)-0.005+0.000005)-Berekening!H10)),IF((INDEX(T1_Rente,4)-0.005+0.000005)=Berekening!H10,IF(Berekening!H45-(INDEX(T1_Rente,4)-0.005+0.000005)*Berekening!H46>0,-1000000000000,1000000000000),-1000000000000))) -> 0 | I25: =MAX(0,IF((INDEX(T1_Rente,4)+0.000005)>Berekening!I10,(Berekening!I45-(INDEX(T1_Rente,4)+0.000005)*Berekening!I46)/(360*((INDEX(T1_Rente,4)+0.000005)-Berekening!I10)),IF((INDEX(T1_Rente,4)+0.000005)=Berekening!I10,IF(Berekening!I45-(INDEX(T1_Rente,4)+0.000005)*Berekening!I46<=0,-1000000000000,1000000000000),-1000000000000)),IF((INDEX(T1_Rente,4)-0.005+0.000005)<Berekening!I10,(Berekening!I45-(INDEX(T1_Rente,4)-0.005+0.000005)*Berekening!I46)/(360*((INDEX(T1_Rente,4)-0.005+0.000005)-Berekening!I10)),IF((INDEX(T1_Rente,4)-0.005+0.000005)=Berekening!I10,IF(Berekening!I45-(INDEX(T1_Rente,4)-0.005+0.000005)*Berekening!I46>0,-1000000000000,1000000000000),-1000000000000))) -> 0 | J25: =MAX(0,IF((INDEX(T1_Rente,4)+0.000005)>Berekening!J10,(Berekening!J45-(INDEX(T1_Rente,4)+0.000005)*Berekening!J46)/(360*((INDEX(T1_Rente,4)+0.000005)-Berekening!J10)),IF((INDEX(T1_Rente,4)+0.000005)=Berekening!J10,IF(Berekening!J45-(INDEX(T1_Rente,4)+0.000005)*Berekening!J46<=0,-1000000000000,1000000000000),-1000000000000)),IF((INDEX(T1_Rente,4)-0.005+0.000005)<Berekening!J10,(Berekening!J45-(INDEX(T1_Rente,4)-0.005+0.000005)*Berekening!J46)/(360*((INDEX(T1_Rente,4)-0.005+0.000005)-Berekening!J10)),IF((INDEX(T1_Rente,4)-0.005+0.000005)=Berekening!J10,IF(Berekening!J45-(INDEX(T1_Rente,4)-0.005+0.000005)*Berekening!J46>0,-1000000000000,1000000000000),-1000000000000))) -> 0 | ... M25: =MAX(0,IF((INDEX(T1_Rente,4)+0.000005)>Berekening!M10,(Berekening!M45-(INDEX(T1_Rente,4)+0.000005)*Berekening!M46)/(360*((INDEX(T1_Rente,4)+0.000005)-Berekening!M10)),IF((INDEX(T1_Rente,4)+0.000005)=Berekening!M10,IF(Berekening!M45-(INDEX(T1_Rente,4)+0.000005)*Berekening!M46<=0,-1000000000000,1000000000000),-1000000000000)),IF((INDEX(T1_Rente,4)-0.005+0.000005)<Berekening!M10,(Berekening!M45-(INDEX(T1_Rente,4)-0.005+0.000005)*Berekening!M46)/(360*((INDEX(T1_Rente,4)-0.005+0.000005)-Berekening!M10)),IF((INDEX(T1_Rente,4)-0.005+0.000005)=Berekening!M10,IF(Berekening!M45-(INDEX(T1_Rente,4)-0.005+0.000005)*Berekening!M46>0,-1000000000000,1000000000000),-1000000000000))) -> 0
A26: Kolom 4: hoogste bedrag waarbij de gewogen rente in deze kolom valt | B26: € | C26: =MIN(1000000000000,IF((INDEX(T1_Rente,4)+0.000005)<Berekening!C10,(Berekening!C45-(INDEX(T1_Rente,4)+0.000005)*Berekening!C46)/(360*((INDEX(T1_Rente,4)+0.000005)-Berekening!C10)),1000000000000),IF((INDEX(T1_Rente,4)-0.005+0.000005)>Berekening!C10,(Berekening!C45-(INDEX(T1_Rente,4)-0.005+0.000005)*Berekening!C46)/(360*((INDEX(T1_Rente,4)-0.005+0.000005)-Berekening!C10)),1000000000000)) -> -17437.939 | D26: =MIN(1000000000000,IF((INDEX(T1_Rente,4)+0.000005)<Berekening!D10,(Berekening!D45-(INDEX(T1_Rente,4)+0.000005)*Berekening!D46)/(360*((INDEX(T1_Rente,4)+0.000005)-Berekening!D10)),1000000000000),IF((INDEX(T1_Rente,4)-0.005+0.000005)>Berekening!D10,(Berekening!D45-(INDEX(T1_Rente,4)-0.005+0.000005)*Berekening!D46)/(360*((INDEX(T1_Rente,4)-0.005+0.000005)-Berekening!D10)),1000000000000)) -> -77679.636 | E26: =MIN(1000000000000,IF((INDEX(T1_Rente,4)+0.000005)<Berekening!E10,(Berekening!E45-(INDEX(T1_Rente,4)+0.000005)*Berekening!E46)/(360*((INDEX(T1_Rente,4)+0.000005)-Berekening!E10)),1000000000000),IF((INDEX(T1_Rente,4)-0.005+0.000005)>Berekening!E10,(Berekening!E45-(INDEX(T1_Rente,4)-0.005+0.000005)*Berekening!E46)/(360*((INDEX(T1_Rente,4)-0.005+0.000005)-Berekening!E10)),1000000000000)) -> -677957.74 | F26: =MIN(1000000000000,IF((INDEX(T1_Rente,4)+0.000005)<Berekening!F10,(Berekening!F45-(INDEX(T1_Rente,4)+0.000005)*Berekening!F46)/(360*((INDEX(T1_Rente,4)+0.000005)-Berekening!F10)),1000000000000),IF((INDEX(T1_Rente,4)-0.005+0.000005)>Berekening!F10,(Berekening!F45-(INDEX(T1_Rente,4)-0.005+0.000005)*Berekening!F46)/(360*((INDEX(T1_Rente,4)-0.005+0.000005)-Berekening!F10)),1000000000000)) -> -14734.383 | G26: =MIN(1000000000000,IF((INDEX(T1_Rente,4)+0.000005)<Berekening!G10,(Berekening!G45-(INDEX(T1_Rente,4)+0.000005)*Berekening!G46)/(360*((INDEX(T1_Rente,4)+0.000005)-Berekening!G10)),1000000000000),IF((INDEX(T1_Rente,4)-0.005+0.000005)>Berekening!G10,(Berekening!G45-(INDEX(T1_Rente,4)-0.005+0.000005)*Berekening!G46)/(360*((INDEX(T1_Rente,4)-0.005+0.000005)-Berekening!G10)),1000000000000)) -> 0 | H26: =MIN(1000000000000,IF((INDEX(T1_Rente,4)+0.000005)<Berekening!H10,(Berekening!H45-(INDEX(T1_Rente,4)+0.000005)*Berekening!H46)/(360*((INDEX(T1_Rente,4)+0.000005)-Berekening!H10)),1000000000000),IF((INDEX(T1_Rente,4)-0.005+0.000005)>Berekening!H10,(Berekening!H45-(INDEX(T1_Rente,4)-0.005+0.000005)*Berekening!H46)/(360*((INDEX(T1_Rente,4)-0.005+0.000005)-Berekening!H10)),1000000000000)) -> 0 | I26: =MIN(1000000000000,IF((INDEX(T1_Rente,4)+0.000005)<Berekening!I10,(Berekening!I45-(INDEX(T1_Rente,4)+0.000005)*Berekening!I46)/(360*((INDEX(T1_Rente,4)+0.000005)-Berekening!I10)),1000000000000),IF((INDEX(T1_Rente,4)-0.005+0.000005)>Berekening!I10,(Berekening!I45-(INDEX(T1_Rente,4)-0.005+0.000005)*Berekening!I46)/(360*((INDEX(T1_Rente,4)-0.005+0.000005)-Berekening!I10)),1000000000000)) -> 0 | J26: =MIN(1000000000000,IF((INDEX(T1_Rente,4)+0.000005)<Berekening!J10,(Berekening!J45-(INDEX(T1_Rente,4)+0.000005)*Berekening!J46)/(360*((INDEX(T1_Rente,4)+0.000005)-Berekening!J10)),1000000000000),IF((INDEX(T1_Rente,4)-0.005+0.000005)>Berekening!J10,(Berekening!J45-(INDEX(T1_Rente,4)-0.005+0.000005)*Berekening!J46)/(360*((INDEX(T1_Rente,4)-0.005+0.000005)-Berekening!J10)),1000000000000)) -> -17437.939 | ... M26: =MIN(1000000000000,IF((INDEX(T1_Rente,4)+0.000005)<Berekening!M10,(Berekening!M45-(INDEX(T1_Rente,4)+0.000005)*Berekening!M46)/(360*((INDEX(T1_Rente,4)+0.000005)-Berekening!M10)),1000000000000),IF((INDEX(T1_Rente,4)-0.005+0.000005)>Berekening!M10,(Berekening!M45-(INDEX(T1_Rente,4)-0.005+0.000005)*Berekening!M46)/(360*((INDEX(T1_Rente,4)-0.005+0.000005)-Berekening!M10)),1000000000000)) -> -17437.939
A27: Kolom 4: haalbaar bedrag (−1 = onmogelijk) | B27: € | C27: =IF(C25>C26,-1,IF(C24<C25-0.000000001,-1,IF(C24>C26,MAX(C25,C26-1),C24))) -> -1 | D27: =IF(D25>D26,-1,IF(D24<D25-0.000000001,-1,IF(D24>D26,MAX(D25,D26-1),D24))) -> -1 | E27: =IF(E25>E26,-1,IF(E24<E25-0.000000001,-1,IF(E24>E26,MAX(E25,E26-1),E24))) -> -1 | F27: =IF(F25>F26,-1,IF(F24<F25-0.000000001,-1,IF(F24>F26,MAX(F25,F26-1),F24))) -> -1 | G27: =IF(G25>G26,-1,IF(G24<G25-0.000000001,-1,IF(G24>G26,MAX(G25,G26-1),G24))) -> 0 | H27: =IF(H25>H26,-1,IF(H24<H25-0.000000001,-1,IF(H24>H26,MAX(H25,H26-1),H24))) -> 0 | I27: =IF(I25>I26,-1,IF(I24<I25-0.000000001,-1,IF(I24>I26,MAX(I25,I26-1),I24))) -> 0 | J27: =IF(J25>J26,-1,IF(J24<J25-0.000000001,-1,IF(J24>J26,MAX(J25,J26-1),J24))) -> -1 | ... M27: =IF(M25>M26,-1,IF(M24<M25-0.000000001,-1,IF(M24>M26,MAX(M25,M26-1),M24))) -> -1
A28: Kolom 5: woonquote | B28: % | C28: =INDEX(T1_Tabel,Berekening!C80,5)+(Berekening!C79-INDEX(T1_Inkomen,Berekening!C80))/(INDEX(T1_Inkomen,Berekening!C80+1)-INDEX(T1_Inkomen,Berekening!C80))*(INDEX(T1_Tabel,Berekening!C80+1,5)-INDEX(T1_Tabel,Berekening!C80,5)) -> 0.2645 | D28: =INDEX(T1_Tabel,Berekening!D80,5)+(Berekening!D79-INDEX(T1_Inkomen,Berekening!D80))/(INDEX(T1_Inkomen,Berekening!D80+1)-INDEX(T1_Inkomen,Berekening!D80))*(INDEX(T1_Tabel,Berekening!D80+1,5)-INDEX(T1_Tabel,Berekening!D80,5)) -> 0.2645 | E28: =INDEX(T1_Tabel,Berekening!E80,5)+(Berekening!E79-INDEX(T1_Inkomen,Berekening!E80))/(INDEX(T1_Inkomen,Berekening!E80+1)-INDEX(T1_Inkomen,Berekening!E80))*(INDEX(T1_Tabel,Berekening!E80+1,5)-INDEX(T1_Tabel,Berekening!E80,5)) -> 0.2645 | F28: =INDEX(T1_Tabel,Berekening!F80,5)+(Berekening!F79-INDEX(T1_Inkomen,Berekening!F80))/(INDEX(T1_Inkomen,Berekening!F80+1)-INDEX(T1_Inkomen,Berekening!F80))*(INDEX(T1_Tabel,Berekening!F80+1,5)-INDEX(T1_Tabel,Berekening!F80,5)) -> 0.2645 | G28: =INDEX(T1_Tabel,Berekening!G80,5)+(Berekening!G79-INDEX(T1_Inkomen,Berekening!G80))/(INDEX(T1_Inkomen,Berekening!G80+1)-INDEX(T1_Inkomen,Berekening!G80))*(INDEX(T1_Tabel,Berekening!G80+1,5)-INDEX(T1_Tabel,Berekening!G80,5)) -> 0.2165 | H28: =INDEX(T1_Tabel,Berekening!H80,5)+(Berekening!H79-INDEX(T1_Inkomen,Berekening!H80))/(INDEX(T1_Inkomen,Berekening!H80+1)-INDEX(T1_Inkomen,Berekening!H80))*(INDEX(T1_Tabel,Berekening!H80+1,5)-INDEX(T1_Tabel,Berekening!H80,5)) -> 0.2645 | I28: =INDEX(T1_Tabel,Berekening!I80,5)+(Berekening!I79-INDEX(T1_Inkomen,Berekening!I80))/(INDEX(T1_Inkomen,Berekening!I80+1)-INDEX(T1_Inkomen,Berekening!I80))*(INDEX(T1_Tabel,Berekening!I80+1,5)-INDEX(T1_Tabel,Berekening!I80,5)) -> 0.2645 | J28: =INDEX(T1_Tabel,Berekening!J80,5)+(Berekening!J79-INDEX(T1_Inkomen,Berekening!J80))/(INDEX(T1_Inkomen,Berekening!J80+1)-INDEX(T1_Inkomen,Berekening!J80))*(INDEX(T1_Tabel,Berekening!J80+1,5)-INDEX(T1_Tabel,Berekening!J80,5)) -> 0.2645 | ... M28: =INDEX(T1_Tabel,Berekening!M80,5)+(Berekening!M79-INDEX(T1_Inkomen,Berekening!M80))/(INDEX(T1_Inkomen,Berekening!M80+1)-INDEX(T1_Inkomen,Berekening!M80))*(INDEX(T1_Tabel,Berekening!M80+1,5)-INDEX(T1_Tabel,Berekening!M80,5)) -> 0.2645
A29: Kolom 5: bedrag als de woonquote van deze kolom geldt | B29: € | C29: =MAX(0,(C28*C6/12-Berekening!C18-Berekening!C44)*Berekening!C11-Berekening!C75+C7) -> 293967.56 | D29: =MAX(0,(D28*D6/12-Berekening!D18-Berekening!D44)*Berekening!D11-Berekening!D75+D7) -> 323019.11 | E29: =MAX(0,(E28*E6/12-Berekening!E18-Berekening!E44)*Berekening!E11-Berekening!E75+E7) -> 171320.01 | F29: =MAX(0,(F28*F6/12-Berekening!F18-Berekening!F44)*Berekening!F11-Berekening!F75+F7) -> 284030.84 | G29: =MAX(0,(G28*G6/12-Berekening!G18-Berekening!G44)*Berekening!G11-Berekening!G75+G7) -> 230961.94 | H29: =MAX(0,(H28*H6/12-Berekening!H18-Berekening!H44)*Berekening!H11-Berekening!H75+H7) -> 618113.02 | I29: =MAX(0,(I28*I6/12-Berekening!I18-Berekening!I44)*Berekening!I11-Berekening!I75+I7) -> 846739.46 | J29: =MAX(0,(J28*J6/12-Berekening!J18-Berekening!J44)*Berekening!J11-Berekening!J75+J7) -> 331253.63 | ... M29: =MAX(0,(M28*M6/12-Berekening!M18-Berekening!M44)*Berekening!M11-Berekening!M75+M7) -> 293967.56
A30: Kolom 5: laagste bedrag waarbij de gewogen rente in deze kolom valt | B30: € | C30: =MAX(0,IF((INDEX(T1_Rente,5)+0.000005)>Berekening!C10,(Berekening!C45-(INDEX(T1_Rente,5)+0.000005)*Berekening!C46)/(360*((INDEX(T1_Rente,5)+0.000005)-Berekening!C10)),IF((INDEX(T1_Rente,5)+0.000005)=Berekening!C10,IF(Berekening!C45-(INDEX(T1_Rente,5)+0.000005)*Berekening!C46<=0,-1000000000000,1000000000000),-1000000000000)),IF((INDEX(T1_Rente,5)-0.005+0.000005)<Berekening!C10,(Berekening!C45-(INDEX(T1_Rente,5)-0.005+0.000005)*Berekening!C46)/(360*((INDEX(T1_Rente,5)-0.005+0.000005)-Berekening!C10)),IF((INDEX(T1_Rente,5)-0.005+0.000005)=Berekening!C10,IF(Berekening!C45-(INDEX(T1_Rente,5)-0.005+0.000005)*Berekening!C46>0,-1000000000000,1000000000000),-1000000000000))) -> 0 | D30: =MAX(0,IF((INDEX(T1_Rente,5)+0.000005)>Berekening!D10,(Berekening!D45-(INDEX(T1_Rente,5)+0.000005)*Berekening!D46)/(360*((INDEX(T1_Rente,5)+0.000005)-Berekening!D10)),IF((INDEX(T1_Rente,5)+0.000005)=Berekening!D10,IF(Berekening!D45-(INDEX(T1_Rente,5)+0.000005)*Berekening!D46<=0,-1000000000000,1000000000000),-1000000000000)),IF((INDEX(T1_Rente,5)-0.005+0.000005)<Berekening!D10,(Berekening!D45-(INDEX(T1_Rente,5)-0.005+0.000005)*Berekening!D46)/(360*((INDEX(T1_Rente,5)-0.005+0.000005)-Berekening!D10)),IF((INDEX(T1_Rente,5)-0.005+0.000005)=Berekening!D10,IF(Berekening!D45-(INDEX(T1_Rente,5)-0.005+0.000005)*Berekening!D46>0,-1000000000000,1000000000000),-1000000000000))) -> 0 | E30: =MAX(0,IF((INDEX(T1_Rente,5)+0.000005)>Berekening!E10,(Berekening!E45-(INDEX(T1_Rente,5)+0.000005)*Berekening!E46)/(360*((INDEX(T1_Rente,5)+0.000005)-Berekening!E10)),IF((INDEX(T1_Rente,5)+0.000005)=Berekening!E10,IF(Berekening!E45-(INDEX(T1_Rente,5)+0.000005)*Berekening!E46<=0,-1000000000000,1000000000000),-1000000000000)),IF((INDEX(T1_Rente,5)-0.005+0.000005)<Berekening!E10,(Berekening!E45-(INDEX(T1_Rente,5)-0.005+0.000005)*Berekening!E46)/(360*((INDEX(T1_Rente,5)-0.005+0.000005)-Berekening!E10)),IF((INDEX(T1_Rente,5)-0.005+0.000005)=Berekening!E10,IF(Berekening!E45-(INDEX(T1_Rente,5)-0.005+0.000005)*Berekening!E46>0,-1000000000000,1000000000000),-1000000000000))) -> 0 | F30: =MAX(0,IF((INDEX(T1_Rente,5)+0.000005)>Berekening!F10,(Berekening!F45-(INDEX(T1_Rente,5)+0.000005)*Berekening!F46)/(360*((INDEX(T1_Rente,5)+0.000005)-Berekening!F10)),IF((INDEX(T1_Rente,5)+0.000005)=Berekening!F10,IF(Berekening!F45-(INDEX(T1_Rente,5)+0.000005)*Berekening!F46<=0,-1000000000000,1000000000000),-1000000000000)),IF((INDEX(T1_Rente,5)-0.005+0.000005)<Berekening!F10,(Berekening!F45-(INDEX(T1_Rente,5)-0.005+0.000005)*Berekening!F46)/(360*((INDEX(T1_Rente,5)-0.005+0.000005)-Berekening!F10)),IF((INDEX(T1_Rente,5)-0.005+0.000005)=Berekening!F10,IF(Berekening!F45-(INDEX(T1_Rente,5)-0.005+0.000005)*Berekening!F46>0,-1000000000000,1000000000000),-1000000000000))) -> 0 | G30: =MAX(0,IF((INDEX(T1_Rente,5)+0.000005)>Berekening!G10,(Berekening!G45-(INDEX(T1_Rente,5)+0.000005)*Berekening!G46)/(360*((INDEX(T1_Rente,5)+0.000005)-Berekening!G10)),IF((INDEX(T1_Rente,5)+0.000005)=Berekening!G10,IF(Berekening!G45-(INDEX(T1_Rente,5)+0.000005)*Berekening!G46<=0,-1000000000000,1000000000000),-1000000000000)),IF((INDEX(T1_Rente,5)-0.005+0.000005)<Berekening!G10,(Berekening!G45-(INDEX(T1_Rente,5)-0.005+0.000005)*Berekening!G46)/(360*((INDEX(T1_Rente,5)-0.005+0.000005)-Berekening!G10)),IF((INDEX(T1_Rente,5)-0.005+0.000005)=Berekening!G10,IF(Berekening!G45-(INDEX(T1_Rente,5)-0.005+0.000005)*Berekening!G46>0,-1000000000000,1000000000000),-1000000000000))) -> 0 | H30: =MAX(0,IF((INDEX(T1_Rente,5)+0.000005)>Berekening!H10,(Berekening!H45-(INDEX(T1_Rente,5)+0.000005)*Berekening!H46)/(360*((INDEX(T1_Rente,5)+0.000005)-Berekening!H10)),IF((INDEX(T1_Rente,5)+0.000005)=Berekening!H10,IF(Berekening!H45-(INDEX(T1_Rente,5)+0.000005)*Berekening!H46<=0,-1000000000000,1000000000000),-1000000000000)),IF((INDEX(T1_Rente,5)-0.005+0.000005)<Berekening!H10,(Berekening!H45-(INDEX(T1_Rente,5)-0.005+0.000005)*Berekening!H46)/(360*((INDEX(T1_Rente,5)-0.005+0.000005)-Berekening!H10)),IF((INDEX(T1_Rente,5)-0.005+0.000005)=Berekening!H10,IF(Berekening!H45-(INDEX(T1_Rente,5)-0.005+0.000005)*Berekening!H46>0,-1000000000000,1000000000000),-1000000000000))) -> 0 | I30: =MAX(0,IF((INDEX(T1_Rente,5)+0.000005)>Berekening!I10,(Berekening!I45-(INDEX(T1_Rente,5)+0.000005)*Berekening!I46)/(360*((INDEX(T1_Rente,5)+0.000005)-Berekening!I10)),IF((INDEX(T1_Rente,5)+0.000005)=Berekening!I10,IF(Berekening!I45-(INDEX(T1_Rente,5)+0.000005)*Berekening!I46<=0,-1000000000000,1000000000000),-1000000000000)),IF((INDEX(T1_Rente,5)-0.005+0.000005)<Berekening!I10,(Berekening!I45-(INDEX(T1_Rente,5)-0.005+0.000005)*Berekening!I46)/(360*((INDEX(T1_Rente,5)-0.005+0.000005)-Berekening!I10)),IF((INDEX(T1_Rente,5)-0.005+0.000005)=Berekening!I10,IF(Berekening!I45-(INDEX(T1_Rente,5)-0.005+0.000005)*Berekening!I46>0,-1000000000000,1000000000000),-1000000000000))) -> 0 | J30: =MAX(0,IF((INDEX(T1_Rente,5)+0.000005)>Berekening!J10,(Berekening!J45-(INDEX(T1_Rente,5)+0.000005)*Berekening!J46)/(360*((INDEX(T1_Rente,5)+0.000005)-Berekening!J10)),IF((INDEX(T1_Rente,5)+0.000005)=Berekening!J10,IF(Berekening!J45-(INDEX(T1_Rente,5)+0.000005)*Berekening!J46<=0,-1000000000000,1000000000000),-1000000000000)),IF((INDEX(T1_Rente,5)-0.005+0.000005)<Berekening!J10,(Berekening!J45-(INDEX(T1_Rente,5)-0.005+0.000005)*Berekening!J46)/(360*((INDEX(T1_Rente,5)-0.005+0.000005)-Berekening!J10)),IF((INDEX(T1_Rente,5)-0.005+0.000005)=Berekening!J10,IF(Berekening!J45-(INDEX(T1_Rente,5)-0.005+0.000005)*Berekening!J46>0,-1000000000000,1000000000000),-1000000000000))) -> 0 | ... M30: =MAX(0,IF((INDEX(T1_Rente,5)+0.000005)>Berekening!M10,(Berekening!M45-(INDEX(T1_Rente,5)+0.000005)*Berekening!M46)/(360*((INDEX(T1_Rente,5)+0.000005)-Berekening!M10)),IF((INDEX(T1_Rente,5)+0.000005)=Berekening!M10,IF(Berekening!M45-(INDEX(T1_Rente,5)+0.000005)*Berekening!M46<=0,-1000000000000,1000000000000),-1000000000000)),IF((INDEX(T1_Rente,5)-0.005+0.000005)<Berekening!M10,(Berekening!M45-(INDEX(T1_Rente,5)-0.005+0.000005)*Berekening!M46)/(360*((INDEX(T1_Rente,5)-0.005+0.000005)-Berekening!M10)),IF((INDEX(T1_Rente,5)-0.005+0.000005)=Berekening!M10,IF(Berekening!M45-(INDEX(T1_Rente,5)-0.005+0.000005)*Berekening!M46>0,-1000000000000,1000000000000),-1000000000000))) -> 0
A31: Kolom 5: hoogste bedrag waarbij de gewogen rente in deze kolom valt | B31: € | C31: =MIN(1000000000000,IF((INDEX(T1_Rente,5)+0.000005)<Berekening!C10,(Berekening!C45-(INDEX(T1_Rente,5)+0.000005)*Berekening!C46)/(360*((INDEX(T1_Rente,5)+0.000005)-Berekening!C10)),1000000000000),IF((INDEX(T1_Rente,5)-0.005+0.000005)>Berekening!C10,(Berekening!C45-(INDEX(T1_Rente,5)-0.005+0.000005)*Berekening!C46)/(360*((INDEX(T1_Rente,5)-0.005+0.000005)-Berekening!C10)),1000000000000)) -> 216025.73 | D31: =MIN(1000000000000,IF((INDEX(T1_Rente,5)+0.000005)<Berekening!D10,(Berekening!D45-(INDEX(T1_Rente,5)+0.000005)*Berekening!D46)/(360*((INDEX(T1_Rente,5)+0.000005)-Berekening!D10)),1000000000000),IF((INDEX(T1_Rente,5)-0.005+0.000005)>Berekening!D10,(Berekening!D45-(INDEX(T1_Rente,5)-0.005+0.000005)*Berekening!D46)/(360*((INDEX(T1_Rente,5)-0.005+0.000005)-Berekening!D10)),1000000000000)) -> 151858.1 | E31: =MIN(1000000000000,IF((INDEX(T1_Rente,5)+0.000005)<Berekening!E10,(Berekening!E45-(INDEX(T1_Rente,5)+0.000005)*Berekening!E46)/(360*((INDEX(T1_Rente,5)+0.000005)-Berekening!E10)),1000000000000),IF((INDEX(T1_Rente,5)-0.005+0.000005)>Berekening!E10,(Berekening!E45-(INDEX(T1_Rente,5)-0.005+0.000005)*Berekening!E46)/(360*((INDEX(T1_Rente,5)-0.005+0.000005)-Berekening!E10)),1000000000000)) -> -722140.05 | F31: =MIN(1000000000000,IF((INDEX(T1_Rente,5)+0.000005)<Berekening!F10,(Berekening!F45-(INDEX(T1_Rente,5)+0.000005)*Berekening!F46)/(360*((INDEX(T1_Rente,5)+0.000005)-Berekening!F10)),1000000000000),IF((INDEX(T1_Rente,5)-0.005+0.000005)>Berekening!F10,(Berekening!F45-(INDEX(T1_Rente,5)-0.005+0.000005)*Berekening!F46)/(360*((INDEX(T1_Rente,5)-0.005+0.000005)-Berekening!F10)),1000000000000)) -> 171365.53 | G31: =MIN(1000000000000,IF((INDEX(T1_Rente,5)+0.000005)<Berekening!G10,(Berekening!G45-(INDEX(T1_Rente,5)+0.000005)*Berekening!G46)/(360*((INDEX(T1_Rente,5)+0.000005)-Berekening!G10)),1000000000000),IF((INDEX(T1_Rente,5)-0.005+0.000005)>Berekening!G10,(Berekening!G45-(INDEX(T1_Rente,5)-0.005+0.000005)*Berekening!G46)/(360*((INDEX(T1_Rente,5)-0.005+0.000005)-Berekening!G10)),1000000000000)) -> 0 | H31: =MIN(1000000000000,IF((INDEX(T1_Rente,5)+0.000005)<Berekening!H10,(Berekening!H45-(INDEX(T1_Rente,5)+0.000005)*Berekening!H46)/(360*((INDEX(T1_Rente,5)+0.000005)-Berekening!H10)),1000000000000),IF((INDEX(T1_Rente,5)-0.005+0.000005)>Berekening!H10,(Berekening!H45-(INDEX(T1_Rente,5)-0.005+0.000005)*Berekening!H46)/(360*((INDEX(T1_Rente,5)-0.005+0.000005)-Berekening!H10)),1000000000000)) -> 0 | I31: =MIN(1000000000000,IF((INDEX(T1_Rente,5)+0.000005)<Berekening!I10,(Berekening!I45-(INDEX(T1_Rente,5)+0.000005)*Berekening!I46)/(360*((INDEX(T1_Rente,5)+0.000005)-Berekening!I10)),1000000000000),IF((INDEX(T1_Rente,5)-0.005+0.000005)>Berekening!I10,(Berekening!I45-(INDEX(T1_Rente,5)-0.005+0.000005)*Berekening!I46)/(360*((INDEX(T1_Rente,5)-0.005+0.000005)-Berekening!I10)),1000000000000)) -> 0 | J31: =MIN(1000000000000,IF((INDEX(T1_Rente,5)+0.000005)<Berekening!J10,(Berekening!J45-(INDEX(T1_Rente,5)+0.000005)*Berekening!J46)/(360*((INDEX(T1_Rente,5)+0.000005)-Berekening!J10)),1000000000000),IF((INDEX(T1_Rente,5)-0.005+0.000005)>Berekening!J10,(Berekening!J45-(INDEX(T1_Rente,5)-0.005+0.000005)*Berekening!J46)/(360*((INDEX(T1_Rente,5)-0.005+0.000005)-Berekening!J10)),1000000000000)) -> 216025.73 | ... M31: =MIN(1000000000000,IF((INDEX(T1_Rente,5)+0.000005)<Berekening!M10,(Berekening!M45-(INDEX(T1_Rente,5)+0.000005)*Berekening!M46)/(360*((INDEX(T1_Rente,5)+0.000005)-Berekening!M10)),1000000000000),IF((INDEX(T1_Rente,5)-0.005+0.000005)>Berekening!M10,(Berekening!M45-(INDEX(T1_Rente,5)-0.005+0.000005)*Berekening!M46)/(360*((INDEX(T1_Rente,5)-0.005+0.000005)-Berekening!M10)),1000000000000)) -> 216025.73
A32: Kolom 5: haalbaar bedrag (−1 = onmogelijk) | B32: € | C32: =IF(C30>C31,-1,IF(C29<C30-0.000000001,-1,IF(C29>C31,MAX(C30,C31-1),C29))) -> 216024.73 | D32: =IF(D30>D31,-1,IF(D29<D30-0.000000001,-1,IF(D29>D31,MAX(D30,D31-1),D29))) -> 151857.1 | E32: =IF(E30>E31,-1,IF(E29<E30-0.000000001,-1,IF(E29>E31,MAX(E30,E31-1),E29))) -> -1 | F32: =IF(F30>F31,-1,IF(F29<F30-0.000000001,-1,IF(F29>F31,MAX(F30,F31-1),F29))) -> 171364.53 | G32: =IF(G30>G31,-1,IF(G29<G30-0.000000001,-1,IF(G29>G31,MAX(G30,G31-1),G29))) -> 0 | H32: =IF(H30>H31,-1,IF(H29<H30-0.000000001,-1,IF(H29>H31,MAX(H30,H31-1),H29))) -> 0 | I32: =IF(I30>I31,-1,IF(I29<I30-0.000000001,-1,IF(I29>I31,MAX(I30,I31-1),I29))) -> 0 | J32: =IF(J30>J31,-1,IF(J29<J30-0.000000001,-1,IF(J29>J31,MAX(J30,J31-1),J29))) -> 216024.73 | ... M32: =IF(M30>M31,-1,IF(M29<M30-0.000000001,-1,IF(M29>M31,MAX(M30,M31-1),M29))) -> 216024.73
A33: Kolom 6: woonquote | B33: % | C33: =INDEX(T1_Tabel,Berekening!C80,6)+(Berekening!C79-INDEX(T1_Inkomen,Berekening!C80))/(INDEX(T1_Inkomen,Berekening!C80+1)-INDEX(T1_Inkomen,Berekening!C80))*(INDEX(T1_Tabel,Berekening!C80+1,6)-INDEX(T1_Tabel,Berekening!C80,6)) -> 0.274 | D33: =INDEX(T1_Tabel,Berekening!D80,6)+(Berekening!D79-INDEX(T1_Inkomen,Berekening!D80))/(INDEX(T1_Inkomen,Berekening!D80+1)-INDEX(T1_Inkomen,Berekening!D80))*(INDEX(T1_Tabel,Berekening!D80+1,6)-INDEX(T1_Tabel,Berekening!D80,6)) -> 0.274 | E33: =INDEX(T1_Tabel,Berekening!E80,6)+(Berekening!E79-INDEX(T1_Inkomen,Berekening!E80))/(INDEX(T1_Inkomen,Berekening!E80+1)-INDEX(T1_Inkomen,Berekening!E80))*(INDEX(T1_Tabel,Berekening!E80+1,6)-INDEX(T1_Tabel,Berekening!E80,6)) -> 0.274 | F33: =INDEX(T1_Tabel,Berekening!F80,6)+(Berekening!F79-INDEX(T1_Inkomen,Berekening!F80))/(INDEX(T1_Inkomen,Berekening!F80+1)-INDEX(T1_Inkomen,Berekening!F80))*(INDEX(T1_Tabel,Berekening!F80+1,6)-INDEX(T1_Tabel,Berekening!F80,6)) -> 0.274 | G33: =INDEX(T1_Tabel,Berekening!G80,6)+(Berekening!G79-INDEX(T1_Inkomen,Berekening!G80))/(INDEX(T1_Inkomen,Berekening!G80+1)-INDEX(T1_Inkomen,Berekening!G80))*(INDEX(T1_Tabel,Berekening!G80+1,6)-INDEX(T1_Tabel,Berekening!G80,6)) -> 0.226 | H33: =INDEX(T1_Tabel,Berekening!H80,6)+(Berekening!H79-INDEX(T1_Inkomen,Berekening!H80))/(INDEX(T1_Inkomen,Berekening!H80+1)-INDEX(T1_Inkomen,Berekening!H80))*(INDEX(T1_Tabel,Berekening!H80+1,6)-INDEX(T1_Tabel,Berekening!H80,6)) -> 0.274 | I33: =INDEX(T1_Tabel,Berekening!I80,6)+(Berekening!I79-INDEX(T1_Inkomen,Berekening!I80))/(INDEX(T1_Inkomen,Berekening!I80+1)-INDEX(T1_Inkomen,Berekening!I80))*(INDEX(T1_Tabel,Berekening!I80+1,6)-INDEX(T1_Tabel,Berekening!I80,6)) -> 0.274 | J33: =INDEX(T1_Tabel,Berekening!J80,6)+(Berekening!J79-INDEX(T1_Inkomen,Berekening!J80))/(INDEX(T1_Inkomen,Berekening!J80+1)-INDEX(T1_Inkomen,Berekening!J80))*(INDEX(T1_Tabel,Berekening!J80+1,6)-INDEX(T1_Tabel,Berekening!J80,6)) -> 0.274 | ... M33: =INDEX(T1_Tabel,Berekening!M80,6)+(Berekening!M79-INDEX(T1_Inkomen,Berekening!M80))/(INDEX(T1_Inkomen,Berekening!M80+1)-INDEX(T1_Inkomen,Berekening!M80))*(INDEX(T1_Tabel,Berekening!M80+1,6)-INDEX(T1_Tabel,Berekening!M80,6)) -> 0.274
A34: Kolom 6: bedrag als de woonquote van deze kolom geldt | B34: € | C34: =MAX(0,(C33*C6/12-Berekening!C18-Berekening!C44)*Berekening!C11-Berekening!C75+C7) -> 328352.17 | D34: =MAX(0,(D33*D6/12-Berekening!D18-Berekening!D44)*Berekening!D11-Berekening!D75+D7) -> 357403.72 | E34: =MAX(0,(E33*E6/12-Berekening!E18-Berekening!E44)*Berekening!E11-Berekening!E75+E7) -> 205704.63 | F34: =MAX(0,(F33*F6/12-Berekening!F18-Berekening!F44)*Berekening!F11-Berekening!F75+F7) -> 317212.25 | G34: =MAX(0,(G33*G6/12-Berekening!G18-Berekening!G44)*Berekening!G11-Berekening!G75+G7) -> 240131.17 | H34: =MAX(0,(H33*H6/12-Berekening!H18-Berekening!H44)*Berekening!H11-Berekening!H75+H7) -> 641036.1 | I34: =MAX(0,(I33*I6/12-Berekening!I18-Berekening!I44)*Berekening!I11-Berekening!I75+I7) -> 881124.08 | J34: =MAX(0,(J33*J6/12-Berekening!J18-Berekening!J44)*Berekening!J11-Berekening!J75+J7) -> 365638.24 | ... M34: =MAX(0,(M33*M6/12-Berekening!M18-Berekening!M44)*Berekening!M11-Berekening!M75+M7) -> 328352.17
A35: Kolom 6: laagste bedrag waarbij de gewogen rente in deze kolom valt | B35: € | C35: =MAX(0,IF((INDEX(T1_Rente,6)+0.000005)>Berekening!C10,(Berekening!C45-(INDEX(T1_Rente,6)+0.000005)*Berekening!C46)/(360*((INDEX(T1_Rente,6)+0.000005)-Berekening!C10)),IF((INDEX(T1_Rente,6)+0.000005)=Berekening!C10,IF(Berekening!C45-(INDEX(T1_Rente,6)+0.000005)*Berekening!C46<=0,-1000000000000,1000000000000),-1000000000000)),IF((INDEX(T1_Rente,6)-0.005+0.000005)<Berekening!C10,(Berekening!C45-(INDEX(T1_Rente,6)-0.005+0.000005)*Berekening!C46)/(360*((INDEX(T1_Rente,6)-0.005+0.000005)-Berekening!C10)),IF((INDEX(T1_Rente,6)-0.005+0.000005)=Berekening!C10,IF(Berekening!C45-(INDEX(T1_Rente,6)-0.005+0.000005)*Berekening!C46>0,-1000000000000,1000000000000),-1000000000000))) -> 216025.73 | D35: =MAX(0,IF((INDEX(T1_Rente,6)+0.000005)>Berekening!D10,(Berekening!D45-(INDEX(T1_Rente,6)+0.000005)*Berekening!D46)/(360*((INDEX(T1_Rente,6)+0.000005)-Berekening!D10)),IF((INDEX(T1_Rente,6)+0.000005)=Berekening!D10,IF(Berekening!D45-(INDEX(T1_Rente,6)+0.000005)*Berekening!D46<=0,-1000000000000,1000000000000),-1000000000000)),IF((INDEX(T1_Rente,6)-0.005+0.000005)<Berekening!D10,(Berekening!D45-(INDEX(T1_Rente,6)-0.005+0.000005)*Berekening!D46)/(360*((INDEX(T1_Rente,6)-0.005+0.000005)-Berekening!D10)),IF((INDEX(T1_Rente,6)-0.005+0.000005)=Berekening!D10,IF(Berekening!D45-(INDEX(T1_Rente,6)-0.005+0.000005)*Berekening!D46>0,-1000000000000,1000000000000),-1000000000000))) -> 151858.1 | E35: =MAX(0,IF((INDEX(T1_Rente,6)+0.000005)>Berekening!E10,(Berekening!E45-(INDEX(T1_Rente,6)+0.000005)*Berekening!E46)/(360*((INDEX(T1_Rente,6)+0.000005)-Berekening!E10)),IF((INDEX(T1_Rente,6)+0.000005)=Berekening!E10,IF(Berekening!E45-(INDEX(T1_Rente,6)+0.000005)*Berekening!E46<=0,-1000000000000,1000000000000),-1000000000000)),IF((INDEX(T1_Rente,6)-0.005+0.000005)<Berekening!E10,(Berekening!E45-(INDEX(T1_Rente,6)-0.005+0.000005)*Berekening!E46)/(360*((INDEX(T1_Rente,6)-0.005+0.000005)-Berekening!E10)),IF((INDEX(T1_Rente,6)-0.005+0.000005)=Berekening!E10,IF(Berekening!E45-(INDEX(T1_Rente,6)-0.005+0.000005)*Berekening!E46>0,-1000000000000,1000000000000),-1000000000000))) -> 0 | F35: =MAX(0,IF((INDEX(T1_Rente,6)+0.000005)>Berekening!F10,(Berekening!F45-(INDEX(T1_Rente,6)+0.000005)*Berekening!F46)/(360*((INDEX(T1_Rente,6)+0.000005)-Berekening!F10)),IF((INDEX(T1_Rente,6)+0.000005)=Berekening!F10,IF(Berekening!F45-(INDEX(T1_Rente,6)+0.000005)*Berekening!F46<=0,-1000000000000,1000000000000),-1000000000000)),IF((INDEX(T1_Rente,6)-0.005+0.000005)<Berekening!F10,(Berekening!F45-(INDEX(T1_Rente,6)-0.005+0.000005)*Berekening!F46)/(360*((INDEX(T1_Rente,6)-0.005+0.000005)-Berekening!F10)),IF((INDEX(T1_Rente,6)-0.005+0.000005)=Berekening!F10,IF(Berekening!F45-(INDEX(T1_Rente,6)-0.005+0.000005)*Berekening!F46>0,-1000000000000,1000000000000),-1000000000000))) -> 171365.53 | G35: =MAX(0,IF((INDEX(T1_Rente,6)+0.000005)>Berekening!G10,(Berekening!G45-(INDEX(T1_Rente,6)+0.000005)*Berekening!G46)/(360*((INDEX(T1_Rente,6)+0.000005)-Berekening!G10)),IF((INDEX(T1_Rente,6)+0.000005)=Berekening!G10,IF(Berekening!G45-(INDEX(T1_Rente,6)+0.000005)*Berekening!G46<=0,-1000000000000,1000000000000),-1000000000000)),IF((INDEX(T1_Rente,6)-0.005+0.000005)<Berekening!G10,(Berekening!G45-(INDEX(T1_Rente,6)-0.005+0.000005)*Berekening!G46)/(360*((INDEX(T1_Rente,6)-0.005+0.000005)-Berekening!G10)),IF((INDEX(T1_Rente,6)-0.005+0.000005)=Berekening!G10,IF(Berekening!G45-(INDEX(T1_Rente,6)-0.005+0.000005)*Berekening!G46>0,-1000000000000,1000000000000),-1000000000000))) -> 0 | H35: =MAX(0,IF((INDEX(T1_Rente,6)+0.000005)>Berekening!H10,(Berekening!H45-(INDEX(T1_Rente,6)+0.000005)*Berekening!H46)/(360*((INDEX(T1_Rente,6)+0.000005)-Berekening!H10)),IF((INDEX(T1_Rente,6)+0.000005)=Berekening!H10,IF(Berekening!H45-(INDEX(T1_Rente,6)+0.000005)*Berekening!H46<=0,-1000000000000,1000000000000),-1000000000000)),IF((INDEX(T1_Rente,6)-0.005+0.000005)<Berekening!H10,(Berekening!H45-(INDEX(T1_Rente,6)-0.005+0.000005)*Berekening!H46)/(360*((INDEX(T1_Rente,6)-0.005+0.000005)-Berekening!H10)),IF((INDEX(T1_Rente,6)-0.005+0.000005)=Berekening!H10,IF(Berekening!H45-(INDEX(T1_Rente,6)-0.005+0.000005)*Berekening!H46>0,-1000000000000,1000000000000),-1000000000000))) -> 0 | I35: =MAX(0,IF((INDEX(T1_Rente,6)+0.000005)>Berekening!I10,(Berekening!I45-(INDEX(T1_Rente,6)+0.000005)*Berekening!I46)/(360*((INDEX(T1_Rente,6)+0.000005)-Berekening!I10)),IF((INDEX(T1_Rente,6)+0.000005)=Berekening!I10,IF(Berekening!I45-(INDEX(T1_Rente,6)+0.000005)*Berekening!I46<=0,-1000000000000,1000000000000),-1000000000000)),IF((INDEX(T1_Rente,6)-0.005+0.000005)<Berekening!I10,(Berekening!I45-(INDEX(T1_Rente,6)-0.005+0.000005)*Berekening!I46)/(360*((INDEX(T1_Rente,6)-0.005+0.000005)-Berekening!I10)),IF((INDEX(T1_Rente,6)-0.005+0.000005)=Berekening!I10,IF(Berekening!I45-(INDEX(T1_Rente,6)-0.005+0.000005)*Berekening!I46>0,-1000000000000,1000000000000),-1000000000000))) -> 0 | J35: =MAX(0,IF((INDEX(T1_Rente,6)+0.000005)>Berekening!J10,(Berekening!J45-(INDEX(T1_Rente,6)+0.000005)*Berekening!J46)/(360*((INDEX(T1_Rente,6)+0.000005)-Berekening!J10)),IF((INDEX(T1_Rente,6)+0.000005)=Berekening!J10,IF(Berekening!J45-(INDEX(T1_Rente,6)+0.000005)*Berekening!J46<=0,-1000000000000,1000000000000),-1000000000000)),IF((INDEX(T1_Rente,6)-0.005+0.000005)<Berekening!J10,(Berekening!J45-(INDEX(T1_Rente,6)-0.005+0.000005)*Berekening!J46)/(360*((INDEX(T1_Rente,6)-0.005+0.000005)-Berekening!J10)),IF((INDEX(T1_Rente,6)-0.005+0.000005)=Berekening!J10,IF(Berekening!J45-(INDEX(T1_Rente,6)-0.005+0.000005)*Berekening!J46>0,-1000000000000,1000000000000),-1000000000000))) -> 216025.73 | ... M35: =MAX(0,IF((INDEX(T1_Rente,6)+0.000005)>Berekening!M10,(Berekening!M45-(INDEX(T1_Rente,6)+0.000005)*Berekening!M46)/(360*((INDEX(T1_Rente,6)+0.000005)-Berekening!M10)),IF((INDEX(T1_Rente,6)+0.000005)=Berekening!M10,IF(Berekening!M45-(INDEX(T1_Rente,6)+0.000005)*Berekening!M46<=0,-1000000000000,1000000000000),-1000000000000)),IF((INDEX(T1_Rente,6)-0.005+0.000005)<Berekening!M10,(Berekening!M45-(INDEX(T1_Rente,6)-0.005+0.000005)*Berekening!M46)/(360*((INDEX(T1_Rente,6)-0.005+0.000005)-Berekening!M10)),IF((INDEX(T1_Rente,6)-0.005+0.000005)=Berekening!M10,IF(Berekening!M45-(INDEX(T1_Rente,6)-0.005+0.000005)*Berekening!M46>0,-1000000000000,1000000000000),-1000000000000))) -> 216025.73
A36: Kolom 6: hoogste bedrag waarbij de gewogen rente in deze kolom valt | B36: € | C36: =MIN(1000000000000,IF((INDEX(T1_Rente,6)+0.000005)<Berekening!C10,(Berekening!C45-(INDEX(T1_Rente,6)+0.000005)*Berekening!C46)/(360*((INDEX(T1_Rente,6)+0.000005)-Berekening!C10)),1000000000000),IF((INDEX(T1_Rente,6)-0.005+0.000005)>Berekening!C10,(Berekening!C45-(INDEX(T1_Rente,6)-0.005+0.000005)*Berekening!C46)/(360*((INDEX(T1_Rente,6)-0.005+0.000005)-Berekening!C10)),1000000000000)) -> 788087.91 | D36: =MIN(1000000000000,IF((INDEX(T1_Rente,6)+0.000005)<Berekening!D10,(Berekening!D45-(INDEX(T1_Rente,6)+0.000005)*Berekening!D46)/(360*((INDEX(T1_Rente,6)+0.000005)-Berekening!D10)),1000000000000),IF((INDEX(T1_Rente,6)-0.005+0.000005)>Berekening!D10,(Berekening!D45-(INDEX(T1_Rente,6)-0.005+0.000005)*Berekening!D46)/(360*((INDEX(T1_Rente,6)-0.005+0.000005)-Berekening!D10)),1000000000000)) -> 714300.46 | E36: =MIN(1000000000000,IF((INDEX(T1_Rente,6)+0.000005)<Berekening!E10,(Berekening!E45-(INDEX(T1_Rente,6)+0.000005)*Berekening!E46)/(360*((INDEX(T1_Rente,6)+0.000005)-Berekening!E10)),1000000000000),IF((INDEX(T1_Rente,6)-0.005+0.000005)>Berekening!E10,(Berekening!E45-(INDEX(T1_Rente,6)-0.005+0.000005)*Berekening!E46)/(360*((INDEX(T1_Rente,6)-0.005+0.000005)-Berekening!E10)),1000000000000)) -> -830401.14 | F36: =MIN(1000000000000,IF((INDEX(T1_Rente,6)+0.000005)<Berekening!F10,(Berekening!F45-(INDEX(T1_Rente,6)+0.000005)*Berekening!F46)/(360*((INDEX(T1_Rente,6)+0.000005)-Berekening!F10)),1000000000000),IF((INDEX(T1_Rente,6)-0.005+0.000005)>Berekening!F10,(Berekening!F45-(INDEX(T1_Rente,6)-0.005+0.000005)*Berekening!F46)/(360*((INDEX(T1_Rente,6)-0.005+0.000005)-Berekening!F10)),1000000000000)) -> 543658.44 | G36: =MIN(1000000000000,IF((INDEX(T1_Rente,6)+0.000005)<Berekening!G10,(Berekening!G45-(INDEX(T1_Rente,6)+0.000005)*Berekening!G46)/(360*((INDEX(T1_Rente,6)+0.000005)-Berekening!G10)),1000000000000),IF((INDEX(T1_Rente,6)-0.005+0.000005)>Berekening!G10,(Berekening!G45-(INDEX(T1_Rente,6)-0.005+0.000005)*Berekening!G46)/(360*((INDEX(T1_Rente,6)-0.005+0.000005)-Berekening!G10)),1000000000000)) -> 0 | H36: =MIN(1000000000000,IF((INDEX(T1_Rente,6)+0.000005)<Berekening!H10,(Berekening!H45-(INDEX(T1_Rente,6)+0.000005)*Berekening!H46)/(360*((INDEX(T1_Rente,6)+0.000005)-Berekening!H10)),1000000000000),IF((INDEX(T1_Rente,6)-0.005+0.000005)>Berekening!H10,(Berekening!H45-(INDEX(T1_Rente,6)-0.005+0.000005)*Berekening!H46)/(360*((INDEX(T1_Rente,6)-0.005+0.000005)-Berekening!H10)),1000000000000)) -> 0 | I36: =MIN(1000000000000,IF((INDEX(T1_Rente,6)+0.000005)<Berekening!I10,(Berekening!I45-(INDEX(T1_Rente,6)+0.000005)*Berekening!I46)/(360*((INDEX(T1_Rente,6)+0.000005)-Berekening!I10)),1000000000000),IF((INDEX(T1_Rente,6)-0.005+0.000005)>Berekening!I10,(Berekening!I45-(INDEX(T1_Rente,6)-0.005+0.000005)*Berekening!I46)/(360*((INDEX(T1_Rente,6)-0.005+0.000005)-Berekening!I10)),1000000000000)) -> 0 | J36: =MIN(1000000000000,IF((INDEX(T1_Rente,6)+0.000005)<Berekening!J10,(Berekening!J45-(INDEX(T1_Rente,6)+0.000005)*Berekening!J46)/(360*((INDEX(T1_Rente,6)+0.000005)-Berekening!J10)),1000000000000),IF((INDEX(T1_Rente,6)-0.005+0.000005)>Berekening!J10,(Berekening!J45-(INDEX(T1_Rente,6)-0.005+0.000005)*Berekening!J46)/(360*((INDEX(T1_Rente,6)-0.005+0.000005)-Berekening!J10)),1000000000000)) -> 788087.91 | ... M36: =MIN(1000000000000,IF((INDEX(T1_Rente,6)+0.000005)<Berekening!M10,(Berekening!M45-(INDEX(T1_Rente,6)+0.000005)*Berekening!M46)/(360*((INDEX(T1_Rente,6)+0.000005)-Berekening!M10)),1000000000000),IF((INDEX(T1_Rente,6)-0.005+0.000005)>Berekening!M10,(Berekening!M45-(INDEX(T1_Rente,6)-0.005+0.000005)*Berekening!M46)/(360*((INDEX(T1_Rente,6)-0.005+0.000005)-Berekening!M10)),1000000000000)) -> 788087.91
A37: Kolom 6: haalbaar bedrag (−1 = onmogelijk) | B37: € | C37: =IF(C35>C36,-1,IF(C34<C35-0.000000001,-1,IF(C34>C36,MAX(C35,C36-1),C34))) -> 328352.17 | D37: =IF(D35>D36,-1,IF(D34<D35-0.000000001,-1,IF(D34>D36,MAX(D35,D36-1),D34))) -> 357403.72 | E37: =IF(E35>E36,-1,IF(E34<E35-0.000000001,-1,IF(E34>E36,MAX(E35,E36-1),E34))) -> -1 | F37: =IF(F35>F36,-1,IF(F34<F35-0.000000001,-1,IF(F34>F36,MAX(F35,F36-1),F34))) -> 317212.25 | G37: =IF(G35>G36,-1,IF(G34<G35-0.000000001,-1,IF(G34>G36,MAX(G35,G36-1),G34))) -> 0 | H37: =IF(H35>H36,-1,IF(H34<H35-0.000000001,-1,IF(H34>H36,MAX(H35,H36-1),H34))) -> 0 | I37: =IF(I35>I36,-1,IF(I34<I35-0.000000001,-1,IF(I34>I36,MAX(I35,I36-1),I34))) -> 0 | J37: =IF(J35>J36,-1,IF(J34<J35-0.000000001,-1,IF(J34>J36,MAX(J35,J36-1),J34))) -> 365638.24 | ... M37: =IF(M35>M36,-1,IF(M34<M35-0.000000001,-1,IF(M34>M36,MAX(M35,M36-1),M34))) -> 328352.17
A38: Kolom 7: woonquote | B38: % | C38: =INDEX(T1_Tabel,Berekening!C80,7)+(Berekening!C79-INDEX(T1_Inkomen,Berekening!C80))/(INDEX(T1_Inkomen,Berekening!C80+1)-INDEX(T1_Inkomen,Berekening!C80))*(INDEX(T1_Tabel,Berekening!C80+1,7)-INDEX(T1_Tabel,Berekening!C80,7)) -> 0.283 | D38: =INDEX(T1_Tabel,Berekening!D80,7)+(Berekening!D79-INDEX(T1_Inkomen,Berekening!D80))/(INDEX(T1_Inkomen,Berekening!D80+1)-INDEX(T1_Inkomen,Berekening!D80))*(INDEX(T1_Tabel,Berekening!D80+1,7)-INDEX(T1_Tabel,Berekening!D80,7)) -> 0.283 | E38: =INDEX(T1_Tabel,Berekening!E80,7)+(Berekening!E79-INDEX(T1_Inkomen,Berekening!E80))/(INDEX(T1_Inkomen,Berekening!E80+1)-INDEX(T1_Inkomen,Berekening!E80))*(INDEX(T1_Tabel,Berekening!E80+1,7)-INDEX(T1_Tabel,Berekening!E80,7)) -> 0.283 | F38: =INDEX(T1_Tabel,Berekening!F80,7)+(Berekening!F79-INDEX(T1_Inkomen,Berekening!F80))/(INDEX(T1_Inkomen,Berekening!F80+1)-INDEX(T1_Inkomen,Berekening!F80))*(INDEX(T1_Tabel,Berekening!F80+1,7)-INDEX(T1_Tabel,Berekening!F80,7)) -> 0.283 | G38: =INDEX(T1_Tabel,Berekening!G80,7)+(Berekening!G79-INDEX(T1_Inkomen,Berekening!G80))/(INDEX(T1_Inkomen,Berekening!G80+1)-INDEX(T1_Inkomen,Berekening!G80))*(INDEX(T1_Tabel,Berekening!G80+1,7)-INDEX(T1_Tabel,Berekening!G80,7)) -> 0.236 | H38: =INDEX(T1_Tabel,Berekening!H80,7)+(Berekening!H79-INDEX(T1_Inkomen,Berekening!H80))/(INDEX(T1_Inkomen,Berekening!H80+1)-INDEX(T1_Inkomen,Berekening!H80))*(INDEX(T1_Tabel,Berekening!H80+1,7)-INDEX(T1_Tabel,Berekening!H80,7)) -> 0.283 | I38: =INDEX(T1_Tabel,Berekening!I80,7)+(Berekening!I79-INDEX(T1_Inkomen,Berekening!I80))/(INDEX(T1_Inkomen,Berekening!I80+1)-INDEX(T1_Inkomen,Berekening!I80))*(INDEX(T1_Tabel,Berekening!I80+1,7)-INDEX(T1_Tabel,Berekening!I80,7)) -> 0.283 | J38: =INDEX(T1_Tabel,Berekening!J80,7)+(Berekening!J79-INDEX(T1_Inkomen,Berekening!J80))/(INDEX(T1_Inkomen,Berekening!J80+1)-INDEX(T1_Inkomen,Berekening!J80))*(INDEX(T1_Tabel,Berekening!J80+1,7)-INDEX(T1_Tabel,Berekening!J80,7)) -> 0.283 | ... M38: =INDEX(T1_Tabel,Berekening!M80,7)+(Berekening!M79-INDEX(T1_Inkomen,Berekening!M80))/(INDEX(T1_Inkomen,Berekening!M80+1)-INDEX(T1_Inkomen,Berekening!M80))*(INDEX(T1_Tabel,Berekening!M80+1,7)-INDEX(T1_Tabel,Berekening!M80,7)) -> 0.283
A39: Kolom 7: bedrag als de woonquote van deze kolom geldt | B39: € | C39: =MAX(0,(C38*C6/12-Berekening!C18-Berekening!C44)*Berekening!C11-Berekening!C75+C7) -> 360927.07 | D39: =MAX(0,(D38*D6/12-Berekening!D18-Berekening!D44)*Berekening!D11-Berekening!D75+D7) -> 389978.62 | E39: =MAX(0,(E38*E6/12-Berekening!E18-Berekening!E44)*Berekening!E11-Berekening!E75+E7) -> 238279.52 | F39: =MAX(0,(F38*F6/12-Berekening!F18-Berekening!F44)*Berekening!F11-Berekening!F75+F7) -> 348647.27 | G39: =MAX(0,(G38*G6/12-Berekening!G18-Berekening!G44)*Berekening!G11-Berekening!G75+G7) -> 249782.99 | H39: =MAX(0,(H38*H6/12-Berekening!H18-Berekening!H44)*Berekening!H11-Berekening!H75+H7) -> 662752.7 | I39: =MAX(0,(I38*I6/12-Berekening!I18-Berekening!I44)*Berekening!I11-Berekening!I75+I7) -> 913698.98 | J39: =MAX(0,(J38*J6/12-Berekening!J18-Berekening!J44)*Berekening!J11-Berekening!J75+J7) -> 398213.14 | ... M39: =MAX(0,(M38*M6/12-Berekening!M18-Berekening!M44)*Berekening!M11-Berekening!M75+M7) -> 360927.07
A40: Kolom 7: laagste bedrag waarbij de gewogen rente in deze kolom valt | B40: € | C40: =MAX(0,IF((INDEX(T1_Rente,7)+0.000005)>Berekening!C10,(Berekening!C45-(INDEX(T1_Rente,7)+0.000005)*Berekening!C46)/(360*((INDEX(T1_Rente,7)+0.000005)-Berekening!C10)),IF((INDEX(T1_Rente,7)+0.000005)=Berekening!C10,IF(Berekening!C45-(INDEX(T1_Rente,7)+0.000005)*Berekening!C46<=0,-1000000000000,1000000000000),-1000000000000)),IF((INDEX(T1_Rente,7)-0.005+0.000005)<Berekening!C10,(Berekening!C45-(INDEX(T1_Rente,7)-0.005+0.000005)*Berekening!C46)/(360*((INDEX(T1_Rente,7)-0.005+0.000005)-Berekening!C10)),IF((INDEX(T1_Rente,7)-0.005+0.000005)=Berekening!C10,IF(Berekening!C45-(INDEX(T1_Rente,7)-0.005+0.000005)*Berekening!C46>0,-1000000000000,1000000000000),-1000000000000))) -> 788087.91 | D40: =MAX(0,IF((INDEX(T1_Rente,7)+0.000005)>Berekening!D10,(Berekening!D45-(INDEX(T1_Rente,7)+0.000005)*Berekening!D46)/(360*((INDEX(T1_Rente,7)+0.000005)-Berekening!D10)),IF((INDEX(T1_Rente,7)+0.000005)=Berekening!D10,IF(Berekening!D45-(INDEX(T1_Rente,7)+0.000005)*Berekening!D46<=0,-1000000000000,1000000000000),-1000000000000)),IF((INDEX(T1_Rente,7)-0.005+0.000005)<Berekening!D10,(Berekening!D45-(INDEX(T1_Rente,7)-0.005+0.000005)*Berekening!D46)/(360*((INDEX(T1_Rente,7)-0.005+0.000005)-Berekening!D10)),IF((INDEX(T1_Rente,7)-0.005+0.000005)=Berekening!D10,IF(Berekening!D45-(INDEX(T1_Rente,7)-0.005+0.000005)*Berekening!D46>0,-1000000000000,1000000000000),-1000000000000))) -> 714300.46 | E40: =MAX(0,IF((INDEX(T1_Rente,7)+0.000005)>Berekening!E10,(Berekening!E45-(INDEX(T1_Rente,7)+0.000005)*Berekening!E46)/(360*((INDEX(T1_Rente,7)+0.000005)-Berekening!E10)),IF((INDEX(T1_Rente,7)+0.000005)=Berekening!E10,IF(Berekening!E45-(INDEX(T1_Rente,7)+0.000005)*Berekening!E46<=0,-1000000000000,1000000000000),-1000000000000)),IF((INDEX(T1_Rente,7)-0.005+0.000005)<Berekening!E10,(Berekening!E45-(INDEX(T1_Rente,7)-0.005+0.000005)*Berekening!E46)/(360*((INDEX(T1_Rente,7)-0.005+0.000005)-Berekening!E10)),IF((INDEX(T1_Rente,7)-0.005+0.000005)=Berekening!E10,IF(Berekening!E45-(INDEX(T1_Rente,7)-0.005+0.000005)*Berekening!E46>0,-1000000000000,1000000000000),-1000000000000))) -> 0 | F40: =MAX(0,IF((INDEX(T1_Rente,7)+0.000005)>Berekening!F10,(Berekening!F45-(INDEX(T1_Rente,7)+0.000005)*Berekening!F46)/(360*((INDEX(T1_Rente,7)+0.000005)-Berekening!F10)),IF((INDEX(T1_Rente,7)+0.000005)=Berekening!F10,IF(Berekening!F45-(INDEX(T1_Rente,7)+0.000005)*Berekening!F46<=0,-1000000000000,1000000000000),-1000000000000)),IF((INDEX(T1_Rente,7)-0.005+0.000005)<Berekening!F10,(Berekening!F45-(INDEX(T1_Rente,7)-0.005+0.000005)*Berekening!F46)/(360*((INDEX(T1_Rente,7)-0.005+0.000005)-Berekening!F10)),IF((INDEX(T1_Rente,7)-0.005+0.000005)=Berekening!F10,IF(Berekening!F45-(INDEX(T1_Rente,7)-0.005+0.000005)*Berekening!F46>0,-1000000000000,1000000000000),-1000000000000))) -> 543658.44 | G40: =MAX(0,IF((INDEX(T1_Rente,7)+0.000005)>Berekening!G10,(Berekening!G45-(INDEX(T1_Rente,7)+0.000005)*Berekening!G46)/(360*((INDEX(T1_Rente,7)+0.000005)-Berekening!G10)),IF((INDEX(T1_Rente,7)+0.000005)=Berekening!G10,IF(Berekening!G45-(INDEX(T1_Rente,7)+0.000005)*Berekening!G46<=0,-1000000000000,1000000000000),-1000000000000)),IF((INDEX(T1_Rente,7)-0.005+0.000005)<Berekening!G10,(Berekening!G45-(INDEX(T1_Rente,7)-0.005+0.000005)*Berekening!G46)/(360*((INDEX(T1_Rente,7)-0.005+0.000005)-Berekening!G10)),IF((INDEX(T1_Rente,7)-0.005+0.000005)=Berekening!G10,IF(Berekening!G45-(INDEX(T1_Rente,7)-0.005+0.000005)*Berekening!G46>0,-1000000000000,1000000000000),-1000000000000))) -> 0 | H40: =MAX(0,IF((INDEX(T1_Rente,7)+0.000005)>Berekening!H10,(Berekening!H45-(INDEX(T1_Rente,7)+0.000005)*Berekening!H46)/(360*((INDEX(T1_Rente,7)+0.000005)-Berekening!H10)),IF((INDEX(T1_Rente,7)+0.000005)=Berekening!H10,IF(Berekening!H45-(INDEX(T1_Rente,7)+0.000005)*Berekening!H46<=0,-1000000000000,1000000000000),-1000000000000)),IF((INDEX(T1_Rente,7)-0.005+0.000005)<Berekening!H10,(Berekening!H45-(INDEX(T1_Rente,7)-0.005+0.000005)*Berekening!H46)/(360*((INDEX(T1_Rente,7)-0.005+0.000005)-Berekening!H10)),IF((INDEX(T1_Rente,7)-0.005+0.000005)=Berekening!H10,IF(Berekening!H45-(INDEX(T1_Rente,7)-0.005+0.000005)*Berekening!H46>0,-1000000000000,1000000000000),-1000000000000))) -> 0 | I40: =MAX(0,IF((INDEX(T1_Rente,7)+0.000005)>Berekening!I10,(Berekening!I45-(INDEX(T1_Rente,7)+0.000005)*Berekening!I46)/(360*((INDEX(T1_Rente,7)+0.000005)-Berekening!I10)),IF((INDEX(T1_Rente,7)+0.000005)=Berekening!I10,IF(Berekening!I45-(INDEX(T1_Rente,7)+0.000005)*Berekening!I46<=0,-1000000000000,1000000000000),-1000000000000)),IF((INDEX(T1_Rente,7)-0.005+0.000005)<Berekening!I10,(Berekening!I45-(INDEX(T1_Rente,7)-0.005+0.000005)*Berekening!I46)/(360*((INDEX(T1_Rente,7)-0.005+0.000005)-Berekening!I10)),IF((INDEX(T1_Rente,7)-0.005+0.000005)=Berekening!I10,IF(Berekening!I45-(INDEX(T1_Rente,7)-0.005+0.000005)*Berekening!I46>0,-1000000000000,1000000000000),-1000000000000))) -> 0 | J40: =MAX(0,IF((INDEX(T1_Rente,7)+0.000005)>Berekening!J10,(Berekening!J45-(INDEX(T1_Rente,7)+0.000005)*Berekening!J46)/(360*((INDEX(T1_Rente,7)+0.000005)-Berekening!J10)),IF((INDEX(T1_Rente,7)+0.000005)=Berekening!J10,IF(Berekening!J45-(INDEX(T1_Rente,7)+0.000005)*Berekening!J46<=0,-1000000000000,1000000000000),-1000000000000)),IF((INDEX(T1_Rente,7)-0.005+0.000005)<Berekening!J10,(Berekening!J45-(INDEX(T1_Rente,7)-0.005+0.000005)*Berekening!J46)/(360*((INDEX(T1_Rente,7)-0.005+0.000005)-Berekening!J10)),IF((INDEX(T1_Rente,7)-0.005+0.000005)=Berekening!J10,IF(Berekening!J45-(INDEX(T1_Rente,7)-0.005+0.000005)*Berekening!J46>0,-1000000000000,1000000000000),-1000000000000))) -> 788087.91 | ... M40: =MAX(0,IF((INDEX(T1_Rente,7)+0.000005)>Berekening!M10,(Berekening!M45-(INDEX(T1_Rente,7)+0.000005)*Berekening!M46)/(360*((INDEX(T1_Rente,7)+0.000005)-Berekening!M10)),IF((INDEX(T1_Rente,7)+0.000005)=Berekening!M10,IF(Berekening!M45-(INDEX(T1_Rente,7)+0.000005)*Berekening!M46<=0,-1000000000000,1000000000000),-1000000000000)),IF((INDEX(T1_Rente,7)-0.005+0.000005)<Berekening!M10,(Berekening!M45-(INDEX(T1_Rente,7)-0.005+0.000005)*Berekening!M46)/(360*((INDEX(T1_Rente,7)-0.005+0.000005)-Berekening!M10)),IF((INDEX(T1_Rente,7)-0.005+0.000005)=Berekening!M10,IF(Berekening!M45-(INDEX(T1_Rente,7)-0.005+0.000005)*Berekening!M46>0,-1000000000000,1000000000000),-1000000000000))) -> 788087.91
A41: Kolom 7: hoogste bedrag waarbij de gewogen rente in deze kolom valt | B41: € | C41: =MIN(1000000000000,IF((INDEX(T1_Rente,7)+0.000005)<Berekening!C10,(Berekening!C45-(INDEX(T1_Rente,7)+0.000005)*Berekening!C46)/(360*((INDEX(T1_Rente,7)+0.000005)-Berekening!C10)),1000000000000),IF((INDEX(T1_Rente,7)-0.005+0.000005)>Berekening!C10,(Berekening!C45-(INDEX(T1_Rente,7)-0.005+0.000005)*Berekening!C46)/(360*((INDEX(T1_Rente,7)-0.005+0.000005)-Berekening!C10)),1000000000000)) -> 4378947.9 | D41: =MIN(1000000000000,IF((INDEX(T1_Rente,7)+0.000005)<Berekening!D10,(Berekening!D45-(INDEX(T1_Rente,7)+0.000005)*Berekening!D46)/(360*((INDEX(T1_Rente,7)+0.000005)-Berekening!D10)),1000000000000),IF((INDEX(T1_Rente,7)-0.005+0.000005)>Berekening!D10,(Berekening!D45-(INDEX(T1_Rente,7)-0.005+0.000005)*Berekening!D46)/(360*((INDEX(T1_Rente,7)-0.005+0.000005)-Berekening!D10)),1000000000000)) -> 4244776.4 | E41: =MIN(1000000000000,IF((INDEX(T1_Rente,7)+0.000005)<Berekening!E10,(Berekening!E45-(INDEX(T1_Rente,7)+0.000005)*Berekening!E46)/(360*((INDEX(T1_Rente,7)+0.000005)-Berekening!E10)),1000000000000),IF((INDEX(T1_Rente,7)-0.005+0.000005)>Berekening!E10,(Berekening!E45-(INDEX(T1_Rente,7)-0.005+0.000005)*Berekening!E46)/(360*((INDEX(T1_Rente,7)-0.005+0.000005)-Berekening!E10)),1000000000000)) -> -1509960.9 | F41: =MIN(1000000000000,IF((INDEX(T1_Rente,7)+0.000005)<Berekening!F10,(Berekening!F45-(INDEX(T1_Rente,7)+0.000005)*Berekening!F46)/(360*((INDEX(T1_Rente,7)+0.000005)-Berekening!F10)),1000000000000),IF((INDEX(T1_Rente,7)-0.005+0.000005)>Berekening!F10,(Berekening!F45-(INDEX(T1_Rente,7)-0.005+0.000005)*Berekening!F46)/(360*((INDEX(T1_Rente,7)-0.005+0.000005)-Berekening!F10)),1000000000000)) -> 1661282.5 | G41: =MIN(1000000000000,IF((INDEX(T1_Rente,7)+0.000005)<Berekening!G10,(Berekening!G45-(INDEX(T1_Rente,7)+0.000005)*Berekening!G46)/(360*((INDEX(T1_Rente,7)+0.000005)-Berekening!G10)),1000000000000),IF((INDEX(T1_Rente,7)-0.005+0.000005)>Berekening!G10,(Berekening!G45-(INDEX(T1_Rente,7)-0.005+0.000005)*Berekening!G46)/(360*((INDEX(T1_Rente,7)-0.005+0.000005)-Berekening!G10)),1000000000000)) -> 0 | H41: =MIN(1000000000000,IF((INDEX(T1_Rente,7)+0.000005)<Berekening!H10,(Berekening!H45-(INDEX(T1_Rente,7)+0.000005)*Berekening!H46)/(360*((INDEX(T1_Rente,7)+0.000005)-Berekening!H10)),1000000000000),IF((INDEX(T1_Rente,7)-0.005+0.000005)>Berekening!H10,(Berekening!H45-(INDEX(T1_Rente,7)-0.005+0.000005)*Berekening!H46)/(360*((INDEX(T1_Rente,7)-0.005+0.000005)-Berekening!H10)),1000000000000)) -> 0 | I41: =MIN(1000000000000,IF((INDEX(T1_Rente,7)+0.000005)<Berekening!I10,(Berekening!I45-(INDEX(T1_Rente,7)+0.000005)*Berekening!I46)/(360*((INDEX(T1_Rente,7)+0.000005)-Berekening!I10)),1000000000000),IF((INDEX(T1_Rente,7)-0.005+0.000005)>Berekening!I10,(Berekening!I45-(INDEX(T1_Rente,7)-0.005+0.000005)*Berekening!I46)/(360*((INDEX(T1_Rente,7)-0.005+0.000005)-Berekening!I10)),1000000000000)) -> 0 | J41: =MIN(1000000000000,IF((INDEX(T1_Rente,7)+0.000005)<Berekening!J10,(Berekening!J45-(INDEX(T1_Rente,7)+0.000005)*Berekening!J46)/(360*((INDEX(T1_Rente,7)+0.000005)-Berekening!J10)),1000000000000),IF((INDEX(T1_Rente,7)-0.005+0.000005)>Berekening!J10,(Berekening!J45-(INDEX(T1_Rente,7)-0.005+0.000005)*Berekening!J46)/(360*((INDEX(T1_Rente,7)-0.005+0.000005)-Berekening!J10)),1000000000000)) -> 4378947.9 | ... M41: =MIN(1000000000000,IF((INDEX(T1_Rente,7)+0.000005)<Berekening!M10,(Berekening!M45-(INDEX(T1_Rente,7)+0.000005)*Berekening!M46)/(360*((INDEX(T1_Rente,7)+0.000005)-Berekening!M10)),1000000000000),IF((INDEX(T1_Rente,7)-0.005+0.000005)>Berekening!M10,(Berekening!M45-(INDEX(T1_Rente,7)-0.005+0.000005)*Berekening!M46)/(360*((INDEX(T1_Rente,7)-0.005+0.000005)-Berekening!M10)),1000000000000)) -> 4378947.9
A42: Kolom 7: haalbaar bedrag (−1 = onmogelijk) | B42: € | C42: =IF(C40>C41,-1,IF(C39<C40-0.000000001,-1,IF(C39>C41,MAX(C40,C41-1),C39))) -> -1 | D42: =IF(D40>D41,-1,IF(D39<D40-0.000000001,-1,IF(D39>D41,MAX(D40,D41-1),D39))) -> -1 | E42: =IF(E40>E41,-1,IF(E39<E40-0.000000001,-1,IF(E39>E41,MAX(E40,E41-1),E39))) -> -1 | F42: =IF(F40>F41,-1,IF(F39<F40-0.000000001,-1,IF(F39>F41,MAX(F40,F41-1),F39))) -> -1 | G42: =IF(G40>G41,-1,IF(G39<G40-0.000000001,-1,IF(G39>G41,MAX(G40,G41-1),G39))) -> 0 | H42: =IF(H40>H41,-1,IF(H39<H40-0.000000001,-1,IF(H39>H41,MAX(H40,H41-1),H39))) -> 0 | I42: =IF(I40>I41,-1,IF(I39<I40-0.000000001,-1,IF(I39>I41,MAX(I40,I41-1),I39))) -> 0 | J42: =IF(J40>J41,-1,IF(J39<J40-0.000000001,-1,IF(J39>J41,MAX(J40,J41-1),J39))) -> -1 | ... M42: =IF(M40>M41,-1,IF(M39<M40-0.000000001,-1,IF(M39>M41,MAX(M40,M41-1),M39))) -> -1
A43: Kolom 8: woonquote | B43: % | C43: =INDEX(T1_Tabel,Berekening!C80,8)+(Berekening!C79-INDEX(T1_Inkomen,Berekening!C80))/(INDEX(T1_Inkomen,Berekening!C80+1)-INDEX(T1_Inkomen,Berekening!C80))*(INDEX(T1_Tabel,Berekening!C80+1,8)-INDEX(T1_Tabel,Berekening!C80,8)) -> 0.292 | D43: =INDEX(T1_Tabel,Berekening!D80,8)+(Berekening!D79-INDEX(T1_Inkomen,Berekening!D80))/(INDEX(T1_Inkomen,Berekening!D80+1)-INDEX(T1_Inkomen,Berekening!D80))*(INDEX(T1_Tabel,Berekening!D80+1,8)-INDEX(T1_Tabel,Berekening!D80,8)) -> 0.292 | E43: =INDEX(T1_Tabel,Berekening!E80,8)+(Berekening!E79-INDEX(T1_Inkomen,Berekening!E80))/(INDEX(T1_Inkomen,Berekening!E80+1)-INDEX(T1_Inkomen,Berekening!E80))*(INDEX(T1_Tabel,Berekening!E80+1,8)-INDEX(T1_Tabel,Berekening!E80,8)) -> 0.292 | F43: =INDEX(T1_Tabel,Berekening!F80,8)+(Berekening!F79-INDEX(T1_Inkomen,Berekening!F80))/(INDEX(T1_Inkomen,Berekening!F80+1)-INDEX(T1_Inkomen,Berekening!F80))*(INDEX(T1_Tabel,Berekening!F80+1,8)-INDEX(T1_Tabel,Berekening!F80,8)) -> 0.292 | G43: =INDEX(T1_Tabel,Berekening!G80,8)+(Berekening!G79-INDEX(T1_Inkomen,Berekening!G80))/(INDEX(T1_Inkomen,Berekening!G80+1)-INDEX(T1_Inkomen,Berekening!G80))*(INDEX(T1_Tabel,Berekening!G80+1,8)-INDEX(T1_Tabel,Berekening!G80,8)) -> 0.246 | H43: =INDEX(T1_Tabel,Berekening!H80,8)+(Berekening!H79-INDEX(T1_Inkomen,Berekening!H80))/(INDEX(T1_Inkomen,Berekening!H80+1)-INDEX(T1_Inkomen,Berekening!H80))*(INDEX(T1_Tabel,Berekening!H80+1,8)-INDEX(T1_Tabel,Berekening!H80,8)) -> 0.292 | I43: =INDEX(T1_Tabel,Berekening!I80,8)+(Berekening!I79-INDEX(T1_Inkomen,Berekening!I80))/(INDEX(T1_Inkomen,Berekening!I80+1)-INDEX(T1_Inkomen,Berekening!I80))*(INDEX(T1_Tabel,Berekening!I80+1,8)-INDEX(T1_Tabel,Berekening!I80,8)) -> 0.292 | J43: =INDEX(T1_Tabel,Berekening!J80,8)+(Berekening!J79-INDEX(T1_Inkomen,Berekening!J80))/(INDEX(T1_Inkomen,Berekening!J80+1)-INDEX(T1_Inkomen,Berekening!J80))*(INDEX(T1_Tabel,Berekening!J80+1,8)-INDEX(T1_Tabel,Berekening!J80,8)) -> 0.292 | ... M43: =INDEX(T1_Tabel,Berekening!M80,8)+(Berekening!M79-INDEX(T1_Inkomen,Berekening!M80))/(INDEX(T1_Inkomen,Berekening!M80+1)-INDEX(T1_Inkomen,Berekening!M80))*(INDEX(T1_Tabel,Berekening!M80+1,8)-INDEX(T1_Tabel,Berekening!M80,8)) -> 0.292
A44: Kolom 8: bedrag als de woonquote van deze kolom geldt | B44: € | C44: =MAX(0,(C43*C6/12-Berekening!C18-Berekening!C44)*Berekening!C11-Berekening!C75+C7) -> 393501.97 | D44: =MAX(0,(D43*D6/12-Berekening!D18-Berekening!D44)*Berekening!D11-Berekening!D75+D7) -> 422553.52 | E44: =MAX(0,(E43*E6/12-Berekening!E18-Berekening!E44)*Berekening!E11-Berekening!E75+E7) -> 270854.42 | F44: =MAX(0,(F43*F6/12-Berekening!F18-Berekening!F44)*Berekening!F11-Berekening!F75+F7) -> 380082.3 | G44: =MAX(0,(G43*G6/12-Berekening!G18-Berekening!G44)*Berekening!G11-Berekening!G75+G7) -> 259434.81 | H44: =MAX(0,(H43*H6/12-Berekening!H18-Berekening!H44)*Berekening!H11-Berekening!H75+H7) -> 684469.29 | I44: =MAX(0,(I43*I6/12-Berekening!I18-Berekening!I44)*Berekening!I11-Berekening!I75+I7) -> 946273.87 | J44: =MAX(0,(J43*J6/12-Berekening!J18-Berekening!J44)*Berekening!J11-Berekening!J75+J7) -> 430788.04 | ... M44: =MAX(0,(M43*M6/12-Berekening!M18-Berekening!M44)*Berekening!M11-Berekening!M75+M7) -> 393501.97
A45: Kolom 8: laagste bedrag waarbij de gewogen rente in deze kolom valt | B45: € | C45: =MAX(0,IF((INDEX(T1_Rente,8)+0.000005)>Berekening!C10,(Berekening!C45-(INDEX(T1_Rente,8)+0.000005)*Berekening!C46)/(360*((INDEX(T1_Rente,8)+0.000005)-Berekening!C10)),IF((INDEX(T1_Rente,8)+0.000005)=Berekening!C10,IF(Berekening!C45-(INDEX(T1_Rente,8)+0.000005)*Berekening!C46<=0,-1000000000000,1000000000000),-1000000000000)),IF((INDEX(T1_Rente,8)-0.005+0.000005)<Berekening!C10,(Berekening!C45-(INDEX(T1_Rente,8)-0.005+0.000005)*Berekening!C46)/(360*((INDEX(T1_Rente,8)-0.005+0.000005)-Berekening!C10)),IF((INDEX(T1_Rente,8)-0.005+0.000005)=Berekening!C10,IF(Berekening!C45-(INDEX(T1_Rente,8)-0.005+0.000005)*Berekening!C46>0,-1000000000000,1000000000000),-1000000000000))) -> 4378947.9 | D45: =MAX(0,IF((INDEX(T1_Rente,8)+0.000005)>Berekening!D10,(Berekening!D45-(INDEX(T1_Rente,8)+0.000005)*Berekening!D46)/(360*((INDEX(T1_Rente,8)+0.000005)-Berekening!D10)),IF((INDEX(T1_Rente,8)+0.000005)=Berekening!D10,IF(Berekening!D45-(INDEX(T1_Rente,8)+0.000005)*Berekening!D46<=0,-1000000000000,1000000000000),-1000000000000)),IF((INDEX(T1_Rente,8)-0.005+0.000005)<Berekening!D10,(Berekening!D45-(INDEX(T1_Rente,8)-0.005+0.000005)*Berekening!D46)/(360*((INDEX(T1_Rente,8)-0.005+0.000005)-Berekening!D10)),IF((INDEX(T1_Rente,8)-0.005+0.000005)=Berekening!D10,IF(Berekening!D45-(INDEX(T1_Rente,8)-0.005+0.000005)*Berekening!D46>0,-1000000000000,1000000000000),-1000000000000))) -> 4244776.4 | E45: =MAX(0,IF((INDEX(T1_Rente,8)+0.000005)>Berekening!E10,(Berekening!E45-(INDEX(T1_Rente,8)+0.000005)*Berekening!E46)/(360*((INDEX(T1_Rente,8)+0.000005)-Berekening!E10)),IF((INDEX(T1_Rente,8)+0.000005)=Berekening!E10,IF(Berekening!E45-(INDEX(T1_Rente,8)+0.000005)*Berekening!E46<=0,-1000000000000,1000000000000),-1000000000000)),IF((INDEX(T1_Rente,8)-0.005+0.000005)<Berekening!E10,(Berekening!E45-(INDEX(T1_Rente,8)-0.005+0.000005)*Berekening!E46)/(360*((INDEX(T1_Rente,8)-0.005+0.000005)-Berekening!E10)),IF((INDEX(T1_Rente,8)-0.005+0.000005)=Berekening!E10,IF(Berekening!E45-(INDEX(T1_Rente,8)-0.005+0.000005)*Berekening!E46>0,-1000000000000,1000000000000),-1000000000000))) -> 0 | F45: =MAX(0,IF((INDEX(T1_Rente,8)+0.000005)>Berekening!F10,(Berekening!F45-(INDEX(T1_Rente,8)+0.000005)*Berekening!F46)/(360*((INDEX(T1_Rente,8)+0.000005)-Berekening!F10)),IF((INDEX(T1_Rente,8)+0.000005)=Berekening!F10,IF(Berekening!F45-(INDEX(T1_Rente,8)+0.000005)*Berekening!F46<=0,-1000000000000,1000000000000),-1000000000000)),IF((INDEX(T1_Rente,8)-0.005+0.000005)<Berekening!F10,(Berekening!F45-(INDEX(T1_Rente,8)-0.005+0.000005)*Berekening!F46)/(360*((INDEX(T1_Rente,8)-0.005+0.000005)-Berekening!F10)),IF((INDEX(T1_Rente,8)-0.005+0.000005)=Berekening!F10,IF(Berekening!F45-(INDEX(T1_Rente,8)-0.005+0.000005)*Berekening!F46>0,-1000000000000,1000000000000),-1000000000000))) -> 1661282.5 | G45: =MAX(0,IF((INDEX(T1_Rente,8)+0.000005)>Berekening!G10,(Berekening!G45-(INDEX(T1_Rente,8)+0.000005)*Berekening!G46)/(360*((INDEX(T1_Rente,8)+0.000005)-Berekening!G10)),IF((INDEX(T1_Rente,8)+0.000005)=Berekening!G10,IF(Berekening!G45-(INDEX(T1_Rente,8)+0.000005)*Berekening!G46<=0,-1000000000000,1000000000000),-1000000000000)),IF((INDEX(T1_Rente,8)-0.005+0.000005)<Berekening!G10,(Berekening!G45-(INDEX(T1_Rente,8)-0.005+0.000005)*Berekening!G46)/(360*((INDEX(T1_Rente,8)-0.005+0.000005)-Berekening!G10)),IF((INDEX(T1_Rente,8)-0.005+0.000005)=Berekening!G10,IF(Berekening!G45-(INDEX(T1_Rente,8)-0.005+0.000005)*Berekening!G46>0,-1000000000000,1000000000000),-1000000000000))) -> 0 | H45: =MAX(0,IF((INDEX(T1_Rente,8)+0.000005)>Berekening!H10,(Berekening!H45-(INDEX(T1_Rente,8)+0.000005)*Berekening!H46)/(360*((INDEX(T1_Rente,8)+0.000005)-Berekening!H10)),IF((INDEX(T1_Rente,8)+0.000005)=Berekening!H10,IF(Berekening!H45-(INDEX(T1_Rente,8)+0.000005)*Berekening!H46<=0,-1000000000000,1000000000000),-1000000000000)),IF((INDEX(T1_Rente,8)-0.005+0.000005)<Berekening!H10,(Berekening!H45-(INDEX(T1_Rente,8)-0.005+0.000005)*Berekening!H46)/(360*((INDEX(T1_Rente,8)-0.005+0.000005)-Berekening!H10)),IF((INDEX(T1_Rente,8)-0.005+0.000005)=Berekening!H10,IF(Berekening!H45-(INDEX(T1_Rente,8)-0.005+0.000005)*Berekening!H46>0,-1000000000000,1000000000000),-1000000000000))) -> 0 | I45: =MAX(0,IF((INDEX(T1_Rente,8)+0.000005)>Berekening!I10,(Berekening!I45-(INDEX(T1_Rente,8)+0.000005)*Berekening!I46)/(360*((INDEX(T1_Rente,8)+0.000005)-Berekening!I10)),IF((INDEX(T1_Rente,8)+0.000005)=Berekening!I10,IF(Berekening!I45-(INDEX(T1_Rente,8)+0.000005)*Berekening!I46<=0,-1000000000000,1000000000000),-1000000000000)),IF((INDEX(T1_Rente,8)-0.005+0.000005)<Berekening!I10,(Berekening!I45-(INDEX(T1_Rente,8)-0.005+0.000005)*Berekening!I46)/(360*((INDEX(T1_Rente,8)-0.005+0.000005)-Berekening!I10)),IF((INDEX(T1_Rente,8)-0.005+0.000005)=Berekening!I10,IF(Berekening!I45-(INDEX(T1_Rente,8)-0.005+0.000005)*Berekening!I46>0,-1000000000000,1000000000000),-1000000000000))) -> 0 | J45: =MAX(0,IF((INDEX(T1_Rente,8)+0.000005)>Berekening!J10,(Berekening!J45-(INDEX(T1_Rente,8)+0.000005)*Berekening!J46)/(360*((INDEX(T1_Rente,8)+0.000005)-Berekening!J10)),IF((INDEX(T1_Rente,8)+0.000005)=Berekening!J10,IF(Berekening!J45-(INDEX(T1_Rente,8)+0.000005)*Berekening!J46<=0,-1000000000000,1000000000000),-1000000000000)),IF((INDEX(T1_Rente,8)-0.005+0.000005)<Berekening!J10,(Berekening!J45-(INDEX(T1_Rente,8)-0.005+0.000005)*Berekening!J46)/(360*((INDEX(T1_Rente,8)-0.005+0.000005)-Berekening!J10)),IF((INDEX(T1_Rente,8)-0.005+0.000005)=Berekening!J10,IF(Berekening!J45-(INDEX(T1_Rente,8)-0.005+0.000005)*Berekening!J46>0,-1000000000000,1000000000000),-1000000000000))) -> 4378947.9 | ... M45: =MAX(0,IF((INDEX(T1_Rente,8)+0.000005)>Berekening!M10,(Berekening!M45-(INDEX(T1_Rente,8)+0.000005)*Berekening!M46)/(360*((INDEX(T1_Rente,8)+0.000005)-Berekening!M10)),IF((INDEX(T1_Rente,8)+0.000005)=Berekening!M10,IF(Berekening!M45-(INDEX(T1_Rente,8)+0.000005)*Berekening!M46<=0,-1000000000000,1000000000000),-1000000000000)),IF((INDEX(T1_Rente,8)-0.005+0.000005)<Berekening!M10,(Berekening!M45-(INDEX(T1_Rente,8)-0.005+0.000005)*Berekening!M46)/(360*((INDEX(T1_Rente,8)-0.005+0.000005)-Berekening!M10)),IF((INDEX(T1_Rente,8)-0.005+0.000005)=Berekening!M10,IF(Berekening!M45-(INDEX(T1_Rente,8)-0.005+0.000005)*Berekening!M46>0,-1000000000000,1000000000000),-1000000000000))) -> 4378947.9
A46: Kolom 8: hoogste bedrag waarbij de gewogen rente in deze kolom valt | B46: € | C46: =MIN(1000000000000,IF((INDEX(T1_Rente,8)+0.000005)<Berekening!C10,(Berekening!C45-(INDEX(T1_Rente,8)+0.000005)*Berekening!C46)/(360*((INDEX(T1_Rente,8)+0.000005)-Berekening!C10)),1000000000000),IF((INDEX(T1_Rente,8)-0.005+0.000005)>Berekening!C10,(Berekening!C45-(INDEX(T1_Rente,8)-0.005+0.000005)*Berekening!C46)/(360*((INDEX(T1_Rente,8)-0.005+0.000005)-Berekening!C10)),1000000000000)) -> 1000000000000 | D46: =MIN(1000000000000,IF((INDEX(T1_Rente,8)+0.000005)<Berekening!D10,(Berekening!D45-(INDEX(T1_Rente,8)+0.000005)*Berekening!D46)/(360*((INDEX(T1_Rente,8)+0.000005)-Berekening!D10)),1000000000000),IF((INDEX(T1_Rente,8)-0.005+0.000005)>Berekening!D10,(Berekening!D45-(INDEX(T1_Rente,8)-0.005+0.000005)*Berekening!D46)/(360*((INDEX(T1_Rente,8)-0.005+0.000005)-Berekening!D10)),1000000000000)) -> 1000000000000 | E46: =MIN(1000000000000,IF((INDEX(T1_Rente,8)+0.000005)<Berekening!E10,(Berekening!E45-(INDEX(T1_Rente,8)+0.000005)*Berekening!E46)/(360*((INDEX(T1_Rente,8)+0.000005)-Berekening!E10)),1000000000000),IF((INDEX(T1_Rente,8)-0.005+0.000005)>Berekening!E10,(Berekening!E45-(INDEX(T1_Rente,8)-0.005+0.000005)*Berekening!E46)/(360*((INDEX(T1_Rente,8)-0.005+0.000005)-Berekening!E10)),1000000000000)) -> 1000000000000 | F46: =MIN(1000000000000,IF((INDEX(T1_Rente,8)+0.000005)<Berekening!F10,(Berekening!F45-(INDEX(T1_Rente,8)+0.000005)*Berekening!F46)/(360*((INDEX(T1_Rente,8)+0.000005)-Berekening!F10)),1000000000000),IF((INDEX(T1_Rente,8)-0.005+0.000005)>Berekening!F10,(Berekening!F45-(INDEX(T1_Rente,8)-0.005+0.000005)*Berekening!F46)/(360*((INDEX(T1_Rente,8)-0.005+0.000005)-Berekening!F10)),1000000000000)) -> 1000000000000 | G46: =MIN(1000000000000,IF((INDEX(T1_Rente,8)+0.000005)<Berekening!G10,(Berekening!G45-(INDEX(T1_Rente,8)+0.000005)*Berekening!G46)/(360*((INDEX(T1_Rente,8)+0.000005)-Berekening!G10)),1000000000000),IF((INDEX(T1_Rente,8)-0.005+0.000005)>Berekening!G10,(Berekening!G45-(INDEX(T1_Rente,8)-0.005+0.000005)*Berekening!G46)/(360*((INDEX(T1_Rente,8)-0.005+0.000005)-Berekening!G10)),1000000000000)) -> 1000000000000 | H46: =MIN(1000000000000,IF((INDEX(T1_Rente,8)+0.000005)<Berekening!H10,(Berekening!H45-(INDEX(T1_Rente,8)+0.000005)*Berekening!H46)/(360*((INDEX(T1_Rente,8)+0.000005)-Berekening!H10)),1000000000000),IF((INDEX(T1_Rente,8)-0.005+0.000005)>Berekening!H10,(Berekening!H45-(INDEX(T1_Rente,8)-0.005+0.000005)*Berekening!H46)/(360*((INDEX(T1_Rente,8)-0.005+0.000005)-Berekening!H10)),1000000000000)) -> 1000000000000 | I46: =MIN(1000000000000,IF((INDEX(T1_Rente,8)+0.000005)<Berekening!I10,(Berekening!I45-(INDEX(T1_Rente,8)+0.000005)*Berekening!I46)/(360*((INDEX(T1_Rente,8)+0.000005)-Berekening!I10)),1000000000000),IF((INDEX(T1_Rente,8)-0.005+0.000005)>Berekening!I10,(Berekening!I45-(INDEX(T1_Rente,8)-0.005+0.000005)*Berekening!I46)/(360*((INDEX(T1_Rente,8)-0.005+0.000005)-Berekening!I10)),1000000000000)) -> 1000000000000 | J46: =MIN(1000000000000,IF((INDEX(T1_Rente,8)+0.000005)<Berekening!J10,(Berekening!J45-(INDEX(T1_Rente,8)+0.000005)*Berekening!J46)/(360*((INDEX(T1_Rente,8)+0.000005)-Berekening!J10)),1000000000000),IF((INDEX(T1_Rente,8)-0.005+0.000005)>Berekening!J10,(Berekening!J45-(INDEX(T1_Rente,8)-0.005+0.000005)*Berekening!J46)/(360*((INDEX(T1_Rente,8)-0.005+0.000005)-Berekening!J10)),1000000000000)) -> 1000000000000 | ... M46: =MIN(1000000000000,IF((INDEX(T1_Rente,8)+0.000005)<Berekening!M10,(Berekening!M45-(INDEX(T1_Rente,8)+0.000005)*Berekening!M46)/(360*((INDEX(T1_Rente,8)+0.000005)-Berekening!M10)),1000000000000),IF((INDEX(T1_Rente,8)-0.005+0.000005)>Berekening!M10,(Berekening!M45-(INDEX(T1_Rente,8)-0.005+0.000005)*Berekening!M46)/(360*((INDEX(T1_Rente,8)-0.005+0.000005)-Berekening!M10)),1000000000000)) -> 1000000000000
A47: Kolom 8: haalbaar bedrag (−1 = onmogelijk) | B47: € | C47: =IF(C45>C46,-1,IF(C44<C45-0.000000001,-1,IF(C44>C46,MAX(C45,C46-1),C44))) -> -1 | D47: =IF(D45>D46,-1,IF(D44<D45-0.000000001,-1,IF(D44>D46,MAX(D45,D46-1),D44))) -> -1 | E47: =IF(E45>E46,-1,IF(E44<E45-0.000000001,-1,IF(E44>E46,MAX(E45,E46-1),E44))) -> 270854.42 | F47: =IF(F45>F46,-1,IF(F44<F45-0.000000001,-1,IF(F44>F46,MAX(F45,F46-1),F44))) -> -1 | G47: =IF(G45>G46,-1,IF(G44<G45-0.000000001,-1,IF(G44>G46,MAX(G45,G46-1),G44))) -> 259434.81 | H47: =IF(H45>H46,-1,IF(H44<H45-0.000000001,-1,IF(H44>H46,MAX(H45,H46-1),H44))) -> 684469.29 | I47: =IF(I45>I46,-1,IF(I44<I45-0.000000001,-1,IF(I44>I46,MAX(I45,I46-1),I44))) -> 946273.87 | J47: =IF(J45>J46,-1,IF(J44<J45-0.000000001,-1,IF(J44>J46,MAX(J45,J46-1),J44))) -> -1 | ... M47: =IF(M45>M46,-1,IF(M44<M45-0.000000001,-1,IF(M44>M46,MAX(M45,M46-1),M44))) -> -1
A48: Kolom 9: woonquote | B48: % | C48: =INDEX(T1_Tabel,Berekening!C80,9)+(Berekening!C79-INDEX(T1_Inkomen,Berekening!C80))/(INDEX(T1_Inkomen,Berekening!C80+1)-INDEX(T1_Inkomen,Berekening!C80))*(INDEX(T1_Tabel,Berekening!C80+1,9)-INDEX(T1_Tabel,Berekening!C80,9)) -> 0.3 | D48: =INDEX(T1_Tabel,Berekening!D80,9)+(Berekening!D79-INDEX(T1_Inkomen,Berekening!D80))/(INDEX(T1_Inkomen,Berekening!D80+1)-INDEX(T1_Inkomen,Berekening!D80))*(INDEX(T1_Tabel,Berekening!D80+1,9)-INDEX(T1_Tabel,Berekening!D80,9)) -> 0.3 | E48: =INDEX(T1_Tabel,Berekening!E80,9)+(Berekening!E79-INDEX(T1_Inkomen,Berekening!E80))/(INDEX(T1_Inkomen,Berekening!E80+1)-INDEX(T1_Inkomen,Berekening!E80))*(INDEX(T1_Tabel,Berekening!E80+1,9)-INDEX(T1_Tabel,Berekening!E80,9)) -> 0.3 | F48: =INDEX(T1_Tabel,Berekening!F80,9)+(Berekening!F79-INDEX(T1_Inkomen,Berekening!F80))/(INDEX(T1_Inkomen,Berekening!F80+1)-INDEX(T1_Inkomen,Berekening!F80))*(INDEX(T1_Tabel,Berekening!F80+1,9)-INDEX(T1_Tabel,Berekening!F80,9)) -> 0.3 | G48: =INDEX(T1_Tabel,Berekening!G80,9)+(Berekening!G79-INDEX(T1_Inkomen,Berekening!G80))/(INDEX(T1_Inkomen,Berekening!G80+1)-INDEX(T1_Inkomen,Berekening!G80))*(INDEX(T1_Tabel,Berekening!G80+1,9)-INDEX(T1_Tabel,Berekening!G80,9)) -> 0.255 | H48: =INDEX(T1_Tabel,Berekening!H80,9)+(Berekening!H79-INDEX(T1_Inkomen,Berekening!H80))/(INDEX(T1_Inkomen,Berekening!H80+1)-INDEX(T1_Inkomen,Berekening!H80))*(INDEX(T1_Tabel,Berekening!H80+1,9)-INDEX(T1_Tabel,Berekening!H80,9)) -> 0.3 | I48: =INDEX(T1_Tabel,Berekening!I80,9)+(Berekening!I79-INDEX(T1_Inkomen,Berekening!I80))/(INDEX(T1_Inkomen,Berekening!I80+1)-INDEX(T1_Inkomen,Berekening!I80))*(INDEX(T1_Tabel,Berekening!I80+1,9)-INDEX(T1_Tabel,Berekening!I80,9)) -> 0.3 | J48: =INDEX(T1_Tabel,Berekening!J80,9)+(Berekening!J79-INDEX(T1_Inkomen,Berekening!J80))/(INDEX(T1_Inkomen,Berekening!J80+1)-INDEX(T1_Inkomen,Berekening!J80))*(INDEX(T1_Tabel,Berekening!J80+1,9)-INDEX(T1_Tabel,Berekening!J80,9)) -> 0.3 | ... M48: =INDEX(T1_Tabel,Berekening!M80,9)+(Berekening!M79-INDEX(T1_Inkomen,Berekening!M80))/(INDEX(T1_Inkomen,Berekening!M80+1)-INDEX(T1_Inkomen,Berekening!M80))*(INDEX(T1_Tabel,Berekening!M80+1,9)-INDEX(T1_Tabel,Berekening!M80,9)) -> 0.3
A49: Kolom 9: bedrag als de woonquote van deze kolom geldt | B49: € | C49: =MAX(0,(C48*C6/12-Berekening!C18-Berekening!C44)*Berekening!C11-Berekening!C75+C7) -> 422457.43 | D49: =MAX(0,(D48*D6/12-Berekening!D18-Berekening!D44)*Berekening!D11-Berekening!D75+D7) -> 451508.98 | E49: =MAX(0,(E48*E6/12-Berekening!E18-Berekening!E44)*Berekening!E11-Berekening!E75+E7) -> 299809.89 | F49: =MAX(0,(F48*F6/12-Berekening!F18-Berekening!F44)*Berekening!F11-Berekening!F75+F7) -> 408024.54 | G49: =MAX(0,(G48*G6/12-Berekening!G18-Berekening!G44)*Berekening!G11-Berekening!G75+G7) -> 268121.45 | H49: =MAX(0,(H48*H6/12-Berekening!H18-Berekening!H44)*Berekening!H11-Berekening!H75+H7) -> 703772.94 | I49: =MAX(0,(I48*I6/12-Berekening!I18-Berekening!I44)*Berekening!I11-Berekening!I75+I7) -> 975229.34 | J49: =MAX(0,(J48*J6/12-Berekening!J18-Berekening!J44)*Berekening!J11-Berekening!J75+J7) -> 459743.5 | ... M49: =MAX(0,(M48*M6/12-Berekening!M18-Berekening!M44)*Berekening!M11-Berekening!M75+M7) -> 422457.43
A50: Kolom 9: laagste bedrag waarbij de gewogen rente in deze kolom valt | B50: € | C50: =MAX(0,IF((INDEX(T1_Rente,9)+0.000005)>Berekening!C10,(Berekening!C45-(INDEX(T1_Rente,9)+0.000005)*Berekening!C46)/(360*((INDEX(T1_Rente,9)+0.000005)-Berekening!C10)),IF((INDEX(T1_Rente,9)+0.000005)=Berekening!C10,IF(Berekening!C45-(INDEX(T1_Rente,9)+0.000005)*Berekening!C46<=0,-1000000000000,1000000000000),-1000000000000)),IF((INDEX(T1_Rente,9)-0.005+0.000005)<Berekening!C10,(Berekening!C45-(INDEX(T1_Rente,9)-0.005+0.000005)*Berekening!C46)/(360*((INDEX(T1_Rente,9)-0.005+0.000005)-Berekening!C10)),IF((INDEX(T1_Rente,9)-0.005+0.000005)=Berekening!C10,IF(Berekening!C45-(INDEX(T1_Rente,9)-0.005+0.000005)*Berekening!C46>0,-1000000000000,1000000000000),-1000000000000))) -> 0 | D50: =MAX(0,IF((INDEX(T1_Rente,9)+0.000005)>Berekening!D10,(Berekening!D45-(INDEX(T1_Rente,9)+0.000005)*Berekening!D46)/(360*((INDEX(T1_Rente,9)+0.000005)-Berekening!D10)),IF((INDEX(T1_Rente,9)+0.000005)=Berekening!D10,IF(Berekening!D45-(INDEX(T1_Rente,9)+0.000005)*Berekening!D46<=0,-1000000000000,1000000000000),-1000000000000)),IF((INDEX(T1_Rente,9)-0.005+0.000005)<Berekening!D10,(Berekening!D45-(INDEX(T1_Rente,9)-0.005+0.000005)*Berekening!D46)/(360*((INDEX(T1_Rente,9)-0.005+0.000005)-Berekening!D10)),IF((INDEX(T1_Rente,9)-0.005+0.000005)=Berekening!D10,IF(Berekening!D45-(INDEX(T1_Rente,9)-0.005+0.000005)*Berekening!D46>0,-1000000000000,1000000000000),-1000000000000))) -> 0 | E50: =MAX(0,IF((INDEX(T1_Rente,9)+0.000005)>Berekening!E10,(Berekening!E45-(INDEX(T1_Rente,9)+0.000005)*Berekening!E46)/(360*((INDEX(T1_Rente,9)+0.000005)-Berekening!E10)),IF((INDEX(T1_Rente,9)+0.000005)=Berekening!E10,IF(Berekening!E45-(INDEX(T1_Rente,9)+0.000005)*Berekening!E46<=0,-1000000000000,1000000000000),-1000000000000)),IF((INDEX(T1_Rente,9)-0.005+0.000005)<Berekening!E10,(Berekening!E45-(INDEX(T1_Rente,9)-0.005+0.000005)*Berekening!E46)/(360*((INDEX(T1_Rente,9)-0.005+0.000005)-Berekening!E10)),IF((INDEX(T1_Rente,9)-0.005+0.000005)=Berekening!E10,IF(Berekening!E45-(INDEX(T1_Rente,9)-0.005+0.000005)*Berekening!E46>0,-1000000000000,1000000000000),-1000000000000))) -> 0 | F50: =MAX(0,IF((INDEX(T1_Rente,9)+0.000005)>Berekening!F10,(Berekening!F45-(INDEX(T1_Rente,9)+0.000005)*Berekening!F46)/(360*((INDEX(T1_Rente,9)+0.000005)-Berekening!F10)),IF((INDEX(T1_Rente,9)+0.000005)=Berekening!F10,IF(Berekening!F45-(INDEX(T1_Rente,9)+0.000005)*Berekening!F46<=0,-1000000000000,1000000000000),-1000000000000)),IF((INDEX(T1_Rente,9)-0.005+0.000005)<Berekening!F10,(Berekening!F45-(INDEX(T1_Rente,9)-0.005+0.000005)*Berekening!F46)/(360*((INDEX(T1_Rente,9)-0.005+0.000005)-Berekening!F10)),IF((INDEX(T1_Rente,9)-0.005+0.000005)=Berekening!F10,IF(Berekening!F45-(INDEX(T1_Rente,9)-0.005+0.000005)*Berekening!F46>0,-1000000000000,1000000000000),-1000000000000))) -> 0 | G50: =MAX(0,IF((INDEX(T1_Rente,9)+0.000005)>Berekening!G10,(Berekening!G45-(INDEX(T1_Rente,9)+0.000005)*Berekening!G46)/(360*((INDEX(T1_Rente,9)+0.000005)-Berekening!G10)),IF((INDEX(T1_Rente,9)+0.000005)=Berekening!G10,IF(Berekening!G45-(INDEX(T1_Rente,9)+0.000005)*Berekening!G46<=0,-1000000000000,1000000000000),-1000000000000)),IF((INDEX(T1_Rente,9)-0.005+0.000005)<Berekening!G10,(Berekening!G45-(INDEX(T1_Rente,9)-0.005+0.000005)*Berekening!G46)/(360*((INDEX(T1_Rente,9)-0.005+0.000005)-Berekening!G10)),IF((INDEX(T1_Rente,9)-0.005+0.000005)=Berekening!G10,IF(Berekening!G45-(INDEX(T1_Rente,9)-0.005+0.000005)*Berekening!G46>0,-1000000000000,1000000000000),-1000000000000))) -> 0 | H50: =MAX(0,IF((INDEX(T1_Rente,9)+0.000005)>Berekening!H10,(Berekening!H45-(INDEX(T1_Rente,9)+0.000005)*Berekening!H46)/(360*((INDEX(T1_Rente,9)+0.000005)-Berekening!H10)),IF((INDEX(T1_Rente,9)+0.000005)=Berekening!H10,IF(Berekening!H45-(INDEX(T1_Rente,9)+0.000005)*Berekening!H46<=0,-1000000000000,1000000000000),-1000000000000)),IF((INDEX(T1_Rente,9)-0.005+0.000005)<Berekening!H10,(Berekening!H45-(INDEX(T1_Rente,9)-0.005+0.000005)*Berekening!H46)/(360*((INDEX(T1_Rente,9)-0.005+0.000005)-Berekening!H10)),IF((INDEX(T1_Rente,9)-0.005+0.000005)=Berekening!H10,IF(Berekening!H45-(INDEX(T1_Rente,9)-0.005+0.000005)*Berekening!H46>0,-1000000000000,1000000000000),-1000000000000))) -> 0 | I50: =MAX(0,IF((INDEX(T1_Rente,9)+0.000005)>Berekening!I10,(Berekening!I45-(INDEX(T1_Rente,9)+0.000005)*Berekening!I46)/(360*((INDEX(T1_Rente,9)+0.000005)-Berekening!I10)),IF((INDEX(T1_Rente,9)+0.000005)=Berekening!I10,IF(Berekening!I45-(INDEX(T1_Rente,9)+0.000005)*Berekening!I46<=0,-1000000000000,1000000000000),-1000000000000)),IF((INDEX(T1_Rente,9)-0.005+0.000005)<Berekening!I10,(Berekening!I45-(INDEX(T1_Rente,9)-0.005+0.000005)*Berekening!I46)/(360*((INDEX(T1_Rente,9)-0.005+0.000005)-Berekening!I10)),IF((INDEX(T1_Rente,9)-0.005+0.000005)=Berekening!I10,IF(Berekening!I45-(INDEX(T1_Rente,9)-0.005+0.000005)*Berekening!I46>0,-1000000000000,1000000000000),-1000000000000))) -> 0 | J50: =MAX(0,IF((INDEX(T1_Rente,9)+0.000005)>Berekening!J10,(Berekening!J45-(INDEX(T1_Rente,9)+0.000005)*Berekening!J46)/(360*((INDEX(T1_Rente,9)+0.000005)-Berekening!J10)),IF((INDEX(T1_Rente,9)+0.000005)=Berekening!J10,IF(Berekening!J45-(INDEX(T1_Rente,9)+0.000005)*Berekening!J46<=0,-1000000000000,1000000000000),-1000000000000)),IF((INDEX(T1_Rente,9)-0.005+0.000005)<Berekening!J10,(Berekening!J45-(INDEX(T1_Rente,9)-0.005+0.000005)*Berekening!J46)/(360*((INDEX(T1_Rente,9)-0.005+0.000005)-Berekening!J10)),IF((INDEX(T1_Rente,9)-0.005+0.000005)=Berekening!J10,IF(Berekening!J45-(INDEX(T1_Rente,9)-0.005+0.000005)*Berekening!J46>0,-1000000000000,1000000000000),-1000000000000))) -> 0 | ... M50: =MAX(0,IF((INDEX(T1_Rente,9)+0.000005)>Berekening!M10,(Berekening!M45-(INDEX(T1_Rente,9)+0.000005)*Berekening!M46)/(360*((INDEX(T1_Rente,9)+0.000005)-Berekening!M10)),IF((INDEX(T1_Rente,9)+0.000005)=Berekening!M10,IF(Berekening!M45-(INDEX(T1_Rente,9)+0.000005)*Berekening!M46<=0,-1000000000000,1000000000000),-1000000000000)),IF((INDEX(T1_Rente,9)-0.005+0.000005)<Berekening!M10,(Berekening!M45-(INDEX(T1_Rente,9)-0.005+0.000005)*Berekening!M46)/(360*((INDEX(T1_Rente,9)-0.005+0.000005)-Berekening!M10)),IF((INDEX(T1_Rente,9)-0.005+0.000005)=Berekening!M10,IF(Berekening!M45-(INDEX(T1_Rente,9)-0.005+0.000005)*Berekening!M46>0,-1000000000000,1000000000000),-1000000000000))) -> 0
A51: Kolom 9: hoogste bedrag waarbij de gewogen rente in deze kolom valt | B51: € | C51: =MIN(1000000000000,IF((INDEX(T1_Rente,9)+0.000005)<Berekening!C10,(Berekening!C45-(INDEX(T1_Rente,9)+0.000005)*Berekening!C46)/(360*((INDEX(T1_Rente,9)+0.000005)-Berekening!C10)),1000000000000),IF((INDEX(T1_Rente,9)-0.005+0.000005)>Berekening!C10,(Berekening!C45-(INDEX(T1_Rente,9)-0.005+0.000005)*Berekening!C46)/(360*((INDEX(T1_Rente,9)-0.005+0.000005)-Berekening!C10)),1000000000000)) -> -3594958.5 | D51: =MIN(1000000000000,IF((INDEX(T1_Rente,9)+0.000005)<Berekening!D10,(Berekening!D45-(INDEX(T1_Rente,9)+0.000005)*Berekening!D46)/(360*((INDEX(T1_Rente,9)+0.000005)-Berekening!D10)),1000000000000),IF((INDEX(T1_Rente,9)-0.005+0.000005)>Berekening!D10,(Berekening!D45-(INDEX(T1_Rente,9)-0.005+0.000005)*Berekening!D46)/(360*((INDEX(T1_Rente,9)-0.005+0.000005)-Berekening!D10)),1000000000000)) -> -3595040.5 | E51: =MIN(1000000000000,IF((INDEX(T1_Rente,9)+0.000005)<Berekening!E10,(Berekening!E45-(INDEX(T1_Rente,9)+0.000005)*Berekening!E46)/(360*((INDEX(T1_Rente,9)+0.000005)-Berekening!E10)),1000000000000),IF((INDEX(T1_Rente,9)-0.005+0.000005)>Berekening!E10,(Berekening!E45-(INDEX(T1_Rente,9)-0.005+0.000005)*Berekening!E46)/(360*((INDEX(T1_Rente,9)-0.005+0.000005)-Berekening!E10)),1000000000000)) -> -922.46057 | F51: =MIN(1000000000000,IF((INDEX(T1_Rente,9)+0.000005)<Berekening!F10,(Berekening!F45-(INDEX(T1_Rente,9)+0.000005)*Berekening!F46)/(360*((INDEX(T1_Rente,9)+0.000005)-Berekening!F10)),1000000000000),IF((INDEX(T1_Rente,9)-0.005+0.000005)>Berekening!F10,(Berekening!F45-(INDEX(T1_Rente,9)-0.005+0.000005)*Berekening!F46)/(360*((INDEX(T1_Rente,9)-0.005+0.000005)-Berekening!F10)),1000000000000)) -> -2.2324692e+09 | G51: =MIN(1000000000000,IF((INDEX(T1_Rente,9)+0.000005)<Berekening!G10,(Berekening!G45-(INDEX(T1_Rente,9)+0.000005)*Berekening!G46)/(360*((INDEX(T1_Rente,9)+0.000005)-Berekening!G10)),1000000000000),IF((INDEX(T1_Rente,9)-0.005+0.000005)>Berekening!G10,(Berekening!G45-(INDEX(T1_Rente,9)-0.005+0.000005)*Berekening!G46)/(360*((INDEX(T1_Rente,9)-0.005+0.000005)-Berekening!G10)),1000000000000)) -> 0 | H51: =MIN(1000000000000,IF((INDEX(T1_Rente,9)+0.000005)<Berekening!H10,(Berekening!H45-(INDEX(T1_Rente,9)+0.000005)*Berekening!H46)/(360*((INDEX(T1_Rente,9)+0.000005)-Berekening!H10)),1000000000000),IF((INDEX(T1_Rente,9)-0.005+0.000005)>Berekening!H10,(Berekening!H45-(INDEX(T1_Rente,9)-0.005+0.000005)*Berekening!H46)/(360*((INDEX(T1_Rente,9)-0.005+0.000005)-Berekening!H10)),1000000000000)) -> 0 | I51: =MIN(1000000000000,IF((INDEX(T1_Rente,9)+0.000005)<Berekening!I10,(Berekening!I45-(INDEX(T1_Rente,9)+0.000005)*Berekening!I46)/(360*((INDEX(T1_Rente,9)+0.000005)-Berekening!I10)),1000000000000),IF((INDEX(T1_Rente,9)-0.005+0.000005)>Berekening!I10,(Berekening!I45-(INDEX(T1_Rente,9)-0.005+0.000005)*Berekening!I46)/(360*((INDEX(T1_Rente,9)-0.005+0.000005)-Berekening!I10)),1000000000000)) -> 0 | J51: =MIN(1000000000000,IF((INDEX(T1_Rente,9)+0.000005)<Berekening!J10,(Berekening!J45-(INDEX(T1_Rente,9)+0.000005)*Berekening!J46)/(360*((INDEX(T1_Rente,9)+0.000005)-Berekening!J10)),1000000000000),IF((INDEX(T1_Rente,9)-0.005+0.000005)>Berekening!J10,(Berekening!J45-(INDEX(T1_Rente,9)-0.005+0.000005)*Berekening!J46)/(360*((INDEX(T1_Rente,9)-0.005+0.000005)-Berekening!J10)),1000000000000)) -> -3594958.5 | ... M51: =MIN(1000000000000,IF((INDEX(T1_Rente,9)+0.000005)<Berekening!M10,(Berekening!M45-(INDEX(T1_Rente,9)+0.000005)*Berekening!M46)/(360*((INDEX(T1_Rente,9)+0.000005)-Berekening!M10)),1000000000000),IF((INDEX(T1_Rente,9)-0.005+0.000005)>Berekening!M10,(Berekening!M45-(INDEX(T1_Rente,9)-0.005+0.000005)*Berekening!M46)/(360*((INDEX(T1_Rente,9)-0.005+0.000005)-Berekening!M10)),1000000000000)) -> -3594958.5
A52: Kolom 9: haalbaar bedrag (−1 = onmogelijk) | B52: € | C52: =IF(C50>C51,-1,IF(C49<C50-0.000000001,-1,IF(C49>C51,MAX(C50,C51-1),C49))) -> -1 | D52: =IF(D50>D51,-1,IF(D49<D50-0.000000001,-1,IF(D49>D51,MAX(D50,D51-1),D49))) -> -1 | E52: =IF(E50>E51,-1,IF(E49<E50-0.000000001,-1,IF(E49>E51,MAX(E50,E51-1),E49))) -> -1 | F52: =IF(F50>F51,-1,IF(F49<F50-0.000000001,-1,IF(F49>F51,MAX(F50,F51-1),F49))) -> -1 | G52: =IF(G50>G51,-1,IF(G49<G50-0.000000001,-1,IF(G49>G51,MAX(G50,G51-1),G49))) -> 0 | H52: =IF(H50>H51,-1,IF(H49<H50-0.000000001,-1,IF(H49>H51,MAX(H50,H51-1),H49))) -> 0 | I52: =IF(I50>I51,-1,IF(I49<I50-0.000000001,-1,IF(I49>I51,MAX(I50,I51-1),I49))) -> 0 | J52: =IF(J50>J51,-1,IF(J49<J50-0.000000001,-1,IF(J49>J51,MAX(J50,J51-1),J49))) -> -1 | ... M52: =IF(M50>M51,-1,IF(M49<M50-0.000000001,-1,IF(M49>M51,MAX(M50,M51-1),M49))) -> -1
A53: Kolom 10: woonquote | B53: % | C53: =INDEX(T1_Tabel,Berekening!C80,10)+(Berekening!C79-INDEX(T1_Inkomen,Berekening!C80))/(INDEX(T1_Inkomen,Berekening!C80+1)-INDEX(T1_Inkomen,Berekening!C80))*(INDEX(T1_Tabel,Berekening!C80+1,10)-INDEX(T1_Tabel,Berekening!C80,10)) -> 0.308 | D53: =INDEX(T1_Tabel,Berekening!D80,10)+(Berekening!D79-INDEX(T1_Inkomen,Berekening!D80))/(INDEX(T1_Inkomen,Berekening!D80+1)-INDEX(T1_Inkomen,Berekening!D80))*(INDEX(T1_Tabel,Berekening!D80+1,10)-INDEX(T1_Tabel,Berekening!D80,10)) -> 0.308 | E53: =INDEX(T1_Tabel,Berekening!E80,10)+(Berekening!E79-INDEX(T1_Inkomen,Berekening!E80))/(INDEX(T1_Inkomen,Berekening!E80+1)-INDEX(T1_Inkomen,Berekening!E80))*(INDEX(T1_Tabel,Berekening!E80+1,10)-INDEX(T1_Tabel,Berekening!E80,10)) -> 0.308 | F53: =INDEX(T1_Tabel,Berekening!F80,10)+(Berekening!F79-INDEX(T1_Inkomen,Berekening!F80))/(INDEX(T1_Inkomen,Berekening!F80+1)-INDEX(T1_Inkomen,Berekening!F80))*(INDEX(T1_Tabel,Berekening!F80+1,10)-INDEX(T1_Tabel,Berekening!F80,10)) -> 0.308 | G53: =INDEX(T1_Tabel,Berekening!G80,10)+(Berekening!G79-INDEX(T1_Inkomen,Berekening!G80))/(INDEX(T1_Inkomen,Berekening!G80+1)-INDEX(T1_Inkomen,Berekening!G80))*(INDEX(T1_Tabel,Berekening!G80+1,10)-INDEX(T1_Tabel,Berekening!G80,10)) -> 0.264 | H53: =INDEX(T1_Tabel,Berekening!H80,10)+(Berekening!H79-INDEX(T1_Inkomen,Berekening!H80))/(INDEX(T1_Inkomen,Berekening!H80+1)-INDEX(T1_Inkomen,Berekening!H80))*(INDEX(T1_Tabel,Berekening!H80+1,10)-INDEX(T1_Tabel,Berekening!H80,10)) -> 0.308 | I53: =INDEX(T1_Tabel,Berekening!I80,10)+(Berekening!I79-INDEX(T1_Inkomen,Berekening!I80))/(INDEX(T1_Inkomen,Berekening!I80+1)-INDEX(T1_Inkomen,Berekening!I80))*(INDEX(T1_Tabel,Berekening!I80+1,10)-INDEX(T1_Tabel,Berekening!I80,10)) -> 0.308 | J53: =INDEX(T1_Tabel,Berekening!J80,10)+(Berekening!J79-INDEX(T1_Inkomen,Berekening!J80))/(INDEX(T1_Inkomen,Berekening!J80+1)-INDEX(T1_Inkomen,Berekening!J80))*(INDEX(T1_Tabel,Berekening!J80+1,10)-INDEX(T1_Tabel,Berekening!J80,10)) -> 0.308 | ... M53: =INDEX(T1_Tabel,Berekening!M80,10)+(Berekening!M79-INDEX(T1_Inkomen,Berekening!M80))/(INDEX(T1_Inkomen,Berekening!M80+1)-INDEX(T1_Inkomen,Berekening!M80))*(INDEX(T1_Tabel,Berekening!M80+1,10)-INDEX(T1_Tabel,Berekening!M80,10)) -> 0.308
A54: Kolom 10: bedrag als de woonquote van deze kolom geldt | B54: € | C54: =MAX(0,(C53*C6/12-Berekening!C18-Berekening!C44)*Berekening!C11-Berekening!C75+C7) -> 451412.9 | D54: =MAX(0,(D53*D6/12-Berekening!D18-Berekening!D44)*Berekening!D11-Berekening!D75+D7) -> 480464.45 | E54: =MAX(0,(E53*E6/12-Berekening!E18-Berekening!E44)*Berekening!E11-Berekening!E75+E7) -> 328765.35 | F54: =MAX(0,(F53*F6/12-Berekening!F18-Berekening!F44)*Berekening!F11-Berekening!F75+F7) -> 435966.78 | G54: =MAX(0,(G53*G6/12-Berekening!G18-Berekening!G44)*Berekening!G11-Berekening!G75+G7) -> 276808.09 | H54: =MAX(0,(H53*H6/12-Berekening!H18-Berekening!H44)*Berekening!H11-Berekening!H75+H7) -> 723076.58 | I54: =MAX(0,(I53*I6/12-Berekening!I18-Berekening!I44)*Berekening!I11-Berekening!I75+I7) -> 1004184.8 | J54: =MAX(0,(J53*J6/12-Berekening!J18-Berekening!J44)*Berekening!J11-Berekening!J75+J7) -> 488698.97 | ... M54: =MAX(0,(M53*M6/12-Berekening!M18-Berekening!M44)*Berekening!M11-Berekening!M75+M7) -> 451412.9
A55: Kolom 10: laagste bedrag waarbij de gewogen rente in deze kolom valt | B55: € | C55: =MAX(0,IF((INDEX(T1_Rente,10)-0.005+0.000005)<Berekening!C10,(Berekening!C45-(INDEX(T1_Rente,10)-0.005+0.000005)*Berekening!C46)/(360*((INDEX(T1_Rente,10)-0.005+0.000005)-Berekening!C10)),IF((INDEX(T1_Rente,10)-0.005+0.000005)=Berekening!C10,IF(Berekening!C45-(INDEX(T1_Rente,10)-0.005+0.000005)*Berekening!C46>0,-1000000000000,1000000000000),-1000000000000))) -> 0 | D55: =MAX(0,IF((INDEX(T1_Rente,10)-0.005+0.000005)<Berekening!D10,(Berekening!D45-(INDEX(T1_Rente,10)-0.005+0.000005)*Berekening!D46)/(360*((INDEX(T1_Rente,10)-0.005+0.000005)-Berekening!D10)),IF((INDEX(T1_Rente,10)-0.005+0.000005)=Berekening!D10,IF(Berekening!D45-(INDEX(T1_Rente,10)-0.005+0.000005)*Berekening!D46>0,-1000000000000,1000000000000),-1000000000000))) -> 0 | E55: =MAX(0,IF((INDEX(T1_Rente,10)-0.005+0.000005)<Berekening!E10,(Berekening!E45-(INDEX(T1_Rente,10)-0.005+0.000005)*Berekening!E46)/(360*((INDEX(T1_Rente,10)-0.005+0.000005)-Berekening!E10)),IF((INDEX(T1_Rente,10)-0.005+0.000005)=Berekening!E10,IF(Berekening!E45-(INDEX(T1_Rente,10)-0.005+0.000005)*Berekening!E46>0,-1000000000000,1000000000000),-1000000000000))) -> 0 | F55: =MAX(0,IF((INDEX(T1_Rente,10)-0.005+0.000005)<Berekening!F10,(Berekening!F45-(INDEX(T1_Rente,10)-0.005+0.000005)*Berekening!F46)/(360*((INDEX(T1_Rente,10)-0.005+0.000005)-Berekening!F10)),IF((INDEX(T1_Rente,10)-0.005+0.000005)=Berekening!F10,IF(Berekening!F45-(INDEX(T1_Rente,10)-0.005+0.000005)*Berekening!F46>0,-1000000000000,1000000000000),-1000000000000))) -> 0 | G55: =MAX(0,IF((INDEX(T1_Rente,10)-0.005+0.000005)<Berekening!G10,(Berekening!G45-(INDEX(T1_Rente,10)-0.005+0.000005)*Berekening!G46)/(360*((INDEX(T1_Rente,10)-0.005+0.000005)-Berekening!G10)),IF((INDEX(T1_Rente,10)-0.005+0.000005)=Berekening!G10,IF(Berekening!G45-(INDEX(T1_Rente,10)-0.005+0.000005)*Berekening!G46>0,-1000000000000,1000000000000),-1000000000000))) -> 0 | H55: =MAX(0,IF((INDEX(T1_Rente,10)-0.005+0.000005)<Berekening!H10,(Berekening!H45-(INDEX(T1_Rente,10)-0.005+0.000005)*Berekening!H46)/(360*((INDEX(T1_Rente,10)-0.005+0.000005)-Berekening!H10)),IF((INDEX(T1_Rente,10)-0.005+0.000005)=Berekening!H10,IF(Berekening!H45-(INDEX(T1_Rente,10)-0.005+0.000005)*Berekening!H46>0,-1000000000000,1000000000000),-1000000000000))) -> 0 | I55: =MAX(0,IF((INDEX(T1_Rente,10)-0.005+0.000005)<Berekening!I10,(Berekening!I45-(INDEX(T1_Rente,10)-0.005+0.000005)*Berekening!I46)/(360*((INDEX(T1_Rente,10)-0.005+0.000005)-Berekening!I10)),IF((INDEX(T1_Rente,10)-0.005+0.000005)=Berekening!I10,IF(Berekening!I45-(INDEX(T1_Rente,10)-0.005+0.000005)*Berekening!I46>0,-1000000000000,1000000000000),-1000000000000))) -> 0 | J55: =MAX(0,IF((INDEX(T1_Rente,10)-0.005+0.000005)<Berekening!J10,(Berekening!J45-(INDEX(T1_Rente,10)-0.005+0.000005)*Berekening!J46)/(360*((INDEX(T1_Rente,10)-0.005+0.000005)-Berekening!J10)),IF((INDEX(T1_Rente,10)-0.005+0.000005)=Berekening!J10,IF(Berekening!J45-(INDEX(T1_Rente,10)-0.005+0.000005)*Berekening!J46>0,-1000000000000,1000000000000),-1000000000000))) -> 0 | ... M55: =MAX(0,IF((INDEX(T1_Rente,10)-0.005+0.000005)<Berekening!M10,(Berekening!M45-(INDEX(T1_Rente,10)-0.005+0.000005)*Berekening!M46)/(360*((INDEX(T1_Rente,10)-0.005+0.000005)-Berekening!M10)),IF((INDEX(T1_Rente,10)-0.005+0.000005)=Berekening!M10,IF(Berekening!M45-(INDEX(T1_Rente,10)-0.005+0.000005)*Berekening!M46>0,-1000000000000,1000000000000),-1000000000000))) -> 0
A56: Kolom 10: hoogste bedrag waarbij de gewogen rente in deze kolom valt | B56: € | C56: =MIN(1000000000000,IF((INDEX(T1_Rente,10)-0.005+0.000005)>Berekening!C10,(Berekening!C45-(INDEX(T1_Rente,10)-0.005+0.000005)*Berekening!C46)/(360*((INDEX(T1_Rente,10)-0.005+0.000005)-Berekening!C10)),1000000000000)) -> -1730609 | D56: =MIN(1000000000000,IF((INDEX(T1_Rente,10)-0.005+0.000005)>Berekening!D10,(Berekening!D45-(INDEX(T1_Rente,10)-0.005+0.000005)*Berekening!D46)/(360*((INDEX(T1_Rente,10)-0.005+0.000005)-Berekening!D10)),1000000000000)) -> -1762042 | E56: =MIN(1000000000000,IF((INDEX(T1_Rente,10)-0.005+0.000005)>Berekening!E10,(Berekening!E45-(INDEX(T1_Rente,10)-0.005+0.000005)*Berekening!E46)/(360*((INDEX(T1_Rente,10)-0.005+0.000005)-Berekening!E10)),1000000000000)) -> -353745.13 | F56: =MIN(1000000000000,IF((INDEX(T1_Rente,10)-0.005+0.000005)>Berekening!F10,(Berekening!F45-(INDEX(T1_Rente,10)-0.005+0.000005)*Berekening!F46)/(360*((INDEX(T1_Rente,10)-0.005+0.000005)-Berekening!F10)),1000000000000)) -> -2802514.7 | G56: =MIN(1000000000000,IF((INDEX(T1_Rente,10)-0.005+0.000005)>Berekening!G10,(Berekening!G45-(INDEX(T1_Rente,10)-0.005+0.000005)*Berekening!G46)/(360*((INDEX(T1_Rente,10)-0.005+0.000005)-Berekening!G10)),1000000000000)) -> 0 | H56: =MIN(1000000000000,IF((INDEX(T1_Rente,10)-0.005+0.000005)>Berekening!H10,(Berekening!H45-(INDEX(T1_Rente,10)-0.005+0.000005)*Berekening!H46)/(360*((INDEX(T1_Rente,10)-0.005+0.000005)-Berekening!H10)),1000000000000)) -> 0 | I56: =MIN(1000000000000,IF((INDEX(T1_Rente,10)-0.005+0.000005)>Berekening!I10,(Berekening!I45-(INDEX(T1_Rente,10)-0.005+0.000005)*Berekening!I46)/(360*((INDEX(T1_Rente,10)-0.005+0.000005)-Berekening!I10)),1000000000000)) -> 0 | J56: =MIN(1000000000000,IF((INDEX(T1_Rente,10)-0.005+0.000005)>Berekening!J10,(Berekening!J45-(INDEX(T1_Rente,10)-0.005+0.000005)*Berekening!J46)/(360*((INDEX(T1_Rente,10)-0.005+0.000005)-Berekening!J10)),1000000000000)) -> -1730609 | ... M56: =MIN(1000000000000,IF((INDEX(T1_Rente,10)-0.005+0.000005)>Berekening!M10,(Berekening!M45-(INDEX(T1_Rente,10)-0.005+0.000005)*Berekening!M46)/(360*((INDEX(T1_Rente,10)-0.005+0.000005)-Berekening!M10)),1000000000000)) -> -1730609
A57: Kolom 10: haalbaar bedrag (−1 = onmogelijk) | B57: € | C57: =IF(C55>C56,-1,IF(C54<C55-0.000000001,-1,IF(C54>C56,MAX(C55,C56-1),C54))) -> -1 | D57: =IF(D55>D56,-1,IF(D54<D55-0.000000001,-1,IF(D54>D56,MAX(D55,D56-1),D54))) -> -1 | E57: =IF(E55>E56,-1,IF(E54<E55-0.000000001,-1,IF(E54>E56,MAX(E55,E56-1),E54))) -> -1 | F57: =IF(F55>F56,-1,IF(F54<F55-0.000000001,-1,IF(F54>F56,MAX(F55,F56-1),F54))) -> -1 | G57: =IF(G55>G56,-1,IF(G54<G55-0.000000001,-1,IF(G54>G56,MAX(G55,G56-1),G54))) -> 0 | H57: =IF(H55>H56,-1,IF(H54<H55-0.000000001,-1,IF(H54>H56,MAX(H55,H56-1),H54))) -> 0 | I57: =IF(I55>I56,-1,IF(I54<I55-0.000000001,-1,IF(I54>I56,MAX(I55,I56-1),I54))) -> 0 | J57: =IF(J55>J56,-1,IF(J54<J55-0.000000001,-1,IF(J54>J56,MAX(J55,J56-1),J54))) -> -1 | ... M57: =IF(M55>M56,-1,IF(M54<M55-0.000000001,-1,IF(M54>M56,MAX(M55,M56-1),M54))) -> -1
